Workbook

Sheet README
B1: Desert Financial ALM Command Center: financial workbook
B2: Hypothetical concept built from public data. Not affiliated with or endorsed by Desert Financial Credit Union.
B4: Purpose | D4: Data contract for the ALM Command Center build prompt (section 6): every tab the app reads, with real public figures where they exist and a documented ALM model where they do not.
B5: As-of date | D5: June 30, 2026 (latest NCUA 5300 call report). Market data through Sept 29, 2026 (rate-drift chip).
B6: Units | D6: Dollars in thousands. Rates and ratios as decimals (5.75% = 0.0575). Dates as ISO text (YYYY-MM-DD). Long (tidy) tables: one row per period and item.
B7: Provenance | D7: public = NCUA call report, Treasury, FOMC, press releases; audited = DFCU annual reports; modeled = this workbook's ALM model or a documented derivation; hypothetical = illustrative targets, limits, plans and placeholders.
B8: Colors | D8: Blue numbers = hardcoded data or inputs. Black = formulas on the same sheet. Green = formulas that pull from another sheet. Yellow fill = live levers in meta (capital target, watch thresholds, NEV Test thresholds, MBL parameters) that drive limit status, NEV Test class and the MBL cap. Model assumptions in the assumptions tab document the Python model; changing them there does not rerun it.
B9: Model | D9: Monthly cash-flow ALM model in Python (model/ folder; run build_all.py then build_workbook.py). Constant balance sheet NII for 24 months; instantaneous NEV with a bootstrapped Treasury zero curve; 20 scenarios.
B10: Data Health | D10: The checks tab reruns the ten validation checks from the build prompt plus extra reconciliations with live formulas.
B12: Key results (live)
B13: Data status | C13: =checks!$D$74 -> Validated | D13: Validation result from the checks tab
B14: Total assets ($K) | C14: =summary!$C$39 -> 9887845 | D14: June 30, 2026 call report
B15: Net worth ratio | C15: =summary!$C$43 -> 0.12095821 | D15: Four-quarter-average method; reported 12.1%
B16: Loan-to-share | C16: =summary!$C$42 -> 0.59910569 | D16: Industry 82.9% aggregate, 69% median (Q2 2026)
B17: AOCI loss / net worth | C17: =summary!$C$45 -> 0.21848783 | D17: Before the Q3 2026 rate rise
B18: Base Year 1 NII ($K) | C18: =summary!$F$8 -> 327538.5 | D18: Constant balance sheet, rates flat at the June 30 curve; excludes giveback
B19: Year 1 NII change, +300bp | C19: =summary!$H$11 -> 0.02788835 | D19: Asset-sensitive in Year 1 (HELOCs at prime, cash); money market repricing and migration offset
B20: Year 1 NII change, -300bp | C20: =summary!$H$5 -> -0.11032574 | D20: Largest earnings risk is falling rates
B21: NEV ratio, base (internal) | C21: =summary!$O$8 -> 0.1717611 | D21: Includes non-maturity deposit franchise value
B22: NEV change, +300bp (internal) | C22: =summary!$P$11 -> -0.10680273
B23: NCUA NEV Test post-shock ratio | C23: =summary!$O$24 -> 0.040512636 | D23: Standardized share values (approximation); 4% = High threshold
B24: NCUA NEV Test class | C24: =summary!$C$60 -> Moderate | D24: Low > 7% and < 40%; High < 4% or > 65%
B25: Q3 2026 actual move: NEV change | C25: =summary!$P$20 -> -0.034791767 | D25: June 30 to Sept 29 curve (10-year +82bp); rate-drift estimate
B26: AFS fair value change since June 30 ($K) | C26: =summary!$C$61 -> -78226.457 | D26: Rate-drift estimate at the Sept 29, 2026 curve (flows through AOCI)
B27: AOCI loss / net worth after Q3 move | C27: =summary!$C$63 -> 0.28582991 | D27: Estimate; Q3 call report will confirm
B28: MBL cap utilization | C28: =summary!$C$55 -> 0.71693602 | D28: 1.75 x min(net worth, 7% of assets)
B29: Junior-lien home equity / loans | C29: =summary!$C$54 -> 0.39680795 | D29: Policy maximum 45% (hypothetical)
B31: Tab index
B32: Tab | C32: Contract | D32: What it holds
B33: summary | C33: extra | D33: Scenario results (NII, EaR, NEV), repricing gap summary, key metrics, liquidity survival: all formulas
B34: checks | C34: extra | D34: Data Health: the ten section 6 checks plus reconciliations to the call report
B35: meta | C35: R | D35: Settings: as-of date, units, NWR method, capital target, thresholds, disclaimer
B36: balance_sheet | C36: R | D36: Audited year-ends 2020-2025, March 31, 2026 (partial call report), June 30, 2026 detail with yields, WAL, duration, convexity
B37: income_statement | C37: R | D37: Audited FY2020-FY2025, H1 2026 call report, quarterly 2025-2026 (modeled allocation); Member Giveback as its own category
B38: income_statement_totals | C38: extra | D38: Reported totals used by the income identity checks
B39: loans | C39: R | D39: 14 products at June 30, 2026: balances and counts tie to the call report; yields, prepayment, credit and behavior modeled
B40: deposits | C40: R | D40: 13 products and tiers: betas, lags, decay, insured share, certificate rollover
B41: cert_maturities | C41: O | D41: Certificate and IRA certificate maturities by month (60 months)
B42: investments | C42: R | D42: Security groups: book, market, yield, duration, convexity, WAL (AFS ties to call report)
B43: securities_detail | C43: extra | D43: Instrument-level securities with fair values in +300, -300 and Q3-actual
... B77: notes | C77: extra | D77: Methods, inferences, transcription adjustments and known limitations
B79: Important caveats
B80: - | D80: Balance sheet and income totals are public or audited. Product splits, yields, deposit tiers, security composition, behavior assumptions, fair values of HTM securities, loans and deposits, and all forward-looking figures are modeled or hypothetical.
B81: - | D81: The Member Giveback Bonus is inferred to be recorded within dividends in the quarter it is paid (Q1). If DFCU accrues it at year-end instead, the modeled regular deposit cost in H1 2026 would be higher and NII lower.
B82: - | D82: The NCUA NEV Test uses standardized non-maturity share values approximated here as a 1% premium at base and 5% after +300bp. Confirm against NCUA's current NEV Supervisory Test documentation before relying on the class.
B83: - | D83: Treasury curves before 2025 (except March 31, 2025) are approximate quarter-end levels compiled without live access; 2026 curves are from the Treasury daily par yield curve.
B84: - | D84: Policy limits, the strategic plan, initiatives, ALCO decisions, peer medians and liquidity lines are illustrative and labeled hypothetical.

Sheet summary
A1: Summary: scenario results, repricing gap, key metrics and liquidity survival (live formulas)
A2: All cells below are formulas over the data tabs. Green = cross-sheet links; black = same-sheet formulas. $ thousands; ratios as decimals.
A3: A. Scenario results (NII: 24-month constant balance sheet; NEV: instantaneous)
A4: scenario_key | B4: scenario_label | C4: type | D4: sort_order | E4: nev_applicable | F4: nii_y1 | G4: nii_y2 | H4: ear_y1 | I4: ear_y2 | J4: net_income_y1 | K4: assets_fv | L4: liabilities_fv | M4: off_balance_fv | N4: nev | O4: nev_ratio | P4: nev_sensitivity
A5: shock_m300 | B5: -300bp shock | C5: shock | D5: 1 | E5: y | F5: =SUMIFS(nii_simulation!$E:$E,nii_simulation!$A:$A,$A5,nii_simulation!$B:$B,"<=12") -> 291402.57 | G5: =SUMIFS(nii_simulation!$E:$E,nii_simulation!$A:$A,$A5,nii_simulation!$B:$B,">12") -> 290452.06 | H5: =F5/F$8-1 -> -0.11032574 | I5: =G5/G$8-1 -> -0.14289624 | J5: =SUMIFS(nii_simulation!$G:$G,nii_simulation!$A:$A,$A5,nii_simulation!$B:$B,"<=12") -> 110261.19 | K5: =IF($E5="y",SUMIFS(nev!$E:$E,nev!$A:$A,$A5,nev!$C:$C,"asset"),"") -> 10416466 | L5: =IF($E5="y",SUMIFS(nev!$E:$E,nev!$A:$A,$A5,nev!$C:$C,"liability"),"") -> 8690955.6 | M5: =IF($E5="y",SUMIFS(nev!$E:$E,nev!$A:$A,$A5,nev!$C:$C,"off_balance"),"") -> 2700 | N5: =IF($E5="y",K5-L5+M5,"") -> 1728210.7 | O5: =IF($E5="y",N5/K5,"") -> 0.16591142 | P5: =IF($E5="y",N5/N$8-1,"") -> 0.044138066
A6: shock_m200 | B6: -200bp shock | C6: shock | D6: 2 | E6: y | F6: =SUMIFS(nii_simulation!$E:$E,nii_simulation!$A:$A,$A6,nii_simulation!$B:$B,"<=12") -> 304033.39 | G6: =SUMIFS(nii_simulation!$E:$E,nii_simulation!$A:$A,$A6,nii_simulation!$B:$B,">12") -> 309019.44 | H6: =F6/F$8-1 -> -0.071762892 | I6: =G6/G$8-1 -> -0.088105173 | J6: =SUMIFS(nii_simulation!$G:$G,nii_simulation!$A:$A,$A6,nii_simulation!$B:$B,"<=12") -> 121272.01 | K6: =IF($E6="y",SUMIFS(nev!$E:$E,nev!$A:$A,$A6,nev!$C:$C,"asset"),"") -> 10151662 | L6: =IF($E6="y",SUMIFS(nev!$E:$E,nev!$A:$A,$A6,nev!$C:$C,"liability"),"") -> 8429216.3 | M6: =IF($E6="y",SUMIFS(nev!$E:$E,nev!$A:$A,$A6,nev!$C:$C,"off_balance"),"") -> 1800 | N6: =IF($E6="y",K6-L6+M6,"") -> 1724245.8 | O6: =IF($E6="y",N6/K6,"") -> 0.16984862 | P6: =IF($E6="y",N6/N$8-1,"") -> 0.041742625
A7: shock_m100 | B7: -100bp shock | C7: shock | D7: 3 | E7: y | F7: =SUMIFS(nii_simulation!$E:$E,nii_simulation!$A:$A,$A7,nii_simulation!$B:$B,"<=12") -> 316744.65 | G7: =SUMIFS(nii_simulation!$E:$E,nii_simulation!$A:$A,$A7,nii_simulation!$B:$B,">12") -> 325888.47 | H7: =F7/F$8-1 -> -0.032954427 | I7: =G7/G$8-1 -> -0.03832585 | J7: =SUMIFS(nii_simulation!$G:$G,nii_simulation!$A:$A,$A7,nii_simulation!$B:$B,"<=12") -> 132363.27 | K7: =IF($E7="y",SUMIFS(nev!$E:$E,nev!$A:$A,$A7,nev!$C:$C,"asset"),"") -> 9896730.2 | L7: =IF($E7="y",SUMIFS(nev!$E:$E,nev!$A:$A,$A7,nev!$C:$C,"liability"),"") -> 8192917.4 | M7: =IF($E7="y",SUMIFS(nev!$E:$E,nev!$A:$A,$A7,nev!$C:$C,"off_balance"),"") -> 900 | N7: =IF($E7="y",K7-L7+M7,"") -> 1704712.8 | O7: =IF($E7="y",N7/K7,"") -> 0.1722501 | P7: =IF($E7="y",N7/N$8-1,"") -> 0.029941277
A8: base | B8: Base (flat rates) | C8: shock | D8: 4 | E8: y | F8: =SUMIFS(nii_simulation!$E:$E,nii_simulation!$A:$A,$A8,nii_simulation!$B:$B,"<=12") -> 327538.5 | G8: =SUMIFS(nii_simulation!$E:$E,nii_simulation!$A:$A,$A8,nii_simulation!$B:$B,">12") -> 338876.19 | H8: =F8/F$8-1 -> 0 | I8: =G8/G$8-1 -> 0 | J8: =SUMIFS(nii_simulation!$G:$G,nii_simulation!$A:$A,$A8,nii_simulation!$B:$B,"<=12") -> 141537.11 | K8: =IF($E8="y",SUMIFS(nev!$E:$E,nev!$A:$A,$A8,nev!$C:$C,"asset"),"") -> 9636380.4 | L8: =IF($E8="y",SUMIFS(nev!$E:$E,nev!$A:$A,$A8,nev!$C:$C,"liability"),"") -> 7981225.1 | M8: =IF($E8="y",SUMIFS(nev!$E:$E,nev!$A:$A,$A8,nev!$C:$C,"off_balance"),"") -> 0 | N8: =IF($E8="y",K8-L8+M8,"") -> 1655155.3 | O8: =IF($E8="y",N8/K8,"") -> 0.1717611 | P8: =IF($E8="y",N8/N$8-1,"") -> 0
A9: shock_p100 | B9: +100bp shock | C9: shock | D9: 5 | E9: y | F9: =SUMIFS(nii_simulation!$E:$E,nii_simulation!$A:$A,$A9,nii_simulation!$B:$B,"<=12") -> 332046.54 | G9: =SUMIFS(nii_simulation!$E:$E,nii_simulation!$A:$A,$A9,nii_simulation!$B:$B,">12") -> 342032.37 | H9: =F9/F$8-1 -> 0.01376341 | I9: =G9/G$8-1 -> 0.0093136604 | J9: =SUMIFS(nii_simulation!$G:$G,nii_simulation!$A:$A,$A9,nii_simulation!$B:$B,"<=12") -> 144425.16 | K9: =IF($E9="y",SUMIFS(nev!$E:$E,nev!$A:$A,$A9,nev!$C:$C,"asset"),"") -> 9392467.8 | L9: =IF($E9="y",SUMIFS(nev!$E:$E,nev!$A:$A,$A9,nev!$C:$C,"liability"),"") -> 7795467.9 | M9: =IF($E9="y",SUMIFS(nev!$E:$E,nev!$A:$A,$A9,nev!$C:$C,"off_balance"),"") -> -1440 | N9: =IF($E9="y",K9-L9+M9,"") -> 1595559.9 | O9: =IF($E9="y",N9/K9,"") -> 0.16987654 | P9: =IF($E9="y",N9/N$8-1,"") -> -0.036005947
A10: shock_p200 | B10: +200bp shock | C10: shock | D10: 6 | E10: y | F10: =SUMIFS(nii_simulation!$E:$E,nii_simulation!$A:$A,$A10,nii_simulation!$B:$B,"<=12") -> 334873.41 | G10: =SUMIFS(nii_simulation!$E:$E,nii_simulation!$A:$A,$A10,nii_simulation!$B:$B,">12") -> 341860.89 | H10: =F10/F$8-1 -> 0.022394068 | I10: =G10/G$8-1 -> 0.0088076496 | J10: =SUMIFS(nii_simulation!$G:$G,nii_simulation!$A:$A,$A10,nii_simulation!$B:$B,"<=12") -> 145632.03 | K10: =IF($E10="y",SUMIFS(nev!$E:$E,nev!$A:$A,$A10,nev!$C:$C,"asset"),"") -> 9160585.4 | L10: =IF($E10="y",SUMIFS(nev!$E:$E,nev!$A:$A,$A10,nev!$C:$C,"liability"),"") -> 7624316.8 | M10: =IF($E10="y",SUMIFS(nev!$E:$E,nev!$A:$A,$A10,nev!$C:$C,"off_balance"),"") -> -2880 | N10: =IF($E10="y",K10-L10+M10,"") -> 1533388.7 | O10: =IF($E10="y",N10/K10,"") -> 0.16738981 | P10: =IF($E10="y",N10/N$8-1,"") -> -0.073568106
A11: shock_p300 | B11: +300bp shock | C11: shock | D11: 7 | E11: y | F11: =SUMIFS(nii_simulation!$E:$E,nii_simulation!$A:$A,$A11,nii_simulation!$B:$B,"<=12") -> 336673 | G11: =SUMIFS(nii_simulation!$E:$E,nii_simulation!$A:$A,$A11,nii_simulation!$B:$B,">12") -> 339925.47 | H11: =F11/F$8-1 -> 0.02788835 | I11: =G11/G$8-1 -> 0.0030963551 | J11: =SUMIFS(nii_simulation!$G:$G,nii_simulation!$A:$A,$A11,nii_simulation!$B:$B,"<=12") -> 146621.62 | K11: =IF($E11="y",SUMIFS(nev!$E:$E,nev!$A:$A,$A11,nev!$C:$C,"asset"),"") -> 8948733.3 | L11: =IF($E11="y",SUMIFS(nev!$E:$E,nev!$A:$A,$A11,nev!$C:$C,"liability"),"") -> 7466033.1 | M11: =IF($E11="y",SUMIFS(nev!$E:$E,nev!$A:$A,$A11,nev!$C:$C,"off_balance"),"") -> -4320 | N11: =IF($E11="y",K11-L11+M11,"") -> 1478380.2 | O11: =IF($E11="y",N11/K11,"") -> 0.16520553 | P11: =IF($E11="y",N11/N$8-1,"") -> -0.10680273
A12: shock_p400 | B12: +400bp shock | C12: shock | D12: 8 | E12: y | F12: =SUMIFS(nii_simulation!$E:$E,nii_simulation!$A:$A,$A12,nii_simulation!$B:$B,"<=12") -> 337181.83 | G12: =SUMIFS(nii_simulation!$E:$E,nii_simulation!$A:$A,$A12,nii_simulation!$B:$B,">12") -> 335695.32 | H12: =F12/F$8-1 -> 0.029441821 | I12: =G12/G$8-1 -> -0.0093865261 | J12: =SUMIFS(nii_simulation!$G:$G,nii_simulation!$A:$A,$A12,nii_simulation!$B:$B,"<=12") -> 147130.44 | K12: =IF($E12="y",SUMIFS(nev!$E:$E,nev!$A:$A,$A12,nev!$C:$C,"asset"),"") -> 8752158.5 | L12: =IF($E12="y",SUMIFS(nev!$E:$E,nev!$A:$A,$A12,nev!$C:$C,"liability"),"") -> 7319145.7 | M12: =IF($E12="y",SUMIFS(nev!$E:$E,nev!$A:$A,$A12,nev!$C:$C,"off_balance"),"") -> -5760 | N12: =IF($E12="y",K12-L12+M12,"") -> 1427252.8 | O12: =IF($E12="y",N12/K12,"") -> 0.16307438 | P12: =IF($E12="y",N12/N$8-1,"") -> -0.13769251
A13: ramp_m200 | B13: -200bp ramp (12 mo) | C13: ramp | D13: 9 | E13: n | F13: =SUMIFS(nii_simulation!$E:$E,nii_simulation!$A:$A,$A13,nii_simulation!$B:$B,"<=12") -> 314725.68 | G13: =SUMIFS(nii_simulation!$E:$E,nii_simulation!$A:$A,$A13,nii_simulation!$B:$B,">12") -> 314702.03 | H13: =F13/F$8-1 -> -0.039118513 | I13: =G13/G$8-1 -> -0.07133626 | J13: =SUMIFS(nii_simulation!$G:$G,nii_simulation!$A:$A,$A13,nii_simulation!$B:$B,"<=12") -> 130209.3 | K13: =IF($E13="y",SUMIFS(nev!$E:$E,nev!$A:$A,$A13,nev!$C:$C,"asset"),"") | L13: =IF($E13="y",SUMIFS(nev!$E:$E,nev!$A:$A,$A13,nev!$C:$C,"liability"),"") | M13: =IF($E13="y",SUMIFS(nev!$E:$E,nev!$A:$A,$A13,nev!$C:$C,"off_balance"),"") | N13: =IF($E13="y",K13-L13+M13,"") | O13: =IF($E13="y",N13/K13,"") | P13: =IF($E13="y",N13/N$8-1,"")
A14: ramp_m100 | B14: -100bp ramp (12 mo) | C14: ramp | D14: 10 | E14: n | F14: =SUMIFS(nii_simulation!$E:$E,nii_simulation!$A:$A,$A14,nii_simulation!$B:$B,"<=12") -> 321189.64 | G14: =SUMIFS(nii_simulation!$E:$E,nii_simulation!$A:$A,$A14,nii_simulation!$B:$B,">12") -> 327956.04 | H14: =F14/F$8-1 -> -0.019383529 | I14: =G14/G$8-1 -> -0.032224598 | J14: =SUMIFS(nii_simulation!$G:$G,nii_simulation!$A:$A,$A14,nii_simulation!$B:$B,"<=12") -> 135930.76 | K14: =IF($E14="y",SUMIFS(nev!$E:$E,nev!$A:$A,$A14,nev!$C:$C,"asset"),"") | L14: =IF($E14="y",SUMIFS(nev!$E:$E,nev!$A:$A,$A14,nev!$C:$C,"liability"),"") | M14: =IF($E14="y",SUMIFS(nev!$E:$E,nev!$A:$A,$A14,nev!$C:$C,"off_balance"),"") | N14: =IF($E14="y",K14-L14+M14,"") | O14: =IF($E14="y",N14/K14,"") | P14: =IF($E14="y",N14/N$8-1,"")
A15: ramp_p100 | B15: +100bp ramp (12 mo) | C15: ramp | D15: 11 | E15: n | F15: =SUMIFS(nii_simulation!$E:$E,nii_simulation!$A:$A,$A15,nii_simulation!$B:$B,"<=12") -> 330947.12 | G15: =SUMIFS(nii_simulation!$E:$E,nii_simulation!$A:$A,$A15,nii_simulation!$B:$B,">12") -> 340381.65 | H15: =F15/F$8-1 -> 0.010406796 | I15: =G15/G$8-1 -> 0.0044425097 | J15: =SUMIFS(nii_simulation!$G:$G,nii_simulation!$A:$A,$A15,nii_simulation!$B:$B,"<=12") -> 144203.24 | K15: =IF($E15="y",SUMIFS(nev!$E:$E,nev!$A:$A,$A15,nev!$C:$C,"asset"),"") | L15: =IF($E15="y",SUMIFS(nev!$E:$E,nev!$A:$A,$A15,nev!$C:$C,"liability"),"") | M15: =IF($E15="y",SUMIFS(nev!$E:$E,nev!$A:$A,$A15,nev!$C:$C,"off_balance"),"") | N15: =IF($E15="y",K15-L15+M15,"") | O15: =IF($E15="y",N15/K15,"") | P15: =IF($E15="y",N15/N$8-1,"")
A16: ramp_p200 | B16: +200bp ramp (12 mo) | C16: ramp | D16: 12 | E16: n | F16: =SUMIFS(nii_simulation!$E:$E,nii_simulation!$A:$A,$A16,nii_simulation!$B:$B,"<=12") -> 333715.69 | G16: =SUMIFS(nii_simulation!$E:$E,nii_simulation!$A:$A,$A16,nii_simulation!$B:$B,">12") -> 338983.83 | H16: =F16/F$8-1 -> 0.018859432 | I16: =G16/G$8-1 -> 0.00031763386 | J16: =SUMIFS(nii_simulation!$G:$G,nii_simulation!$A:$A,$A16,nii_simulation!$B:$B,"<=12") -> 146229.31 | K16: =IF($E16="y",SUMIFS(nev!$E:$E,nev!$A:$A,$A16,nev!$C:$C,"asset"),"") | L16: =IF($E16="y",SUMIFS(nev!$E:$E,nev!$A:$A,$A16,nev!$C:$C,"liability"),"") | M16: =IF($E16="y",SUMIFS(nev!$E:$E,nev!$A:$A,$A16,nev!$C:$C,"off_balance"),"") | N16: =IF($E16="y",K16-L16+M16,"") | O16: =IF($E16="y",N16/K16,"") | P16: =IF($E16="y",N16/N$8-1,"")
... A23: recession_cuts | B23: Recession with cuts | C23: narrative | D23: 19 | E23: n | F23: =SUMIFS(nii_simulation!$E:$E,nii_simulation!$A:$A,$A23,nii_simulation!$B:$B,"<=12") -> 315228.97 | G23: =SUMIFS(nii_simulation!$E:$E,nii_simulation!$A:$A,$A23,nii_simulation!$B:$B,">12") -> 319005 | H23: =F23/F$8-1 -> -0.037581928 | I23: =G23/G$8-1 -> -0.058638483 | J23: =SUMIFS(nii_simulation!$G:$G,nii_simulation!$A:$A,$A23,nii_simulation!$B:$B,"<=12") -> 95518.932 | K23: =IF($E23="y",SUMIFS(nev!$E:$E,nev!$A:$A,$A23,nev!$C:$C,"asset"),"") | L23: =IF($E23="y",SUMIFS(nev!$E:$E,nev!$A:$A,$A23,nev!$C:$C,"liability"),"") | M23: =IF($E23="y",SUMIFS(nev!$E:$E,nev!$A:$A,$A23,nev!$C:$C,"off_balance"),"") | N23: =IF($E23="y",K23-L23+M23,"") | O23: =IF($E23="y",N23/K23,"") | P23: =IF($E23="y",N23/N$8-1,"")
A24: ncua_nev_test | B24: NCUA NEV Test (+300, standardized NMS) | C24: supervisory | D24: 20 | E24: y | F24: =SUMIFS(nii_simulation!$E:$E,nii_simulation!$A:$A,$A24,nii_simulation!$B:$B,"<=12") -> 336673 | G24: =SUMIFS(nii_simulation!$E:$E,nii_simulation!$A:$A,$A24,nii_simulation!$B:$B,">12") -> 339925.47 | H24: =F24/F$8-1 -> 0.02788835 | I24: =G24/G$8-1 -> 0.0030963551 | J24: =SUMIFS(nii_simulation!$G:$G,nii_simulation!$A:$A,$A24,nii_simulation!$B:$B,"<=12") -> 146621.62 | K24: =IF($E24="y",SUMIFS(nev!$E:$E,nev!$A:$A,$A24,nev!$C:$C,"asset"),"") -> 8948733.3 | L24: =IF($E24="y",SUMIFS(nev!$E:$E,nev!$A:$A,$A24,nev!$C:$C,"liability"),"") -> 8581876.5 | M24: =IF($E24="y",SUMIFS(nev!$E:$E,nev!$A:$A,$A24,nev!$C:$C,"off_balance"),"") -> -4320 | N24: =IF($E24="y",K24-L24+M24,"") -> 362536.77 | O24: =IF($E24="y",N24/K24,"") -> 0.040512636 | P24: =N24/SUMIFS(nev_test!$C:$C,nev_test!$A:$A,meta!$B$3,nev_test!$B:$B,"ncua_test")-1 -> -0.50337472
A26: B. Repricing gap, June 30, 2026 (NMD beta-weighted hybrid)
A27: bucket | B27: assets | C27: liabilities | D27: equity | E27: gap | F27: cumulative_gap | G27: cumulative_gap_pct_assets
A28: 0_3m | B28: =SUMIFS(repricing_gap!$D:$D,repricing_gap!$A:$A,meta!$B$3,repricing_gap!$B:$B,$A28,repricing_gap!$C:$C,"asset") -> 2751903.5 | C28: =SUMIFS(repricing_gap!$D:$D,repricing_gap!$A:$A,meta!$B$3,repricing_gap!$B:$B,$A28,repricing_gap!$C:$C,"liability") -> 2230363.4 | D28: =SUMIFS(repricing_gap!$D:$D,repricing_gap!$A:$A,meta!$B$3,repricing_gap!$B:$B,$A28,repricing_gap!$C:$C,"equity") -> 0 | E28: =B28-C28-D28 -> 521540.08 | F28: =E28 -> 521540.08 | G28: =F28/SUM($B$28:$B$34) -> 0.052745576
A29: 3_12m | B29: =SUMIFS(repricing_gap!$D:$D,repricing_gap!$A:$A,meta!$B$3,repricing_gap!$B:$B,$A29,repricing_gap!$C:$C,"asset") -> 847849.95 | C29: =SUMIFS(repricing_gap!$D:$D,repricing_gap!$A:$A,meta!$B$3,repricing_gap!$B:$B,$A29,repricing_gap!$C:$C,"liability") -> 1853615.7 | D29: =SUMIFS(repricing_gap!$D:$D,repricing_gap!$A:$A,meta!$B$3,repricing_gap!$B:$B,$A29,repricing_gap!$C:$C,"equity") -> 0 | E29: =B29-C29-D29 -> -1005765.8 | F29: =F28+E29 -> -484225.72 | G29: =F29/SUM($B$28:$B$34) -> -0.048971816
A30: 1_3y | B30: =SUMIFS(repricing_gap!$D:$D,repricing_gap!$A:$A,meta!$B$3,repricing_gap!$B:$B,$A30,repricing_gap!$C:$C,"asset") -> 2132570.2 | C30: =SUMIFS(repricing_gap!$D:$D,repricing_gap!$A:$A,meta!$B$3,repricing_gap!$B:$B,$A30,repricing_gap!$C:$C,"liability") -> 1753396.9 | D30: =SUMIFS(repricing_gap!$D:$D,repricing_gap!$A:$A,meta!$B$3,repricing_gap!$B:$B,$A30,repricing_gap!$C:$C,"equity") -> 0 | E30: =B30-C30-D30 -> 379173.29 | F30: =F29+E30 -> -105052.44 | G30: =F30/SUM($B$28:$B$34) -> -0.010624402
A31: 3_5y | B31: =SUMIFS(repricing_gap!$D:$D,repricing_gap!$A:$A,meta!$B$3,repricing_gap!$B:$B,$A31,repricing_gap!$C:$C,"asset") -> 1542013.5 | C31: =SUMIFS(repricing_gap!$D:$D,repricing_gap!$A:$A,meta!$B$3,repricing_gap!$B:$B,$A31,repricing_gap!$C:$C,"liability") -> 984960.76 | D31: =SUMIFS(repricing_gap!$D:$D,repricing_gap!$A:$A,meta!$B$3,repricing_gap!$B:$B,$A31,repricing_gap!$C:$C,"equity") -> 0 | E31: =B31-C31-D31 -> 557052.76 | F31: =F30+E31 -> 452000.33 | G31: =F31/SUM($B$28:$B$34) -> 0.045712724
A32: 5_10y | B32: =SUMIFS(repricing_gap!$D:$D,repricing_gap!$A:$A,meta!$B$3,repricing_gap!$B:$B,$A32,repricing_gap!$C:$C,"asset") -> 1122748 | C32: =SUMIFS(repricing_gap!$D:$D,repricing_gap!$A:$A,meta!$B$3,repricing_gap!$B:$B,$A32,repricing_gap!$C:$C,"liability") -> 1190866.1 | D32: =SUMIFS(repricing_gap!$D:$D,repricing_gap!$A:$A,meta!$B$3,repricing_gap!$B:$B,$A32,repricing_gap!$C:$C,"equity") -> 0 | E32: =B32-C32-D32 -> -68118.112 | F32: =F31+E32 -> 383882.22 | G32: =F32/SUM($B$28:$B$34) -> 0.038823648
A33: 10y_plus | B33: =SUMIFS(repricing_gap!$D:$D,repricing_gap!$A:$A,meta!$B$3,repricing_gap!$B:$B,$A33,repricing_gap!$C:$C,"asset") -> 871798.21 | C33: =SUMIFS(repricing_gap!$D:$D,repricing_gap!$A:$A,meta!$B$3,repricing_gap!$B:$B,$A33,repricing_gap!$C:$C,"liability") -> 842397.35 | D33: =SUMIFS(repricing_gap!$D:$D,repricing_gap!$A:$A,meta!$B$3,repricing_gap!$B:$B,$A33,repricing_gap!$C:$C,"equity") -> 0 | E33: =B33-C33-D33 -> 29400.862 | F33: =F32+E33 -> 413283.08 | G33: =F33/SUM($B$28:$B$34) -> 0.041797083
A34: nonrate | B34: =SUMIFS(repricing_gap!$D:$D,repricing_gap!$A:$A,meta!$B$3,repricing_gap!$B:$B,$A34,repricing_gap!$C:$C,"asset") -> 618961.62 | C34: =SUMIFS(repricing_gap!$D:$D,repricing_gap!$A:$A,meta!$B$3,repricing_gap!$B:$B,$A34,repricing_gap!$C:$C,"liability") -> 124418.2 | D34: =SUMIFS(repricing_gap!$D:$D,repricing_gap!$A:$A,meta!$B$3,repricing_gap!$B:$B,$A34,repricing_gap!$C:$C,"equity") -> 907826.51 | E34: =B34-C34-D34 -> -413283.08 | F34: =F33+E34 -> -1.1070399e-05 | G34: =F34/SUM($B$28:$B$34) -> -1.1195967e-12
A35: total | B35: =SUM(B28:B34) -> 9887845 | C35: =SUM(C28:C34) -> 8980018.5 | D35: =SUM(D28:D34) -> 907826.51 | E35: =SUM(E28:E34) -> -1.1070399e-05
A37: C. Key metrics, June 30, 2026
A38: metric_key | B38: label | C38: value | D38: formula / source
A39: total_assets | B39: Total assets ($K) | C39: =history!$B$24 -> 9887845 | D39: history
A40: loans | B40: Loans ($K) | C40: =history!$C$24 -> 5305440.5 | D40: history
A41: shares | B41: Shares ($K) | C41: =history!$D$24 -> 8855600.3 | D41: history
A42: lts | B42: Loan-to-share | C42: =history!$O$24 -> 0.59910569 | D42: history
A43: nwr | B43: Net worth ratio (4-quarter average method) | C43: =history!$S$24 -> 0.12095821 | D43: history
A44: nwr_quarter_end | B44: Net worth ratio (quarter-end assets) | C44: =history!$U$24/history!$B$24 -> 0.11748041 | D44: history
A45: aoci_pct_nw | B45: AOCI loss as % of net worth | C45: =-history!$R$24/history!$U$24 -> 0.21848783 | D45: history
A46: roa | B46: ROA, year to date (annualized) | C46: =history!$J$24 -> 0.011233332 | D46: history
A47: pre_giveback_roa | B47: Pre-giveback ROA, YTD | C47: =history!$W$24 -> 0.01451493 | D47: history
A48: nim | B48: NIM, YTD (ex-giveback) | C48: =history!$K$24 -> 0.031919747 | D48: history
A49: efficiency | B49: Efficiency ratio, YTD | C49: =history!$L$24 -> 0.65184056 | D49: history
A50: delinq_60 | B50: Delinquency (60+) | C50: =history!$M$24 -> 0.0046588915 | D50: history
A51: nco | B51: Net charge-offs, YTD (annualized) | C51: =history!$N$24 -> 0.0036269851 | D51: history
A52: cost_of_funds | B52: Cost of funds, YTD | C52: =history!$P$24 -> 0.015071626 | D52: history
A53: liquidity_ratio | B53: On-balance-sheet liquidity / shares | C53: =(SUMIFS(balance_sheet!$E:$E,balance_sheet!$A:$A,meta!$B$3,balance_sheet!$C:$C,"cash")+SUMIFS(investments!$E:$E,investments!$A:$A,meta!$B$3))/history!$D$24 -> 0.4358791 | D53: balance_sheet, investments
A54: he_concentration | B54: Junior-lien home equity / loans | C54: =(SUMIFS(loans!$D:$D,loans!$B:$B,"heloc")+SUMIFS(loans!$D:$D,loans!$B:$B,"he_fixed"))/SUM(loans!$D:$D) -> 0.39680795 | D54: loans
A55: mbl_utilization | B55: MBL cap utilization | C55: =capital!$I$24/capital!$J$24 -> 0.71693602 | D55: capital
A56: borrowings_to_assets | B56: Borrowings / assets | C56: =SUMIFS(balance_sheet!$E:$E,balance_sheet!$A:$A,meta!$B$3,balance_sheet!$C:$C,"borrowings")/history!$B$24 -> 0 | D56: balance_sheet
A57: brokered_to_shares | B57: Brokered deposits / shares | C57: =0 -> 0 | D57: none outstanding (assumed)
A58: uninsured_to_shares | B58: Uninsured shares / shares (estimate) | C58: =SUMPRODUCT(deposits!$E$2:$E$100,1-deposits!$L$2:$L$100)/SUM(deposits!$E$2:$E$100) -> 0.086203109 | D58: deposits
A59: nev_test_internal | B59: NEV Test class, internal method | C59: =INDEX(nev_test!$K$2:$K$100,MATCH(meta!$B$3&"|internal",nev_test!$L$2:$L$100,0)) -> Low | D59: nev_test
A60: nev_test_ncua | B60: NEV Test class, NCUA standardized method | C60: =INDEX(nev_test!$K$2:$K$100,MATCH(meta!$B$3&"|ncua_test",nev_test!$L$2:$L$100,0)) -> Moderate | D60: nev_test
A61: afs_drift_q3 | B61: AFS fair value change, June 30 to Sept 29 curve ($K) | C61: =SUMIFS(securities_detail!$Q:$Q,securities_detail!$E:$E,"afs")-SUMIFS(securities_detail!$G:$G,securities_detail!$E:$E,"afs") -> -78226.457 | D61: securities_detail (rate-drift estimate)
A62: htm_drift_q3 | B62: HTM fair value change, June 30 to Sept 29 curve ($K) | C62: =SUMIFS(securities_detail!$Q:$Q,securities_detail!$E:$E,"htm")-SUMIFS(securities_detail!$G:$G,securities_detail!$E:$E,"htm") -> -47207.662 | D62: securities_detail (economic view)
A63: aoci_pct_nw_now | B63: AOCI loss / net worth after the Q3 move (estimate) | C63: =-(history!$R$24+C61)/history!$U$24 -> 0.28582991 | D63: history + AFS drift
A64: duration_of_equity | B64: Duration of equity, base (years) | C64: =(SUMPRODUCT((nev!$A$2:$A$1000="base")*(nev!$C$2:$C$1000="asset")*nev!$E$2:$E$1000*nev!$F$2:$F$1000)-SUMPRODUCT((nev!$A$2:$A$1000="base")*(nev!$C$2:$C$1000="liability")*nev!$E$2:$E$1000*nev!$F$2:$F$1000))/N8 -> 3.1891477 | D64: nev
A66: D. Liquidity stress: available liquidity vs. cumulative stressed outflows
A67: scenario_key | B67: horizon_days | C67: outflows | D67: on_balance_available | E67: contingent_available | F67: total_available | G67: surplus
A68: liq_idiosyncratic | B68: 7 | C68: =SUMIFS(liquidity_stress!$J:$J,liquidity_stress!$A:$A,$A68,liquidity_stress!$B:$B,"insured_retail_nmd",liquidity_stress!$C:$C,$B68)+SUMIFS(liquidity_stress!$J:$J,liquidity_stress!$A:$A,$A68,liquidity_stress!$B:$B,"uninsured_deposits",liquidity_stress!$C:$C,$B68)+SUMIFS(liquidity_stress!$J:$J,liquidity_stress!$A:$A,$A68,liquidity_stress!$B:$B,"business_deposits",liquidity_stress!$C:$C,$B68)+SUMIFS(liquidity_stress!$J:$J,liquidity_stress!$A:$A,$A68,liquidity_stress!$B:$B,"money_market_high_balance",liquidity_stress!$C:$C,$B68)+SUMIFS(liquidity_stress!$J:$J,liquidity_stress!$A:$A,$A68,liquidity_stress!$B:$B,"certificates_maturing",liquidity_stress!$C:$C,$B68)+SUMIFS(liquidity_stress!$J:$J,liquidity_stress!$A:$A,$A68,liquidity_stress!$B:$B,"heloc_line_draws",liquidity_stress!$C:$C,$B68)+SUMIFS(liquidity_stress!$J:$J,liquidity_stress!$A:$A,$A68,liquidity_stress!$B:$B,"other_commitment_draws",liquidity_stress!$C:$C,$B68) -> 218994.28 | D68: =SUMIFS(liquidity_sources!$K:$K,liquidity_sources!$G:$G,"n",liquidity_sources!$H:$H,"<="&$B68)-SUMIFS(liquidity_stress!$D:$D,liquidity_stress!$A:$A,$A68,liquidity_stress!$B:$B,"securities_value_haircut",liquidity_stress!$C:$C,$B68)*SUMIFS(liquidity_sources!$D:$D,liquidity_sources!$B:$B,"afs_securities") -> 2525265.3 | E68: =SUMIFS(liquidity_sources!$K:$K,liquidity_sources!$G:$G,"y",liquidity_sources!$H:$H,"<="&$B68)*(1-SUMIFS(liquidity_stress!$D:$D,liquidity_stress!$A:$A,$A68,liquidity_stress!$B:$B,"contingent_source_availability",liquidity_stress!$C:$C,$B68)) -> 3337207.8 | F68: =D68+E68 -> 5862473.2 | G68: =F68-C68 -> 5643478.9
A69: liq_idiosyncratic | B69: 30 | C69: =SUMIFS(liquidity_stress!$J:$J,liquidity_stress!$A:$A,$A69,liquidity_stress!$B:$B,"insured_retail_nmd",liquidity_stress!$C:$C,$B69)+SUMIFS(liquidity_stress!$J:$J,liquidity_stress!$A:$A,$A69,liquidity_stress!$B:$B,"uninsured_deposits",liquidity_stress!$C:$C,$B69)+SUMIFS(liquidity_stress!$J:$J,liquidity_stress!$A:$A,$A69,liquidity_stress!$B:$B,"business_deposits",liquidity_stress!$C:$C,$B69)+SUMIFS(liquidity_stress!$J:$J,liquidity_stress!$A:$A,$A69,liquidity_stress!$B:$B,"money_market_high_balance",liquidity_stress!$C:$C,$B69)+SUMIFS(liquidity_stress!$J:$J,liquidity_stress!$A:$A,$A69,liquidity_stress!$B:$B,"certificates_maturing",liquidity_stress!$C:$C,$B69)+SUMIFS(liquidity_stress!$J:$J,liquidity_stress!$A:$A,$A69,liquidity_stress!$B:$B,"heloc_line_draws",liquidity_stress!$C:$C,$B69)+SUMIFS(liquidity_stress!$J:$J,liquidity_stress!$A:$A,$A69,liquidity_stress!$B:$B,"other_commitment_draws",liquidity_stress!$C:$C,$B69) -> 640039.95 | D69: =SUMIFS(liquidity_sources!$K:$K,liquidity_sources!$G:$G,"n",liquidity_sources!$H:$H,"<="&$B69)-SUMIFS(liquidity_stress!$D:$D,liquidity_stress!$A:$A,$A69,liquidity_stress!$B:$B,"securities_value_haircut",liquidity_stress!$C:$C,$B69)*SUMIFS(liquidity_sources!$D:$D,liquidity_sources!$B:$B,"afs_securities") -> 2525265.3 | E69: =SUMIFS(liquidity_sources!$K:$K,liquidity_sources!$G:$G,"y",liquidity_sources!$H:$H,"<="&$B69)*(1-SUMIFS(liquidity_stress!$D:$D,liquidity_stress!$A:$A,$A69,liquidity_stress!$B:$B,"contingent_source_availability",liquidity_stress!$C:$C,$B69)) -> 3669292.9 | F69: =D69+E69 -> 6194558.2 | G69: =F69-C69 -> 5554518.2
A70: liq_idiosyncratic | B70: 90 | C70: =SUMIFS(liquidity_stress!$J:$J,liquidity_stress!$A:$A,$A70,liquidity_stress!$B:$B,"insured_retail_nmd",liquidity_stress!$C:$C,$B70)+SUMIFS(liquidity_stress!$J:$J,liquidity_stress!$A:$A,$A70,liquidity_stress!$B:$B,"uninsured_deposits",liquidity_stress!$C:$C,$B70)+SUMIFS(liquidity_stress!$J:$J,liquidity_stress!$A:$A,$A70,liquidity_stress!$B:$B,"business_deposits",liquidity_stress!$C:$C,$B70)+SUMIFS(liquidity_stress!$J:$J,liquidity_stress!$A:$A,$A70,liquidity_stress!$B:$B,"money_market_high_balance",liquidity_stress!$C:$C,$B70)+SUMIFS(liquidity_stress!$J:$J,liquidity_stress!$A:$A,$A70,liquidity_stress!$B:$B,"certificates_maturing",liquidity_stress!$C:$C,$B70)+SUMIFS(liquidity_stress!$J:$J,liquidity_stress!$A:$A,$A70,liquidity_stress!$B:$B,"heloc_line_draws",liquidity_stress!$C:$C,$B70)+SUMIFS(liquidity_stress!$J:$J,liquidity_stress!$A:$A,$A70,liquidity_stress!$B:$B,"other_commitment_draws",liquidity_stress!$C:$C,$B70) -> 1177062.4 | D70: =SUMIFS(liquidity_sources!$K:$K,liquidity_sources!$G:$G,"n",liquidity_sources!$H:$H,"<="&$B70)-SUMIFS(liquidity_stress!$D:$D,liquidity_stress!$A:$A,$A70,liquidity_stress!$B:$B,"securities_value_haircut",liquidity_stress!$C:$C,$B70)*SUMIFS(liquidity_sources!$D:$D,liquidity_sources!$B:$B,"afs_securities") -> 2525265.3 | E70: =SUMIFS(liquidity_sources!$K:$K,liquidity_sources!$G:$G,"y",liquidity_sources!$H:$H,"<="&$B70)*(1-SUMIFS(liquidity_stress!$D:$D,liquidity_stress!$A:$A,$A70,liquidity_stress!$B:$B,"contingent_source_availability",liquidity_stress!$C:$C,$B70)) -> 3630473.3 | F70: =D70+E70 -> 6155738.7 | G70: =F70-C70 -> 4978676.2
A71: liq_idiosyncratic | B71: 180 | C71: =SUMIFS(liquidity_stress!$J:$J,liquidity_stress!$A:$A,$A71,liquidity_stress!$B:$B,"insured_retail_nmd",liquidity_stress!$C:$C,$B71)+SUMIFS(liquidity_stress!$J:$J,liquidity_stress!$A:$A,$A71,liquidity_stress!$B:$B,"uninsured_deposits",liquidity_stress!$C:$C,$B71)+SUMIFS(liquidity_stress!$J:$J,liquidity_stress!$A:$A,$A71,liquidity_stress!$B:$B,"business_deposits",liquidity_stress!$C:$C,$B71)+SUMIFS(liquidity_stress!$J:$J,liquidity_stress!$A:$A,$A71,liquidity_stress!$B:$B,"money_market_high_balance",liquidity_stress!$C:$C,$B71)+SUMIFS(liquidity_stress!$J:$J,liquidity_stress!$A:$A,$A71,liquidity_stress!$B:$B,"certificates_maturing",liquidity_stress!$C:$C,$B71)+SUMIFS(liquidity_stress!$J:$J,liquidity_stress!$A:$A,$A71,liquidity_stress!$B:$B,"heloc_line_draws",liquidity_stress!$C:$C,$B71)+SUMIFS(liquidity_stress!$J:$J,liquidity_stress!$A:$A,$A71,liquidity_stress!$B:$B,"other_commitment_draws",liquidity_stress!$C:$C,$B71) -> 1643241.6 | D71: =SUMIFS(liquidity_sources!$K:$K,liquidity_sources!$G:$G,"n",liquidity_sources!$H:$H,"<="&$B71)-SUMIFS(liquidity_stress!$D:$D,liquidity_stress!$A:$A,$A71,liquidity_stress!$B:$B,"securities_value_haircut",liquidity_stress!$C:$C,$B71)*SUMIFS(liquidity_sources!$D:$D,liquidity_sources!$B:$B,"afs_securities") -> 2525265.3 | E71: =SUMIFS(liquidity_sources!$K:$K,liquidity_sources!$G:$G,"y",liquidity_sources!$H:$H,"<="&$B71)*(1-SUMIFS(liquidity_stress!$D:$D,liquidity_stress!$A:$A,$A71,liquidity_stress!$B:$B,"contingent_source_availability",liquidity_stress!$C:$C,$B71)) -> 3630473.3 | F71: =D71+E71 -> 6155738.7 | G71: =F71-C71 -> 4512497
A72: liq_idiosyncratic | B72: 365 | C72: =SUMIFS(liquidity_stress!$J:$J,liquidity_stress!$A:$A,$A72,liquidity_stress!$B:$B,"insured_retail_nmd",liquidity_stress!$C:$C,$B72)+SUMIFS(liquidity_stress!$J:$J,liquidity_stress!$A:$A,$A72,liquidity_stress!$B:$B,"uninsured_deposits",liquidity_stress!$C:$C,$B72)+SUMIFS(liquidity_stress!$J:$J,liquidity_stress!$A:$A,$A72,liquidity_stress!$B:$B,"business_deposits",liquidity_stress!$C:$C,$B72)+SUMIFS(liquidity_stress!$J:$J,liquidity_stress!$A:$A,$A72,liquidity_stress!$B:$B,"money_market_high_balance",liquidity_stress!$C:$C,$B72)+SUMIFS(liquidity_stress!$J:$J,liquidity_stress!$A:$A,$A72,liquidity_stress!$B:$B,"certificates_maturing",liquidity_stress!$C:$C,$B72)+SUMIFS(liquidity_stress!$J:$J,liquidity_stress!$A:$A,$A72,liquidity_stress!$B:$B,"heloc_line_draws",liquidity_stress!$C:$C,$B72)+SUMIFS(liquidity_stress!$J:$J,liquidity_stress!$A:$A,$A72,liquidity_stress!$B:$B,"other_commitment_draws",liquidity_stress!$C:$C,$B72) -> 2109420.8 | D72: =SUMIFS(liquidity_sources!$K:$K,liquidity_sources!$G:$G,"n",liquidity_sources!$H:$H,"<="&$B72)-SUMIFS(liquidity_stress!$D:$D,liquidity_stress!$A:$A,$A72,liquidity_stress!$B:$B,"securities_value_haircut",liquidity_stress!$C:$C,$B72)*SUMIFS(liquidity_sources!$D:$D,liquidity_sources!$B:$B,"afs_securities") -> 2525265.3 | E72: =SUMIFS(liquidity_sources!$K:$K,liquidity_sources!$G:$G,"y",liquidity_sources!$H:$H,"<="&$B72)*(1-SUMIFS(liquidity_stress!$D:$D,liquidity_stress!$A:$A,$A72,liquidity_stress!$B:$B,"contingent_source_availability",liquidity_stress!$C:$C,$B72)) -> 3630473.3 | F72: =D72+E72 -> 6155738.7 | G72: =F72-C72 -> 4046317.8
A73: liq_idiosyncratic | B73: survival_horizon_days | C73: =IF(G68<0,7,IF(G69<0,30,IF(G70<0,90,IF(G71<0,180,365)))) -> 365
A74: liq_market_wide | B74: 7 | C74: =SUMIFS(liquidity_stress!$J:$J,liquidity_stress!$A:$A,$A74,liquidity_stress!$B:$B,"insured_retail_nmd",liquidity_stress!$C:$C,$B74)+SUMIFS(liquidity_stress!$J:$J,liquidity_stress!$A:$A,$A74,liquidity_stress!$B:$B,"uninsured_deposits",liquidity_stress!$C:$C,$B74)+SUMIFS(liquidity_stress!$J:$J,liquidity_stress!$A:$A,$A74,liquidity_stress!$B:$B,"business_deposits",liquidity_stress!$C:$C,$B74)+SUMIFS(liquidity_stress!$J:$J,liquidity_stress!$A:$A,$A74,liquidity_stress!$B:$B,"money_market_high_balance",liquidity_stress!$C:$C,$B74)+SUMIFS(liquidity_stress!$J:$J,liquidity_stress!$A:$A,$A74,liquidity_stress!$B:$B,"certificates_maturing",liquidity_stress!$C:$C,$B74)+SUMIFS(liquidity_stress!$J:$J,liquidity_stress!$A:$A,$A74,liquidity_stress!$B:$B,"heloc_line_draws",liquidity_stress!$C:$C,$B74)+SUMIFS(liquidity_stress!$J:$J,liquidity_stress!$A:$A,$A74,liquidity_stress!$B:$B,"other_commitment_draws",liquidity_stress!$C:$C,$B74) -> 147176.25 | D74: =SUMIFS(liquidity_sources!$K:$K,liquidity_sources!$G:$G,"n",liquidity_sources!$H:$H,"<="&$B74)-SUMIFS(liquidity_stress!$D:$D,liquidity_stress!$A:$A,$A74,liquidity_stress!$B:$B,"securities_value_haircut",liquidity_stress!$C:$C,$B74)*SUMIFS(liquidity_sources!$D:$D,liquidity_sources!$B:$B,"afs_securities") -> 2466517.1 | E74: =SUMIFS(liquidity_sources!$K:$K,liquidity_sources!$G:$G,"y",liquidity_sources!$H:$H,"<="&$B74)*(1-SUMIFS(liquidity_stress!$D:$D,liquidity_stress!$A:$A,$A74,liquidity_stress!$B:$B,"contingent_source_availability",liquidity_stress!$C:$C,$B74)) -> 3782168.9 | F74: =D74+E74 -> 6248686 | G74: =F74-C74 -> 6101509.7
A75: liq_market_wide | B75: 30 | C75: =SUMIFS(liquidity_stress!$J:$J,liquidity_stress!$A:$A,$A75,liquidity_stress!$B:$B,"insured_retail_nmd",liquidity_stress!$C:$C,$B75)+SUMIFS(liquidity_stress!$J:$J,liquidity_stress!$A:$A,$A75,liquidity_stress!$B:$B,"uninsured_deposits",liquidity_stress!$C:$C,$B75)+SUMIFS(liquidity_stress!$J:$J,liquidity_stress!$A:$A,$A75,liquidity_stress!$B:$B,"business_deposits",liquidity_stress!$C:$C,$B75)+SUMIFS(liquidity_stress!$J:$J,liquidity_stress!$A:$A,$A75,liquidity_stress!$B:$B,"money_market_high_balance",liquidity_stress!$C:$C,$B75)+SUMIFS(liquidity_stress!$J:$J,liquidity_stress!$A:$A,$A75,liquidity_stress!$B:$B,"certificates_maturing",liquidity_stress!$C:$C,$B75)+SUMIFS(liquidity_stress!$J:$J,liquidity_stress!$A:$A,$A75,liquidity_stress!$B:$B,"heloc_line_draws",liquidity_stress!$C:$C,$B75)+SUMIFS(liquidity_stress!$J:$J,liquidity_stress!$A:$A,$A75,liquidity_stress!$B:$B,"other_commitment_draws",liquidity_stress!$C:$C,$B75) -> 477768.55 | D75: =SUMIFS(liquidity_sources!$K:$K,liquidity_sources!$G:$G,"n",liquidity_sources!$H:$H,"<="&$B75)-SUMIFS(liquidity_stress!$D:$D,liquidity_stress!$A:$A,$A75,liquidity_stress!$B:$B,"securities_value_haircut",liquidity_stress!$C:$C,$B75)*SUMIFS(liquidity_sources!$D:$D,liquidity_sources!$B:$B,"afs_securities") -> 2427351.6 | E75: =SUMIFS(liquidity_sources!$K:$K,liquidity_sources!$G:$G,"y",liquidity_sources!$H:$H,"<="&$B75)*(1-SUMIFS(liquidity_stress!$D:$D,liquidity_stress!$A:$A,$A75,liquidity_stress!$B:$B,"contingent_source_availability",liquidity_stress!$C:$C,$B75)) -> 4158531.9 | F75: =D75+E75 -> 6585883.5 | G75: =F75-C75 -> 6108115
A76: liq_market_wide | B76: 90 | C76: =SUMIFS(liquidity_stress!$J:$J,liquidity_stress!$A:$A,$A76,liquidity_stress!$B:$B,"insured_retail_nmd",liquidity_stress!$C:$C,$B76)+SUMIFS(liquidity_stress!$J:$J,liquidity_stress!$A:$A,$A76,liquidity_stress!$B:$B,"uninsured_deposits",liquidity_stress!$C:$C,$B76)+SUMIFS(liquidity_stress!$J:$J,liquidity_stress!$A:$A,$A76,liquidity_stress!$B:$B,"business_deposits",liquidity_stress!$C:$C,$B76)+SUMIFS(liquidity_stress!$J:$J,liquidity_stress!$A:$A,$A76,liquidity_stress!$B:$B,"money_market_high_balance",liquidity_stress!$C:$C,$B76)+SUMIFS(liquidity_stress!$J:$J,liquidity_stress!$A:$A,$A76,liquidity_stress!$B:$B,"certificates_maturing",liquidity_stress!$C:$C,$B76)+SUMIFS(liquidity_stress!$J:$J,liquidity_stress!$A:$A,$A76,liquidity_stress!$B:$B,"heloc_line_draws",liquidity_stress!$C:$C,$B76)+SUMIFS(liquidity_stress!$J:$J,liquidity_stress!$A:$A,$A76,liquidity_stress!$B:$B,"other_commitment_draws",liquidity_stress!$C:$C,$B76) -> 915829.77 | D76: =SUMIFS(liquidity_sources!$K:$K,liquidity_sources!$G:$G,"n",liquidity_sources!$H:$H,"<="&$B76)-SUMIFS(liquidity_stress!$D:$D,liquidity_stress!$A:$A,$A76,liquidity_stress!$B:$B,"securities_value_haircut",liquidity_stress!$C:$C,$B76)*SUMIFS(liquidity_sources!$D:$D,liquidity_sources!$B:$B,"afs_securities") -> 2427351.6 | E76: =SUMIFS(liquidity_sources!$K:$K,liquidity_sources!$G:$G,"y",liquidity_sources!$H:$H,"<="&$B76)*(1-SUMIFS(liquidity_stress!$D:$D,liquidity_stress!$A:$A,$A76,liquidity_stress!$B:$B,"contingent_source_availability",liquidity_stress!$C:$C,$B76)) -> 4408431.9 | F76: =D76+E76 -> 6835783.5 | G76: =F76-C76 -> 5919953.7
A77: liq_market_wide | B77: 180 | C77: =SUMIFS(liquidity_stress!$J:$J,liquidity_stress!$A:$A,$A77,liquidity_stress!$B:$B,"insured_retail_nmd",liquidity_stress!$C:$C,$B77)+SUMIFS(liquidity_stress!$J:$J,liquidity_stress!$A:$A,$A77,liquidity_stress!$B:$B,"uninsured_deposits",liquidity_stress!$C:$C,$B77)+SUMIFS(liquidity_stress!$J:$J,liquidity_stress!$A:$A,$A77,liquidity_stress!$B:$B,"business_deposits",liquidity_stress!$C:$C,$B77)+SUMIFS(liquidity_stress!$J:$J,liquidity_stress!$A:$A,$A77,liquidity_stress!$B:$B,"money_market_high_balance",liquidity_stress!$C:$C,$B77)+SUMIFS(liquidity_stress!$J:$J,liquidity_stress!$A:$A,$A77,liquidity_stress!$B:$B,"certificates_maturing",liquidity_stress!$C:$C,$B77)+SUMIFS(liquidity_stress!$J:$J,liquidity_stress!$A:$A,$A77,liquidity_stress!$B:$B,"heloc_line_draws",liquidity_stress!$C:$C,$B77)+SUMIFS(liquidity_stress!$J:$J,liquidity_stress!$A:$A,$A77,liquidity_stress!$B:$B,"other_commitment_draws",liquidity_stress!$C:$C,$B77) -> 1272635.8 | D77: =SUMIFS(liquidity_sources!$K:$K,liquidity_sources!$G:$G,"n",liquidity_sources!$H:$H,"<="&$B77)-SUMIFS(liquidity_stress!$D:$D,liquidity_stress!$A:$A,$A77,liquidity_stress!$B:$B,"securities_value_haircut",liquidity_stress!$C:$C,$B77)*SUMIFS(liquidity_sources!$D:$D,liquidity_sources!$B:$B,"afs_securities") -> 2427351.6 | E77: =SUMIFS(liquidity_sources!$K:$K,liquidity_sources!$G:$G,"y",liquidity_sources!$H:$H,"<="&$B77)*(1-SUMIFS(liquidity_stress!$D:$D,liquidity_stress!$A:$A,$A77,liquidity_stress!$B:$B,"contingent_source_availability",liquidity_stress!$C:$C,$B77)) -> 4408431.9 | F77: =D77+E77 -> 6835783.5 | G77: =F77-C77 -> 5563147.7
A78: liq_market_wide | B78: 365 | C78: =SUMIFS(liquidity_stress!$J:$J,liquidity_stress!$A:$A,$A78,liquidity_stress!$B:$B,"insured_retail_nmd",liquidity_stress!$C:$C,$B78)+SUMIFS(liquidity_stress!$J:$J,liquidity_stress!$A:$A,$A78,liquidity_stress!$B:$B,"uninsured_deposits",liquidity_stress!$C:$C,$B78)+SUMIFS(liquidity_stress!$J:$J,liquidity_stress!$A:$A,$A78,liquidity_stress!$B:$B,"business_deposits",liquidity_stress!$C:$C,$B78)+SUMIFS(liquidity_stress!$J:$J,liquidity_stress!$A:$A,$A78,liquidity_stress!$B:$B,"money_market_high_balance",liquidity_stress!$C:$C,$B78)+SUMIFS(liquidity_stress!$J:$J,liquidity_stress!$A:$A,$A78,liquidity_stress!$B:$B,"certificates_maturing",liquidity_stress!$C:$C,$B78)+SUMIFS(liquidity_stress!$J:$J,liquidity_stress!$A:$A,$A78,liquidity_stress!$B:$B,"heloc_line_draws",liquidity_stress!$C:$C,$B78)+SUMIFS(liquidity_stress!$J:$J,liquidity_stress!$A:$A,$A78,liquidity_stress!$B:$B,"other_commitment_draws",liquidity_stress!$C:$C,$B78) -> 1573433.6 | D78: =SUMIFS(liquidity_sources!$K:$K,liquidity_sources!$G:$G,"n",liquidity_sources!$H:$H,"<="&$B78)-SUMIFS(liquidity_stress!$D:$D,liquidity_stress!$A:$A,$A78,liquidity_stress!$B:$B,"securities_value_haircut",liquidity_stress!$C:$C,$B78)*SUMIFS(liquidity_sources!$D:$D,liquidity_sources!$B:$B,"afs_securities") -> 2427351.6 | E78: =SUMIFS(liquidity_sources!$K:$K,liquidity_sources!$G:$G,"y",liquidity_sources!$H:$H,"<="&$B78)*(1-SUMIFS(liquidity_stress!$D:$D,liquidity_stress!$A:$A,$A78,liquidity_stress!$B:$B,"contingent_source_availability",liquidity_stress!$C:$C,$B78)) -> 4408431.9 | F78: =D78+E78 -> 6835783.5 | G78: =F78-C78 -> 5262349.9
A79: liq_market_wide | B79: survival_horizon_days | C79: =IF(G74<0,7,IF(G75<0,30,IF(G76<0,90,IF(G77<0,180,365)))) -> 365
A80: liq_combined_severe | B80: 7 | C80: =SUMIFS(liquidity_stress!$J:$J,liquidity_stress!$A:$A,$A80,liquidity_stress!$B:$B,"insured_retail_nmd",liquidity_stress!$C:$C,$B80)+SUMIFS(liquidity_stress!$J:$J,liquidity_stress!$A:$A,$A80,liquidity_stress!$B:$B,"uninsured_deposits",liquidity_stress!$C:$C,$B80)+SUMIFS(liquidity_stress!$J:$J,liquidity_stress!$A:$A,$A80,liquidity_stress!$B:$B,"business_deposits",liquidity_stress!$C:$C,$B80)+SUMIFS(liquidity_stress!$J:$J,liquidity_stress!$A:$A,$A80,liquidity_stress!$B:$B,"money_market_high_balance",liquidity_stress!$C:$C,$B80)+SUMIFS(liquidity_stress!$J:$J,liquidity_stress!$A:$A,$A80,liquidity_stress!$B:$B,"certificates_maturing",liquidity_stress!$C:$C,$B80)+SUMIFS(liquidity_stress!$J:$J,liquidity_stress!$A:$A,$A80,liquidity_stress!$B:$B,"heloc_line_draws",liquidity_stress!$C:$C,$B80)+SUMIFS(liquidity_stress!$J:$J,liquidity_stress!$A:$A,$A80,liquidity_stress!$B:$B,"other_commitment_draws",liquidity_stress!$C:$C,$B80) -> 416376.89 | D80: =SUMIFS(liquidity_sources!$K:$K,liquidity_sources!$G:$G,"n",liquidity_sources!$H:$H,"<="&$B80)-SUMIFS(liquidity_stress!$D:$D,liquidity_stress!$A:$A,$A80,liquidity_stress!$B:$B,"securities_value_haircut",liquidity_stress!$C:$C,$B80)*SUMIFS(liquidity_sources!$D:$D,liquidity_sources!$B:$B,"afs_securities") -> 2427351.6 | E80: =SUMIFS(liquidity_sources!$K:$K,liquidity_sources!$G:$G,"y",liquidity_sources!$H:$H,"<="&$B80)*(1-SUMIFS(liquidity_stress!$D:$D,liquidity_stress!$A:$A,$A80,liquidity_stress!$B:$B,"contingent_source_availability",liquidity_stress!$C:$C,$B80)) -> 2669766.3 | F80: =D80+E80 -> 5097117.9 | G80: =F80-C80 -> 4680741
A81: liq_combined_severe | B81: 30 | C81: =SUMIFS(liquidity_stress!$J:$J,liquidity_stress!$A:$A,$A81,liquidity_stress!$B:$B,"insured_retail_nmd",liquidity_stress!$C:$C,$B81)+SUMIFS(liquidity_stress!$J:$J,liquidity_stress!$A:$A,$A81,liquidity_stress!$B:$B,"uninsured_deposits",liquidity_stress!$C:$C,$B81)+SUMIFS(liquidity_stress!$J:$J,liquidity_stress!$A:$A,$A81,liquidity_stress!$B:$B,"business_deposits",liquidity_stress!$C:$C,$B81)+SUMIFS(liquidity_stress!$J:$J,liquidity_stress!$A:$A,$A81,liquidity_stress!$B:$B,"money_market_high_balance",liquidity_stress!$C:$C,$B81)+SUMIFS(liquidity_stress!$J:$J,liquidity_stress!$A:$A,$A81,liquidity_stress!$B:$B,"certificates_maturing",liquidity_stress!$C:$C,$B81)+SUMIFS(liquidity_stress!$J:$J,liquidity_stress!$A:$A,$A81,liquidity_stress!$B:$B,"heloc_line_draws",liquidity_stress!$C:$C,$B81)+SUMIFS(liquidity_stress!$J:$J,liquidity_stress!$A:$A,$A81,liquidity_stress!$B:$B,"other_commitment_draws",liquidity_stress!$C:$C,$B81) -> 1082632.7 | D81: =SUMIFS(liquidity_sources!$K:$K,liquidity_sources!$G:$G,"n",liquidity_sources!$H:$H,"<="&$B81)-SUMIFS(liquidity_stress!$D:$D,liquidity_stress!$A:$A,$A81,liquidity_stress!$B:$B,"securities_value_haircut",liquidity_stress!$C:$C,$B81)*SUMIFS(liquidity_sources!$D:$D,liquidity_sources!$B:$B,"afs_securities") -> 2368603.4 | E81: =SUMIFS(liquidity_sources!$K:$K,liquidity_sources!$G:$G,"y",liquidity_sources!$H:$H,"<="&$B81)*(1-SUMIFS(liquidity_stress!$D:$D,liquidity_stress!$A:$A,$A81,liquidity_stress!$B:$B,"contingent_source_availability",liquidity_stress!$C:$C,$B81)) -> 2935434.3 | F81: =D81+E81 -> 5304037.7 | G81: =F81-C81 -> 4221404.9
A82: liq_combined_severe | B82: 90 | C82: =SUMIFS(liquidity_stress!$J:$J,liquidity_stress!$A:$A,$A82,liquidity_stress!$B:$B,"insured_retail_nmd",liquidity_stress!$C:$C,$B82)+SUMIFS(liquidity_stress!$J:$J,liquidity_stress!$A:$A,$A82,liquidity_stress!$B:$B,"uninsured_deposits",liquidity_stress!$C:$C,$B82)+SUMIFS(liquidity_stress!$J:$J,liquidity_stress!$A:$A,$A82,liquidity_stress!$B:$B,"business_deposits",liquidity_stress!$C:$C,$B82)+SUMIFS(liquidity_stress!$J:$J,liquidity_stress!$A:$A,$A82,liquidity_stress!$B:$B,"money_market_high_balance",liquidity_stress!$C:$C,$B82)+SUMIFS(liquidity_stress!$J:$J,liquidity_stress!$A:$A,$A82,liquidity_stress!$B:$B,"certificates_maturing",liquidity_stress!$C:$C,$B82)+SUMIFS(liquidity_stress!$J:$J,liquidity_stress!$A:$A,$A82,liquidity_stress!$B:$B,"heloc_line_draws",liquidity_stress!$C:$C,$B82)+SUMIFS(liquidity_stress!$J:$J,liquidity_stress!$A:$A,$A82,liquidity_stress!$B:$B,"other_commitment_draws",liquidity_stress!$C:$C,$B82) -> 1924487.2 | D82: =SUMIFS(liquidity_sources!$K:$K,liquidity_sources!$G:$G,"n",liquidity_sources!$H:$H,"<="&$B82)-SUMIFS(liquidity_stress!$D:$D,liquidity_stress!$A:$A,$A82,liquidity_stress!$B:$B,"securities_value_haircut",liquidity_stress!$C:$C,$B82)*SUMIFS(liquidity_sources!$D:$D,liquidity_sources!$B:$B,"afs_securities") -> 2368603.4 | E82: =SUMIFS(liquidity_sources!$K:$K,liquidity_sources!$G:$G,"y",liquidity_sources!$H:$H,"<="&$B82)*(1-SUMIFS(liquidity_stress!$D:$D,liquidity_stress!$A:$A,$A82,liquidity_stress!$B:$B,"contingent_source_availability",liquidity_stress!$C:$C,$B82)) -> 2852514.8 | F82: =D82+E82 -> 5221118.1 | G82: =F82-C82 -> 3296631
A83: liq_combined_severe | B83: 180 | C83: =SUMIFS(liquidity_stress!$J:$J,liquidity_stress!$A:$A,$A83,liquidity_stress!$B:$B,"insured_retail_nmd",liquidity_stress!$C:$C,$B83)+SUMIFS(liquidity_stress!$J:$J,liquidity_stress!$A:$A,$A83,liquidity_stress!$B:$B,"uninsured_deposits",liquidity_stress!$C:$C,$B83)+SUMIFS(liquidity_stress!$J:$J,liquidity_stress!$A:$A,$A83,liquidity_stress!$B:$B,"business_deposits",liquidity_stress!$C:$C,$B83)+SUMIFS(liquidity_stress!$J:$J,liquidity_stress!$A:$A,$A83,liquidity_stress!$B:$B,"money_market_high_balance",liquidity_stress!$C:$C,$B83)+SUMIFS(liquidity_stress!$J:$J,liquidity_stress!$A:$A,$A83,liquidity_stress!$B:$B,"certificates_maturing",liquidity_stress!$C:$C,$B83)+SUMIFS(liquidity_stress!$J:$J,liquidity_stress!$A:$A,$A83,liquidity_stress!$B:$B,"heloc_line_draws",liquidity_stress!$C:$C,$B83)+SUMIFS(liquidity_stress!$J:$J,liquidity_stress!$A:$A,$A83,liquidity_stress!$B:$B,"other_commitment_draws",liquidity_stress!$C:$C,$B83) -> 2480175.2 | D83: =SUMIFS(liquidity_sources!$K:$K,liquidity_sources!$G:$G,"n",liquidity_sources!$H:$H,"<="&$B83)-SUMIFS(liquidity_stress!$D:$D,liquidity_stress!$A:$A,$A83,liquidity_stress!$B:$B,"securities_value_haircut",liquidity_stress!$C:$C,$B83)*SUMIFS(liquidity_sources!$D:$D,liquidity_sources!$B:$B,"afs_securities") -> 2368603.4 | E83: =SUMIFS(liquidity_sources!$K:$K,liquidity_sources!$G:$G,"y",liquidity_sources!$H:$H,"<="&$B83)*(1-SUMIFS(liquidity_stress!$D:$D,liquidity_stress!$A:$A,$A83,liquidity_stress!$B:$B,"contingent_source_availability",liquidity_stress!$C:$C,$B83)) -> 2852514.8 | F83: =D83+E83 -> 5221118.1 | G83: =F83-C83 -> 2740943
A84: liq_combined_severe | B84: 365 | C84: =SUMIFS(liquidity_stress!$J:$J,liquidity_stress!$A:$A,$A84,liquidity_stress!$B:$B,"insured_retail_nmd",liquidity_stress!$C:$C,$B84)+SUMIFS(liquidity_stress!$J:$J,liquidity_stress!$A:$A,$A84,liquidity_stress!$B:$B,"uninsured_deposits",liquidity_stress!$C:$C,$B84)+SUMIFS(liquidity_stress!$J:$J,liquidity_stress!$A:$A,$A84,liquidity_stress!$B:$B,"business_deposits",liquidity_stress!$C:$C,$B84)+SUMIFS(liquidity_stress!$J:$J,liquidity_stress!$A:$A,$A84,liquidity_stress!$B:$B,"money_market_high_balance",liquidity_stress!$C:$C,$B84)+SUMIFS(liquidity_stress!$J:$J,liquidity_stress!$A:$A,$A84,liquidity_stress!$B:$B,"certificates_maturing",liquidity_stress!$C:$C,$B84)+SUMIFS(liquidity_stress!$J:$J,liquidity_stress!$A:$A,$A84,liquidity_stress!$B:$B,"heloc_line_draws",liquidity_stress!$C:$C,$B84)+SUMIFS(liquidity_stress!$J:$J,liquidity_stress!$A:$A,$A84,liquidity_stress!$B:$B,"other_commitment_draws",liquidity_stress!$C:$C,$B84) -> 3034573.2 | D84: =SUMIFS(liquidity_sources!$K:$K,liquidity_sources!$G:$G,"n",liquidity_sources!$H:$H,"<="&$B84)-SUMIFS(liquidity_stress!$D:$D,liquidity_stress!$A:$A,$A84,liquidity_stress!$B:$B,"securities_value_haircut",liquidity_stress!$C:$C,$B84)*SUMIFS(liquidity_sources!$D:$D,liquidity_sources!$B:$B,"afs_securities") -> 2368603.4 | E84: =SUMIFS(liquidity_sources!$K:$K,liquidity_sources!$G:$G,"y",liquidity_sources!$H:$H,"<="&$B84)*(1-SUMIFS(liquidity_stress!$D:$D,liquidity_stress!$A:$A,$A84,liquidity_stress!$B:$B,"contingent_source_availability",liquidity_stress!$C:$C,$B84)) -> 2852514.8 | F84: =D84+E84 -> 5221118.1 | G84: =F84-C84 -> 2186545
A85: liq_combined_severe | B85: survival_horizon_days | C85: =IF(G80<0,7,IF(G81<0,30,IF(G82<0,90,IF(G83<0,180,365)))) -> 365
A86: liq_rate_disintermediation | B86: 7 | C86: =SUMIFS(liquidity_stress!$J:$J,liquidity_stress!$A:$A,$A86,liquidity_stress!$B:$B,"insured_retail_nmd",liquidity_stress!$C:$C,$B86)+SUMIFS(liquidity_stress!$J:$J,liquidity_stress!$A:$A,$A86,liquidity_stress!$B:$B,"uninsured_deposits",liquidity_stress!$C:$C,$B86)+SUMIFS(liquidity_stress!$J:$J,liquidity_stress!$A:$A,$A86,liquidity_stress!$B:$B,"business_deposits",liquidity_stress!$C:$C,$B86)+SUMIFS(liquidity_stress!$J:$J,liquidity_stress!$A:$A,$A86,liquidity_stress!$B:$B,"money_market_high_balance",liquidity_stress!$C:$C,$B86)+SUMIFS(liquidity_stress!$J:$J,liquidity_stress!$A:$A,$A86,liquidity_stress!$B:$B,"certificates_maturing",liquidity_stress!$C:$C,$B86)+SUMIFS(liquidity_stress!$J:$J,liquidity_stress!$A:$A,$A86,liquidity_stress!$B:$B,"heloc_line_draws",liquidity_stress!$C:$C,$B86)+SUMIFS(liquidity_stress!$J:$J,liquidity_stress!$A:$A,$A86,liquidity_stress!$B:$B,"other_commitment_draws",liquidity_stress!$C:$C,$B86) -> 66024.434 | D86: =SUMIFS(liquidity_sources!$K:$K,liquidity_sources!$G:$G,"n",liquidity_sources!$H:$H,"<="&$B86)-SUMIFS(liquidity_stress!$D:$D,liquidity_stress!$A:$A,$A86,liquidity_stress!$B:$B,"securities_value_haircut",liquidity_stress!$C:$C,$B86)*SUMIFS(liquidity_sources!$D:$D,liquidity_sources!$B:$B,"afs_securities") -> 2290272.4 | E86: =SUMIFS(liquidity_sources!$K:$K,liquidity_sources!$G:$G,"y",liquidity_sources!$H:$H,"<="&$B86)*(1-SUMIFS(liquidity_stress!$D:$D,liquidity_stress!$A:$A,$A86,liquidity_stress!$B:$B,"contingent_source_availability",liquidity_stress!$C:$C,$B86)) -> 4004649.4 | F86: =D86+E86 -> 6294921.8 | G86: =F86-C86 -> 6228897.4
A87: liq_rate_disintermediation | B87: 30 | C87: =SUMIFS(liquidity_stress!$J:$J,liquidity_stress!$A:$A,$A87,liquidity_stress!$B:$B,"insured_retail_nmd",liquidity_stress!$C:$C,$B87)+SUMIFS(liquidity_stress!$J:$J,liquidity_stress!$A:$A,$A87,liquidity_stress!$B:$B,"uninsured_deposits",liquidity_stress!$C:$C,$B87)+SUMIFS(liquidity_stress!$J:$J,liquidity_stress!$A:$A,$A87,liquidity_stress!$B:$B,"business_deposits",liquidity_stress!$C:$C,$B87)+SUMIFS(liquidity_stress!$J:$J,liquidity_stress!$A:$A,$A87,liquidity_stress!$B:$B,"money_market_high_balance",liquidity_stress!$C:$C,$B87)+SUMIFS(liquidity_stress!$J:$J,liquidity_stress!$A:$A,$A87,liquidity_stress!$B:$B,"certificates_maturing",liquidity_stress!$C:$C,$B87)+SUMIFS(liquidity_stress!$J:$J,liquidity_stress!$A:$A,$A87,liquidity_stress!$B:$B,"heloc_line_draws",liquidity_stress!$C:$C,$B87)+SUMIFS(liquidity_stress!$J:$J,liquidity_stress!$A:$A,$A87,liquidity_stress!$B:$B,"other_commitment_draws",liquidity_stress!$C:$C,$B87) -> 250336.36 | D87: =SUMIFS(liquidity_sources!$K:$K,liquidity_sources!$G:$G,"n",liquidity_sources!$H:$H,"<="&$B87)-SUMIFS(liquidity_stress!$D:$D,liquidity_stress!$A:$A,$A87,liquidity_stress!$B:$B,"securities_value_haircut",liquidity_stress!$C:$C,$B87)*SUMIFS(liquidity_sources!$D:$D,liquidity_sources!$B:$B,"afs_securities") -> 2290272.4 | E87: =SUMIFS(liquidity_sources!$K:$K,liquidity_sources!$G:$G,"y",liquidity_sources!$H:$H,"<="&$B87)*(1-SUMIFS(liquidity_stress!$D:$D,liquidity_stress!$A:$A,$A87,liquidity_stress!$B:$B,"contingent_source_availability",liquidity_stress!$C:$C,$B87)) -> 4403151.4 | F87: =D87+E87 -> 6693423.8 | G87: =F87-C87 -> 6443087.5
A88: liq_rate_disintermediation | B88: 90 | C88: =SUMIFS(liquidity_stress!$J:$J,liquidity_stress!$A:$A,$A88,liquidity_stress!$B:$B,"insured_retail_nmd",liquidity_stress!$C:$C,$B88)+SUMIFS(liquidity_stress!$J:$J,liquidity_stress!$A:$A,$A88,liquidity_stress!$B:$B,"uninsured_deposits",liquidity_stress!$C:$C,$B88)+SUMIFS(liquidity_stress!$J:$J,liquidity_stress!$A:$A,$A88,liquidity_stress!$B:$B,"business_deposits",liquidity_stress!$C:$C,$B88)+SUMIFS(liquidity_stress!$J:$J,liquidity_stress!$A:$A,$A88,liquidity_stress!$B:$B,"money_market_high_balance",liquidity_stress!$C:$C,$B88)+SUMIFS(liquidity_stress!$J:$J,liquidity_stress!$A:$A,$A88,liquidity_stress!$B:$B,"certificates_maturing",liquidity_stress!$C:$C,$B88)+SUMIFS(liquidity_stress!$J:$J,liquidity_stress!$A:$A,$A88,liquidity_stress!$B:$B,"heloc_line_draws",liquidity_stress!$C:$C,$B88)+SUMIFS(liquidity_stress!$J:$J,liquidity_stress!$A:$A,$A88,liquidity_stress!$B:$B,"other_commitment_draws",liquidity_stress!$C:$C,$B88) -> 616774.9 | D88: =SUMIFS(liquidity_sources!$K:$K,liquidity_sources!$G:$G,"n",liquidity_sources!$H:$H,"<="&$B88)-SUMIFS(liquidity_stress!$D:$D,liquidity_stress!$A:$A,$A88,liquidity_stress!$B:$B,"securities_value_haircut",liquidity_stress!$C:$C,$B88)*SUMIFS(liquidity_sources!$D:$D,liquidity_sources!$B:$B,"afs_securities") -> 2290272.4 | E88: =SUMIFS(liquidity_sources!$K:$K,liquidity_sources!$G:$G,"y",liquidity_sources!$H:$H,"<="&$B88)*(1-SUMIFS(liquidity_stress!$D:$D,liquidity_stress!$A:$A,$A88,liquidity_stress!$B:$B,"contingent_source_availability",liquidity_stress!$C:$C,$B88)) -> 4667751.4 | F88: =D88+E88 -> 6958023.8 | G88: =F88-C88 -> 6341248.9
A89: liq_rate_disintermediation | B89: 180 | C89: =SUMIFS(liquidity_stress!$J:$J,liquidity_stress!$A:$A,$A89,liquidity_stress!$B:$B,"insured_retail_nmd",liquidity_stress!$C:$C,$B89)+SUMIFS(liquidity_stress!$J:$J,liquidity_stress!$A:$A,$A89,liquidity_stress!$B:$B,"uninsured_deposits",liquidity_stress!$C:$C,$B89)+SUMIFS(liquidity_stress!$J:$J,liquidity_stress!$A:$A,$A89,liquidity_stress!$B:$B,"business_deposits",liquidity_stress!$C:$C,$B89)+SUMIFS(liquidity_stress!$J:$J,liquidity_stress!$A:$A,$A89,liquidity_stress!$B:$B,"money_market_high_balance",liquidity_stress!$C:$C,$B89)+SUMIFS(liquidity_stress!$J:$J,liquidity_stress!$A:$A,$A89,liquidity_stress!$B:$B,"certificates_maturing",liquidity_stress!$C:$C,$B89)+SUMIFS(liquidity_stress!$J:$J,liquidity_stress!$A:$A,$A89,liquidity_stress!$B:$B,"heloc_line_draws",liquidity_stress!$C:$C,$B89)+SUMIFS(liquidity_stress!$J:$J,liquidity_stress!$A:$A,$A89,liquidity_stress!$B:$B,"other_commitment_draws",liquidity_stress!$C:$C,$B89) -> 944345.99 | D89: =SUMIFS(liquidity_sources!$K:$K,liquidity_sources!$G:$G,"n",liquidity_sources!$H:$H,"<="&$B89)-SUMIFS(liquidity_stress!$D:$D,liquidity_stress!$A:$A,$A89,liquidity_stress!$B:$B,"securities_value_haircut",liquidity_stress!$C:$C,$B89)*SUMIFS(liquidity_sources!$D:$D,liquidity_sources!$B:$B,"afs_securities") -> 2290272.4 | E89: =SUMIFS(liquidity_sources!$K:$K,liquidity_sources!$G:$G,"y",liquidity_sources!$H:$H,"<="&$B89)*(1-SUMIFS(liquidity_stress!$D:$D,liquidity_stress!$A:$A,$A89,liquidity_stress!$B:$B,"contingent_source_availability",liquidity_stress!$C:$C,$B89)) -> 4667751.4 | F89: =D89+E89 -> 6958023.8 | G89: =F89-C89 -> 6013677.8
A90: liq_rate_disintermediation | B90: 365 | C90: =SUMIFS(liquidity_stress!$J:$J,liquidity_stress!$A:$A,$A90,liquidity_stress!$B:$B,"insured_retail_nmd",liquidity_stress!$C:$C,$B90)+SUMIFS(liquidity_stress!$J:$J,liquidity_stress!$A:$A,$A90,liquidity_stress!$B:$B,"uninsured_deposits",liquidity_stress!$C:$C,$B90)+SUMIFS(liquidity_stress!$J:$J,liquidity_stress!$A:$A,$A90,liquidity_stress!$B:$B,"business_deposits",liquidity_stress!$C:$C,$B90)+SUMIFS(liquidity_stress!$J:$J,liquidity_stress!$A:$A,$A90,liquidity_stress!$B:$B,"money_market_high_balance",liquidity_stress!$C:$C,$B90)+SUMIFS(liquidity_stress!$J:$J,liquidity_stress!$A:$A,$A90,liquidity_stress!$B:$B,"certificates_maturing",liquidity_stress!$C:$C,$B90)+SUMIFS(liquidity_stress!$J:$J,liquidity_stress!$A:$A,$A90,liquidity_stress!$B:$B,"heloc_line_draws",liquidity_stress!$C:$C,$B90)+SUMIFS(liquidity_stress!$J:$J,liquidity_stress!$A:$A,$A90,liquidity_stress!$B:$B,"other_commitment_draws",liquidity_stress!$C:$C,$B90) -> 1241068.7 | D90: =SUMIFS(liquidity_sources!$K:$K,liquidity_sources!$G:$G,"n",liquidity_sources!$H:$H,"<="&$B90)-SUMIFS(liquidity_stress!$D:$D,liquidity_stress!$A:$A,$A90,liquidity_stress!$B:$B,"securities_value_haircut",liquidity_stress!$C:$C,$B90)*SUMIFS(liquidity_sources!$D:$D,liquidity_sources!$B:$B,"afs_securities") -> 2290272.4 | E90: =SUMIFS(liquidity_sources!$K:$K,liquidity_sources!$G:$G,"y",liquidity_sources!$H:$H,"<="&$B90)*(1-SUMIFS(liquidity_stress!$D:$D,liquidity_stress!$A:$A,$A90,liquidity_stress!$B:$B,"contingent_source_availability",liquidity_stress!$C:$C,$B90)) -> 4667751.4 | F90: =D90+E90 -> 6958023.8 | G90: =F90-C90 -> 5716955.1
A91: liq_rate_disintermediation | B91: survival_horizon_days | C91: =IF(G86<0,7,IF(G87<0,30,IF(G88<0,90,IF(G89<0,180,365)))) -> 365

Sheet checks
A1: Data Health: validation checks (section 6) and additional reconciliations
A2: Every result is a live formula. PASS / FAIL / WARN; tolerance shown per check.
A4: check_id | B4: check | C4: item | D4: value_a | E4: value_b | F4: difference | G4: tolerance | H4: result
A5: 1 | B5: Balance sheet: assets = liabilities + equity (0.1%) | C5: 2020-12-31 | D5: =SUMIFS(balance_sheet!$E:$E,balance_sheet!$A:$A,"2020-12-31",balance_sheet!$B:$B,"asset") -> 6637949.8 | E5: =SUMIFS(balance_sheet!$E:$E,balance_sheet!$A:$A,"2020-12-31",balance_sheet!$B:$B,"liability")+SUMIFS(balance_sheet!$E:$E,balance_sheet!$A:$A,"2020-12-31",balance_sheet!$B:$B,"equity") -> 6637949.8 | F5: =ROUND(D5-E5,2) -> 0 | G5: 0.001 | H5: =IF(ABS(F5)<=G5*ABS(D5),"PASS","FAIL") -> PASS
A6: 1 | B6: Balance sheet: assets = liabilities + equity (0.1%) | C6: 2021-12-31 | D6: =SUMIFS(balance_sheet!$E:$E,balance_sheet!$A:$A,"2021-12-31",balance_sheet!$B:$B,"asset") -> 8206373.3 | E6: =SUMIFS(balance_sheet!$E:$E,balance_sheet!$A:$A,"2021-12-31",balance_sheet!$B:$B,"liability")+SUMIFS(balance_sheet!$E:$E,balance_sheet!$A:$A,"2021-12-31",balance_sheet!$B:$B,"equity") -> 8206373.3 | F6: =ROUND(D6-E6,2) -> 0 | G6: 0.001 | H6: =IF(ABS(F6)<=G6*ABS(D6),"PASS","FAIL") -> PASS
A7: 1 | B7: Balance sheet: assets = liabilities + equity (0.1%) | C7: 2022-12-31 | D7: =SUMIFS(balance_sheet!$E:$E,balance_sheet!$A:$A,"2022-12-31",balance_sheet!$B:$B,"asset") -> 8192281.9 | E7: =SUMIFS(balance_sheet!$E:$E,balance_sheet!$A:$A,"2022-12-31",balance_sheet!$B:$B,"liability")+SUMIFS(balance_sheet!$E:$E,balance_sheet!$A:$A,"2022-12-31",balance_sheet!$B:$B,"equity") -> 8192281.9 | F7: =ROUND(D7-E7,2) -> 0 | G7: 0.001 | H7: =IF(ABS(F7)<=G7*ABS(D7),"PASS","FAIL") -> PASS
A8: 1 | B8: Balance sheet: assets = liabilities + equity (0.1%) | C8: 2023-12-31 | D8: =SUMIFS(balance_sheet!$E:$E,balance_sheet!$A:$A,"2023-12-31",balance_sheet!$B:$B,"asset") -> 8710563.8 | E8: =SUMIFS(balance_sheet!$E:$E,balance_sheet!$A:$A,"2023-12-31",balance_sheet!$B:$B,"liability")+SUMIFS(balance_sheet!$E:$E,balance_sheet!$A:$A,"2023-12-31",balance_sheet!$B:$B,"equity") -> 8710563.8 | F8: =ROUND(D8-E8,2) -> 0 | G8: 0.001 | H8: =IF(ABS(F8)<=G8*ABS(D8),"PASS","FAIL") -> PASS
A9: 1 | B9: Balance sheet: assets = liabilities + equity (0.1%) | C9: 2024-12-31 | D9: =SUMIFS(balance_sheet!$E:$E,balance_sheet!$A:$A,"2024-12-31",balance_sheet!$B:$B,"asset") -> 8783626.8 | E9: =SUMIFS(balance_sheet!$E:$E,balance_sheet!$A:$A,"2024-12-31",balance_sheet!$B:$B,"liability")+SUMIFS(balance_sheet!$E:$E,balance_sheet!$A:$A,"2024-12-31",balance_sheet!$B:$B,"equity") -> 8783626.8 | F9: =ROUND(D9-E9,2) -> 0 | G9: 0.001 | H9: =IF(ABS(F9)<=G9*ABS(D9),"PASS","FAIL") -> PASS
A10: 1 | B10: Balance sheet: assets = liabilities + equity (0.1%) | C10: 2025-12-31 | D10: =SUMIFS(balance_sheet!$E:$E,balance_sheet!$A:$A,"2025-12-31",balance_sheet!$B:$B,"asset") -> 9535159.3 | E10: =SUMIFS(balance_sheet!$E:$E,balance_sheet!$A:$A,"2025-12-31",balance_sheet!$B:$B,"liability")+SUMIFS(balance_sheet!$E:$E,balance_sheet!$A:$A,"2025-12-31",balance_sheet!$B:$B,"equity") -> 9535159.3 | F10: =ROUND(D10-E10,2) -> 0 | G10: 0.001 | H10: =IF(ABS(F10)<=G10*ABS(D10),"PASS","FAIL") -> PASS
A11: 1 | B11: Balance sheet: assets = liabilities + equity (0.1%) | C11: 2026-03-31 | D11: =SUMIFS(balance_sheet!$E:$E,balance_sheet!$A:$A,"2026-03-31",balance_sheet!$B:$B,"asset") -> 9791191.4 | E11: =SUMIFS(balance_sheet!$E:$E,balance_sheet!$A:$A,"2026-03-31",balance_sheet!$B:$B,"liability")+SUMIFS(balance_sheet!$E:$E,balance_sheet!$A:$A,"2026-03-31",balance_sheet!$B:$B,"equity") -> 9791191.4 | F11: =ROUND(D11-E11,2) -> 0 | G11: 0.001 | H11: =IF(ABS(F11)<=G11*ABS(D11),"PASS","FAIL") -> PASS
A12: 1 | B12: Balance sheet: assets = liabilities + equity (0.1%) | C12: 2026-06-30 | D12: =SUMIFS(balance_sheet!$E:$E,balance_sheet!$A:$A,"2026-06-30",balance_sheet!$B:$B,"asset") -> 9887845 | E12: =SUMIFS(balance_sheet!$E:$E,balance_sheet!$A:$A,"2026-06-30",balance_sheet!$B:$B,"liability")+SUMIFS(balance_sheet!$E:$E,balance_sheet!$A:$A,"2026-06-30",balance_sheet!$B:$B,"equity") -> 9887845 | F12: =ROUND(D12-E12,2) -> 0 | G12: 0.001 | H12: =IF(ABS(F12)<=G12*ABS(D12),"PASS","FAIL") -> PASS
A13: 2 | B13: Loan products sum to balance sheet loans (0.1%) | C13: 2026-06-30 | D13: =SUMIFS(loans!$D:$D,loans!$A:$A,meta!$B$3) -> 5305440.5 | E13: =SUMIFS(balance_sheet!$E:$E,balance_sheet!$A:$A,meta!$B$3,balance_sheet!$C:$C,"loans") -> 5305440.5 | F13: =D13-E13 -> 0 | G13: 0.001 | H13: =IF(ABS(F13)<=G13*ABS(E13),"PASS","FAIL") -> PASS
A14: 2 | B14: Deposit products sum to balance sheet shares (0.1%) | C14: 2026-06-30 | D14: =SUMIFS(deposits!$E:$E,deposits!$A:$A,meta!$B$3) -> 8855600.3 | E14: =SUMIFS(balance_sheet!$E:$E,balance_sheet!$A:$A,meta!$B$3,balance_sheet!$C:$C,"shares") -> 8855600.3 | F14: =D14-E14 -> 0 | G14: 0.001 | H14: =IF(ABS(F14)<=G14*ABS(E14),"PASS","FAIL") -> PASS
A15: 3 | B15: Repricing gap: asset buckets incl. nonrate = total assets | C15: 2026-06-30 | D15: =SUMIFS(repricing_gap!$D:$D,repricing_gap!$A:$A,meta!$B$3,repricing_gap!$C:$C,"asset") -> 9887845 | E15: =SUMIFS(balance_sheet!$E:$E,balance_sheet!$A:$A,meta!$B$3,balance_sheet!$B:$B,"asset") -> 9887845 | F15: =D15-E15 -> 0 | G15: 0.001 | H15: =IF(ABS(F15)<=G15*ABS(E15),"PASS","FAIL") -> PASS
A16: 3 | B16: Repricing gap: liability + equity buckets = liabilities + equity | C16: 2026-06-30 | D16: =SUMIFS(repricing_gap!$D:$D,repricing_gap!$A:$A,meta!$B$3,repricing_gap!$C:$C,"liability")+SUMIFS(repricing_gap!$D:$D,repricing_gap!$A:$A,meta!$B$3,repricing_gap!$C:$C,"equity") -> 9887845 | E16: =SUMIFS(balance_sheet!$E:$E,balance_sheet!$A:$A,meta!$B$3,balance_sheet!$B:$B,"liability")+SUMIFS(balance_sheet!$E:$E,balance_sheet!$A:$A,meta!$B$3,balance_sheet!$B:$B,"equity") -> 9887845 | F16: =D16-E16 -> 0 | G16: 0.001 | H16: =IF(ABS(F16)<=G16*ABS(E16),"PASS","FAIL") -> PASS
A17: 4 | B17: Income statement: NII = interest income - interest expense | C17: 2020-12-31 ytd | D17: =SUMIFS(income_statement!$E:$E,income_statement!$A:$A,"2020-12-31",income_statement!$B:$B,"ytd",income_statement!$C:$C,"interest_income")-SUMIFS(income_statement!$E:$E,income_statement!$A:$A,"2020-12-31",income_statement!$B:$B,"ytd",income_statement!$C:$C,"interest_expense") -> 132733.63 | E17: =income_statement_totals!$M$2 -> 132733.63 | F17: =D17-E17 -> 0 | G17: 0.5 | H17: =IF(ABS(F17)<=G17,"PASS","FAIL") -> PASS
A18: 4 | B18: Income statement: net income ties to components | C18: 2020-12-31 ytd | D18: =SUMIFS(income_statement!$E:$E,income_statement!$A:$A,"2020-12-31",income_statement!$B:$B,"ytd",income_statement!$C:$C,"interest_income")-SUMIFS(income_statement!$E:$E,income_statement!$A:$A,"2020-12-31",income_statement!$B:$B,"ytd",income_statement!$C:$C,"interest_expense")-SUMIFS(income_statement!$E:$E,income_statement!$A:$A,"2020-12-31",income_statement!$B:$B,"ytd",income_statement!$C:$C,"member_giveback")-SUMIFS(income_statement!$E:$E,income_statement!$A:$A,"2020-12-31",income_statement!$B:$B,"ytd",income_statement!$C:$C,"provision")+SUMIFS(income_statement!$E:$E,income_statement!$A:$A,"2020-12-31",income_statement!$B:$B,"ytd",income_statement!$C:$C,"noninterest_income")-SUMIFS(income_statement!$E:$E,income_statement!$A:$A,"2020-12-31",income_statement!$B:$B,"ytd",income_statement!$C:$C,"noninterest_expense")+SUMIFS(income_statement!$E:$E,income_statement!$A:$A,"2020-12-31",income_statement!$B:$B,"ytd",income_statement!$C:$C,"one_time") -> 42541.475 | E18: =income_statement_totals!$J$2 -> 42541.475 | F18: =D18-E18 -> 0 | G18: 0.5 | H18: =IF(ABS(F18)<=G18,"PASS","FAIL") -> PASS
A19: 4 | B19: Income statement: NII = interest income - interest expense | C19: 2021-12-31 ytd | D19: =SUMIFS(income_statement!$E:$E,income_statement!$A:$A,"2021-12-31",income_statement!$B:$B,"ytd",income_statement!$C:$C,"interest_income")-SUMIFS(income_statement!$E:$E,income_statement!$A:$A,"2021-12-31",income_statement!$B:$B,"ytd",income_statement!$C:$C,"interest_expense") -> 143032.57 | E19: =income_statement_totals!$M$3 -> 143032.57 | F19: =D19-E19 -> 0 | G19: 0.5 | H19: =IF(ABS(F19)<=G19,"PASS","FAIL") -> PASS
A20: 4 | B20: Income statement: net income ties to components | C20: 2021-12-31 ytd | D20: =SUMIFS(income_statement!$E:$E,income_statement!$A:$A,"2021-12-31",income_statement!$B:$B,"ytd",income_statement!$C:$C,"interest_income")-SUMIFS(income_statement!$E:$E,income_statement!$A:$A,"2021-12-31",income_statement!$B:$B,"ytd",income_statement!$C:$C,"interest_expense")-SUMIFS(income_statement!$E:$E,income_statement!$A:$A,"2021-12-31",income_statement!$B:$B,"ytd",income_statement!$C:$C,"member_giveback")-SUMIFS(income_statement!$E:$E,income_statement!$A:$A,"2021-12-31",income_statement!$B:$B,"ytd",income_statement!$C:$C,"provision")+SUMIFS(income_statement!$E:$E,income_statement!$A:$A,"2021-12-31",income_statement!$B:$B,"ytd",income_statement!$C:$C,"noninterest_income")-SUMIFS(income_statement!$E:$E,income_statement!$A:$A,"2021-12-31",income_statement!$B:$B,"ytd",income_statement!$C:$C,"noninterest_expense")+SUMIFS(income_statement!$E:$E,income_statement!$A:$A,"2021-12-31",income_statement!$B:$B,"ytd",income_statement!$C:$C,"one_time") -> 87441.822 | E20: =income_statement_totals!$J$3 -> 87441.822 | F20: =D20-E20 -> 0 | G20: 0.5 | H20: =IF(ABS(F20)<=G20,"PASS","FAIL") -> PASS
A21: 4 | B21: Income statement: NII = interest income - interest expense | C21: 2022-12-31 ytd | D21: =SUMIFS(income_statement!$E:$E,income_statement!$A:$A,"2022-12-31",income_statement!$B:$B,"ytd",income_statement!$C:$C,"interest_income")-SUMIFS(income_statement!$E:$E,income_statement!$A:$A,"2022-12-31",income_statement!$B:$B,"ytd",income_statement!$C:$C,"interest_expense") -> 198276.02 | E21: =income_statement_totals!$M$4 -> 198276.02 | F21: =D21-E21 -> 0 | G21: 0.5 | H21: =IF(ABS(F21)<=G21,"PASS","FAIL") -> PASS
A22: 4 | B22: Income statement: net income ties to components | C22: 2022-12-31 ytd | D22: =SUMIFS(income_statement!$E:$E,income_statement!$A:$A,"2022-12-31",income_statement!$B:$B,"ytd",income_statement!$C:$C,"interest_income")-SUMIFS(income_statement!$E:$E,income_statement!$A:$A,"2022-12-31",income_statement!$B:$B,"ytd",income_statement!$C:$C,"interest_expense")-SUMIFS(income_statement!$E:$E,income_statement!$A:$A,"2022-12-31",income_statement!$B:$B,"ytd",income_statement!$C:$C,"member_giveback")-SUMIFS(income_statement!$E:$E,income_statement!$A:$A,"2022-12-31",income_statement!$B:$B,"ytd",income_statement!$C:$C,"provision")+SUMIFS(income_statement!$E:$E,income_statement!$A:$A,"2022-12-31",income_statement!$B:$B,"ytd",income_statement!$C:$C,"noninterest_income")-SUMIFS(income_statement!$E:$E,income_statement!$A:$A,"2022-12-31",income_statement!$B:$B,"ytd",income_statement!$C:$C,"noninterest_expense")+SUMIFS(income_statement!$E:$E,income_statement!$A:$A,"2022-12-31",income_statement!$B:$B,"ytd",income_statement!$C:$C,"one_time") -> 86022.867 | E22: =income_statement_totals!$J$4 -> 86022.867 | F22: =D22-E22 -> 0 | G22: 0.5 | H22: =IF(ABS(F22)<=G22,"PASS","FAIL") -> PASS
A23: 4 | B23: Income statement: NII = interest income - interest expense | C23: 2023-12-31 ytd | D23: =SUMIFS(income_statement!$E:$E,income_statement!$A:$A,"2023-12-31",income_statement!$B:$B,"ytd",income_statement!$C:$C,"interest_income")-SUMIFS(income_statement!$E:$E,income_statement!$A:$A,"2023-12-31",income_statement!$B:$B,"ytd",income_statement!$C:$C,"interest_expense") -> 212420.64 | E23: =income_statement_totals!$M$5 -> 212420.64 | F23: =D23-E23 -> 0 | G23: 0.5 | H23: =IF(ABS(F23)<=G23,"PASS","FAIL") -> PASS
A24: 4 | B24: Income statement: net income ties to components | C24: 2023-12-31 ytd | D24: =SUMIFS(income_statement!$E:$E,income_statement!$A:$A,"2023-12-31",income_statement!$B:$B,"ytd",income_statement!$C:$C,"interest_income")-SUMIFS(income_statement!$E:$E,income_statement!$A:$A,"2023-12-31",income_statement!$B:$B,"ytd",income_statement!$C:$C,"interest_expense")-SUMIFS(income_statement!$E:$E,income_statement!$A:$A,"2023-12-31",income_statement!$B:$B,"ytd",income_statement!$C:$C,"member_giveback")-SUMIFS(income_statement!$E:$E,income_statement!$A:$A,"2023-12-31",income_statement!$B:$B,"ytd",income_statement!$C:$C,"provision")+SUMIFS(income_statement!$E:$E,income_statement!$A:$A,"2023-12-31",income_statement!$B:$B,"ytd",income_statement!$C:$C,"noninterest_income")-SUMIFS(income_statement!$E:$E,income_statement!$A:$A,"2023-12-31",income_statement!$B:$B,"ytd",income_statement!$C:$C,"noninterest_expense")+SUMIFS(income_statement!$E:$E,income_statement!$A:$A,"2023-12-31",income_statement!$B:$B,"ytd",income_statement!$C:$C,"one_time") -> 85294.418 | E24: =income_statement_totals!$J$5 -> 85294.418 | F24: =D24-E24 -> 0 | G24: 0.5 | H24: =IF(ABS(F24)<=G24,"PASS","FAIL") -> PASS
A25: 4 | B25: Income statement: NII = interest income - interest expense | C25: 2024-12-31 ytd | D25: =SUMIFS(income_statement!$E:$E,income_statement!$A:$A,"2024-12-31",income_statement!$B:$B,"ytd",income_statement!$C:$C,"interest_income")-SUMIFS(income_statement!$E:$E,income_statement!$A:$A,"2024-12-31",income_statement!$B:$B,"ytd",income_statement!$C:$C,"interest_expense") -> 217705.06 | E25: =income_statement_totals!$M$6 -> 217705.06 | F25: =D25-E25 -> 0 | G25: 0.5 | H25: =IF(ABS(F25)<=G25,"PASS","FAIL") -> PASS
A26: 4 | B26: Income statement: net income ties to components | C26: 2024-12-31 ytd | D26: =SUMIFS(income_statement!$E:$E,income_statement!$A:$A,"2024-12-31",income_statement!$B:$B,"ytd",income_statement!$C:$C,"interest_income")-SUMIFS(income_statement!$E:$E,income_statement!$A:$A,"2024-12-31",income_statement!$B:$B,"ytd",income_statement!$C:$C,"interest_expense")-SUMIFS(income_statement!$E:$E,income_statement!$A:$A,"2024-12-31",income_statement!$B:$B,"ytd",income_statement!$C:$C,"member_giveback")-SUMIFS(income_statement!$E:$E,income_statement!$A:$A,"2024-12-31",income_statement!$B:$B,"ytd",income_statement!$C:$C,"provision")+SUMIFS(income_statement!$E:$E,income_statement!$A:$A,"2024-12-31",income_statement!$B:$B,"ytd",income_statement!$C:$C,"noninterest_income")-SUMIFS(income_statement!$E:$E,income_statement!$A:$A,"2024-12-31",income_statement!$B:$B,"ytd",income_statement!$C:$C,"noninterest_expense")+SUMIFS(income_statement!$E:$E,income_statement!$A:$A,"2024-12-31",income_statement!$B:$B,"ytd",income_statement!$C:$C,"one_time") -> 72217.108 | E26: =income_statement_totals!$J$6 -> 72217.108 | F26: =D26-E26 -> 0 | G26: 0.5 | H26: =IF(ABS(F26)<=G26,"PASS","FAIL") -> PASS
A27: 4 | B27: Income statement: NII = interest income - interest expense | C27: 2025-12-31 ytd | D27: =SUMIFS(income_statement!$E:$E,income_statement!$A:$A,"2025-12-31",income_statement!$B:$B,"ytd",income_statement!$C:$C,"interest_income")-SUMIFS(income_statement!$E:$E,income_statement!$A:$A,"2025-12-31",income_statement!$B:$B,"ytd",income_statement!$C:$C,"interest_expense") -> 257443.59 | E27: =income_statement_totals!$M$7 -> 257443.59 | F27: =D27-E27 -> 0 | G27: 0.5 | H27: =IF(ABS(F27)<=G27,"PASS","FAIL") -> PASS
A28: 4 | B28: Income statement: net income ties to components | C28: 2025-12-31 ytd | D28: =SUMIFS(income_statement!$E:$E,income_statement!$A:$A,"2025-12-31",income_statement!$B:$B,"ytd",income_statement!$C:$C,"interest_income")-SUMIFS(income_statement!$E:$E,income_statement!$A:$A,"2025-12-31",income_statement!$B:$B,"ytd",income_statement!$C:$C,"interest_expense")-SUMIFS(income_statement!$E:$E,income_statement!$A:$A,"2025-12-31",income_statement!$B:$B,"ytd",income_statement!$C:$C,"member_giveback")-SUMIFS(income_statement!$E:$E,income_statement!$A:$A,"2025-12-31",income_statement!$B:$B,"ytd",income_statement!$C:$C,"provision")+SUMIFS(income_statement!$E:$E,income_statement!$A:$A,"2025-12-31",income_statement!$B:$B,"ytd",income_statement!$C:$C,"noninterest_income")-SUMIFS(income_statement!$E:$E,income_statement!$A:$A,"2025-12-31",income_statement!$B:$B,"ytd",income_statement!$C:$C,"noninterest_expense")+SUMIFS(income_statement!$E:$E,income_statement!$A:$A,"2025-12-31",income_statement!$B:$B,"ytd",income_statement!$C:$C,"one_time") -> 74570.244 | E28: =income_statement_totals!$J$7 -> 74570.244 | F28: =D28-E28 -> 0 | G28: 0.5 | H28: =IF(ABS(F28)<=G28,"PASS","FAIL") -> PASS
A29: 4 | B29: Income statement: NII = interest income - interest expense | C29: 2026-06-30 ytd | D29: =SUMIFS(income_statement!$E:$E,income_statement!$A:$A,"2026-06-30",income_statement!$B:$B,"ytd",income_statement!$C:$C,"interest_income")-SUMIFS(income_statement!$E:$E,income_statement!$A:$A,"2026-06-30",income_statement!$B:$B,"ytd",income_statement!$C:$C,"interest_expense") -> 155630.26 | E29: =income_statement_totals!$M$8 -> 155630.26 | F29: =D29-E29 -> 0 | G29: 0.5 | H29: =IF(ABS(F29)<=G29,"PASS","FAIL") -> PASS
A30: 4 | B30: Income statement: net income ties to components | C30: 2026-06-30 ytd | D30: =SUMIFS(income_statement!$E:$E,income_statement!$A:$A,"2026-06-30",income_statement!$B:$B,"ytd",income_statement!$C:$C,"interest_income")-SUMIFS(income_statement!$E:$E,income_statement!$A:$A,"2026-06-30",income_statement!$B:$B,"ytd",income_statement!$C:$C,"interest_expense")-SUMIFS(income_statement!$E:$E,income_statement!$A:$A,"2026-06-30",income_statement!$B:$B,"ytd",income_statement!$C:$C,"member_giveback")-SUMIFS(income_statement!$E:$E,income_statement!$A:$A,"2026-06-30",income_statement!$B:$B,"ytd",income_statement!$C:$C,"provision")+SUMIFS(income_statement!$E:$E,income_statement!$A:$A,"2026-06-30",income_statement!$B:$B,"ytd",income_statement!$C:$C,"noninterest_income")-SUMIFS(income_statement!$E:$E,income_statement!$A:$A,"2026-06-30",income_statement!$B:$B,"ytd",income_statement!$C:$C,"noninterest_expense")+SUMIFS(income_statement!$E:$E,income_statement!$A:$A,"2026-06-30",income_statement!$B:$B,"ytd",income_statement!$C:$C,"one_time") -> 54770.059 | E30: =income_statement_totals!$J$8 -> 54770.059 | F30: =D30-E30 -> 0 | G30: 0.5 | H30: =IF(ABS(F30)<=G30,"PASS","FAIL") -> PASS
A31: 4 | B31: Income statement: NII = interest income - interest expense | C31: 2025-03-31 qtd | D31: =SUMIFS(income_statement!$E:$E,income_statement!$A:$A,"2025-03-31",income_statement!$B:$B,"qtd",income_statement!$C:$C,"interest_income")-SUMIFS(income_statement!$E:$E,income_statement!$A:$A,"2025-03-31",income_statement!$B:$B,"qtd",income_statement!$C:$C,"interest_expense") -> 58939.936 | E31: =income_statement_totals!$M$9 -> 58939.936 | F31: =D31-E31 -> 0 | G31: 0.5 | H31: =IF(ABS(F31)<=G31,"PASS","FAIL") -> PASS
A32: 4 | B32: Income statement: net income ties to components | C32: 2025-03-31 qtd | D32: =SUMIFS(income_statement!$E:$E,income_statement!$A:$A,"2025-03-31",income_statement!$B:$B,"qtd",income_statement!$C:$C,"interest_income")-SUMIFS(income_statement!$E:$E,income_statement!$A:$A,"2025-03-31",income_statement!$B:$B,"qtd",income_statement!$C:$C,"interest_expense")-SUMIFS(income_statement!$E:$E,income_statement!$A:$A,"2025-03-31",income_statement!$B:$B,"qtd",income_statement!$C:$C,"member_giveback")-SUMIFS(income_statement!$E:$E,income_statement!$A:$A,"2025-03-31",income_statement!$B:$B,"qtd",income_statement!$C:$C,"provision")+SUMIFS(income_statement!$E:$E,income_statement!$A:$A,"2025-03-31",income_statement!$B:$B,"qtd",income_statement!$C:$C,"noninterest_income")-SUMIFS(income_statement!$E:$E,income_statement!$A:$A,"2025-03-31",income_statement!$B:$B,"qtd",income_statement!$C:$C,"noninterest_expense")+SUMIFS(income_statement!$E:$E,income_statement!$A:$A,"2025-03-31",income_statement!$B:$B,"qtd",income_statement!$C:$C,"one_time") -> 1683.1956 | E32: =income_statement_totals!$J$9 -> 1683.1956 | F32: =D32-E32 -> 0 | G32: 0.5 | H32: =IF(ABS(F32)<=G32,"PASS","FAIL") -> PASS
A33: 4 | B33: Income statement: NII = interest income - interest expense | C33: 2025-06-30 qtd | D33: =SUMIFS(income_statement!$E:$E,income_statement!$A:$A,"2025-06-30",income_statement!$B:$B,"qtd",income_statement!$C:$C,"interest_income")-SUMIFS(income_statement!$E:$E,income_statement!$A:$A,"2025-06-30",income_statement!$B:$B,"qtd",income_statement!$C:$C,"interest_expense") -> 62104.218 | E33: =income_statement_totals!$M$10 -> 62104.218 | F33: =D33-E33 -> 0 | G33: 0.5 | H33: =IF(ABS(F33)<=G33,"PASS","FAIL") -> PASS
A34: 4 | B34: Income statement: net income ties to components | C34: 2025-06-30 qtd | D34: =SUMIFS(income_statement!$E:$E,income_statement!$A:$A,"2025-06-30",income_statement!$B:$B,"qtd",income_statement!$C:$C,"interest_income")-SUMIFS(income_statement!$E:$E,income_statement!$A:$A,"2025-06-30",income_statement!$B:$B,"qtd",income_statement!$C:$C,"interest_expense")-SUMIFS(income_statement!$E:$E,income_statement!$A:$A,"2025-06-30",income_statement!$B:$B,"qtd",income_statement!$C:$C,"member_giveback")-SUMIFS(income_statement!$E:$E,income_statement!$A:$A,"2025-06-30",income_statement!$B:$B,"qtd",income_statement!$C:$C,"provision")+SUMIFS(income_statement!$E:$E,income_statement!$A:$A,"2025-06-30",income_statement!$B:$B,"qtd",income_statement!$C:$C,"noninterest_income")-SUMIFS(income_statement!$E:$E,income_statement!$A:$A,"2025-06-30",income_statement!$B:$B,"qtd",income_statement!$C:$C,"noninterest_expense")+SUMIFS(income_statement!$E:$E,income_statement!$A:$A,"2025-06-30",income_statement!$B:$B,"qtd",income_statement!$C:$C,"one_time") -> 23706.685 | E34: =income_statement_totals!$J$10 -> 23706.685 | F34: =D34-E34 -> 0 | G34: 0.5 | H34: =IF(ABS(F34)<=G34,"PASS","FAIL") -> PASS
A35: 4 | B35: Income statement: NII = interest income - interest expense | C35: 2025-09-30 qtd | D35: =SUMIFS(income_statement!$E:$E,income_statement!$A:$A,"2025-09-30",income_statement!$B:$B,"qtd",income_statement!$C:$C,"interest_income")-SUMIFS(income_statement!$E:$E,income_statement!$A:$A,"2025-09-30",income_statement!$B:$B,"qtd",income_statement!$C:$C,"interest_expense") -> 65969.013 | E35: =income_statement_totals!$M$11 -> 65969.013 | F35: =D35-E35 -> 0 | G35: 0.5 | H35: =IF(ABS(F35)<=G35,"PASS","FAIL") -> PASS
A36: 4 | B36: Income statement: net income ties to components | C36: 2025-09-30 qtd | D36: =SUMIFS(income_statement!$E:$E,income_statement!$A:$A,"2025-09-30",income_statement!$B:$B,"qtd",income_statement!$C:$C,"interest_income")-SUMIFS(income_statement!$E:$E,income_statement!$A:$A,"2025-09-30",income_statement!$B:$B,"qtd",income_statement!$C:$C,"interest_expense")-SUMIFS(income_statement!$E:$E,income_statement!$A:$A,"2025-09-30",income_statement!$B:$B,"qtd",income_statement!$C:$C,"member_giveback")-SUMIFS(income_statement!$E:$E,income_statement!$A:$A,"2025-09-30",income_statement!$B:$B,"qtd",income_statement!$C:$C,"provision")+SUMIFS(income_statement!$E:$E,income_statement!$A:$A,"2025-09-30",income_statement!$B:$B,"qtd",income_statement!$C:$C,"noninterest_income")-SUMIFS(income_statement!$E:$E,income_statement!$A:$A,"2025-09-30",income_statement!$B:$B,"qtd",income_statement!$C:$C,"noninterest_expense")+SUMIFS(income_statement!$E:$E,income_statement!$A:$A,"2025-09-30",income_statement!$B:$B,"qtd",income_statement!$C:$C,"one_time") -> 22458.245 | E36: =income_statement_totals!$J$11 -> 22458.245 | F36: =D36-E36 -> 0 | G36: 0.5 | H36: =IF(ABS(F36)<=G36,"PASS","FAIL") -> PASS
A37: 4 | B37: Income statement: NII = interest income - interest expense | C37: 2025-12-31 qtd | D37: =SUMIFS(income_statement!$E:$E,income_statement!$A:$A,"2025-12-31",income_statement!$B:$B,"qtd",income_statement!$C:$C,"interest_income")-SUMIFS(income_statement!$E:$E,income_statement!$A:$A,"2025-12-31",income_statement!$B:$B,"qtd",income_statement!$C:$C,"interest_expense") -> 70430.426 | E37: =income_statement_totals!$M$12 -> 70430.426 | F37: =D37-E37 -> 0 | G37: 0.5 | H37: =IF(ABS(F37)<=G37,"PASS","FAIL") -> PASS
A38: 4 | B38: Income statement: net income ties to components | C38: 2025-12-31 qtd | D38: =SUMIFS(income_statement!$E:$E,income_statement!$A:$A,"2025-12-31",income_statement!$B:$B,"qtd",income_statement!$C:$C,"interest_income")-SUMIFS(income_statement!$E:$E,income_statement!$A:$A,"2025-12-31",income_statement!$B:$B,"qtd",income_statement!$C:$C,"interest_expense")-SUMIFS(income_statement!$E:$E,income_statement!$A:$A,"2025-12-31",income_statement!$B:$B,"qtd",income_statement!$C:$C,"member_giveback")-SUMIFS(income_statement!$E:$E,income_statement!$A:$A,"2025-12-31",income_statement!$B:$B,"qtd",income_statement!$C:$C,"provision")+SUMIFS(income_statement!$E:$E,income_statement!$A:$A,"2025-12-31",income_statement!$B:$B,"qtd",income_statement!$C:$C,"noninterest_income")-SUMIFS(income_statement!$E:$E,income_statement!$A:$A,"2025-12-31",income_statement!$B:$B,"qtd",income_statement!$C:$C,"noninterest_expense")+SUMIFS(income_statement!$E:$E,income_statement!$A:$A,"2025-12-31",income_statement!$B:$B,"qtd",income_statement!$C:$C,"one_time") -> 26722.118 | E38: =income_statement_totals!$J$12 -> 26722.118 | F38: =D38-E38 -> 0 | G38: 0.5 | H38: =IF(ABS(F38)<=G38,"PASS","FAIL") -> PASS
A39: 4 | B39: Income statement: NII = interest income - interest expense | C39: 2026-03-31 qtd | D39: =SUMIFS(income_statement!$E:$E,income_statement!$A:$A,"2026-03-31",income_statement!$B:$B,"qtd",income_statement!$C:$C,"interest_income")-SUMIFS(income_statement!$E:$E,income_statement!$A:$A,"2026-03-31",income_statement!$B:$B,"qtd",income_statement!$C:$C,"interest_expense") -> 77032.458 | E39: =income_statement_totals!$M$13 -> 77032.458 | F39: =D39-E39 -> 0 | G39: 0.5 | H39: =IF(ABS(F39)<=G39,"PASS","FAIL") -> PASS
A40: 4 | B40: Income statement: net income ties to components | C40: 2026-03-31 qtd | D40: =SUMIFS(income_statement!$E:$E,income_statement!$A:$A,"2026-03-31",income_statement!$B:$B,"qtd",income_statement!$C:$C,"interest_income")-SUMIFS(income_statement!$E:$E,income_statement!$A:$A,"2026-03-31",income_statement!$B:$B,"qtd",income_statement!$C:$C,"interest_expense")-SUMIFS(income_statement!$E:$E,income_statement!$A:$A,"2026-03-31",income_statement!$B:$B,"qtd",income_statement!$C:$C,"member_giveback")-SUMIFS(income_statement!$E:$E,income_statement!$A:$A,"2026-03-31",income_statement!$B:$B,"qtd",income_statement!$C:$C,"provision")+SUMIFS(income_statement!$E:$E,income_statement!$A:$A,"2026-03-31",income_statement!$B:$B,"qtd",income_statement!$C:$C,"noninterest_income")-SUMIFS(income_statement!$E:$E,income_statement!$A:$A,"2026-03-31",income_statement!$B:$B,"qtd",income_statement!$C:$C,"noninterest_expense")+SUMIFS(income_statement!$E:$E,income_statement!$A:$A,"2026-03-31",income_statement!$B:$B,"qtd",income_statement!$C:$C,"one_time") -> 21206.147 | E40: =income_statement_totals!$J$13 -> 21206.147 | F40: =D40-E40 -> 0 | G40: 0.5 | H40: =IF(ABS(F40)<=G40,"PASS","FAIL") -> PASS
A41: 4 | B41: Income statement: NII = interest income - interest expense | C41: 2026-03-31 ytd | D41: =SUMIFS(income_statement!$E:$E,income_statement!$A:$A,"2026-03-31",income_statement!$B:$B,"ytd",income_statement!$C:$C,"interest_income")-SUMIFS(income_statement!$E:$E,income_statement!$A:$A,"2026-03-31",income_statement!$B:$B,"ytd",income_statement!$C:$C,"interest_expense") -> 77032.458 | E41: =income_statement_totals!$M$14 -> 77032.458 | F41: =D41-E41 -> 0 | G41: 0.5 | H41: =IF(ABS(F41)<=G41,"PASS","FAIL") -> PASS
A42: 4 | B42: Income statement: net income ties to components | C42: 2026-03-31 ytd | D42: =SUMIFS(income_statement!$E:$E,income_statement!$A:$A,"2026-03-31",income_statement!$B:$B,"ytd",income_statement!$C:$C,"interest_income")-SUMIFS(income_statement!$E:$E,income_statement!$A:$A,"2026-03-31",income_statement!$B:$B,"ytd",income_statement!$C:$C,"interest_expense")-SUMIFS(income_statement!$E:$E,income_statement!$A:$A,"2026-03-31",income_statement!$B:$B,"ytd",income_statement!$C:$C,"member_giveback")-SUMIFS(income_statement!$E:$E,income_statement!$A:$A,"2026-03-31",income_statement!$B:$B,"ytd",income_statement!$C:$C,"provision")+SUMIFS(income_statement!$E:$E,income_statement!$A:$A,"2026-03-31",income_statement!$B:$B,"ytd",income_statement!$C:$C,"noninterest_income")-SUMIFS(income_statement!$E:$E,income_statement!$A:$A,"2026-03-31",income_statement!$B:$B,"ytd",income_statement!$C:$C,"noninterest_expense")+SUMIFS(income_statement!$E:$E,income_statement!$A:$A,"2026-03-31",income_statement!$B:$B,"ytd",income_statement!$C:$C,"one_time") -> 21206.147 | E42: =income_statement_totals!$J$14 -> 21206.147 | F42: =D42-E42 -> 0 | G42: 0.5 | H42: =IF(ABS(F42)<=G42,"PASS","FAIL") -> PASS
A43: 4 | B43: Income statement: NII = interest income - interest expense | C43: 2026-06-30 qtd | D43: =SUMIFS(income_statement!$E:$E,income_statement!$A:$A,"2026-06-30",income_statement!$B:$B,"qtd",income_statement!$C:$C,"interest_income")-SUMIFS(income_statement!$E:$E,income_statement!$A:$A,"2026-06-30",income_statement!$B:$B,"qtd",income_statement!$C:$C,"interest_expense") -> 78597.801 | E43: =income_statement_totals!$M$15 -> 78597.801 | F43: =D43-E43 -> 0 | G43: 0.5 | H43: =IF(ABS(F43)<=G43,"PASS","FAIL") -> PASS
A44: 4 | B44: Income statement: net income ties to components | C44: 2026-06-30 qtd | D44: =SUMIFS(income_statement!$E:$E,income_statement!$A:$A,"2026-06-30",income_statement!$B:$B,"qtd",income_statement!$C:$C,"interest_income")-SUMIFS(income_statement!$E:$E,income_statement!$A:$A,"2026-06-30",income_statement!$B:$B,"qtd",income_statement!$C:$C,"interest_expense")-SUMIFS(income_statement!$E:$E,income_statement!$A:$A,"2026-06-30",income_statement!$B:$B,"qtd",income_statement!$C:$C,"member_giveback")-SUMIFS(income_statement!$E:$E,income_statement!$A:$A,"2026-06-30",income_statement!$B:$B,"qtd",income_statement!$C:$C,"provision")+SUMIFS(income_statement!$E:$E,income_statement!$A:$A,"2026-06-30",income_statement!$B:$B,"qtd",income_statement!$C:$C,"noninterest_income")-SUMIFS(income_statement!$E:$E,income_statement!$A:$A,"2026-06-30",income_statement!$B:$B,"qtd",income_statement!$C:$C,"noninterest_expense")+SUMIFS(income_statement!$E:$E,income_statement!$A:$A,"2026-06-30",income_statement!$B:$B,"qtd",income_statement!$C:$C,"one_time") -> 33563.912 | E44: =income_statement_totals!$J$15 -> 33563.912 | F44: =D44-E44 -> 0 | G44: 0.5 | H44: =IF(ABS(F44)<=G44,"PASS","FAIL") -> PASS
A45: 5 | B45: NEV = asset FV - liability FV + off-balance (vs. nev_test) | C45: base | D45: =summary!$N$8 -> 1655155.3 | E45: =SUMIFS(nev_test!$C:$C,nev_test!$A:$A,meta!$B$3,nev_test!$B:$B,"internal") -> 1655155.3 | F45: =D45-E45 -> 0 | G45: 1 | H45: =IF(ABS(F45)<=G45,"PASS","FAIL") -> PASS
A46: 5 | B46: NEV ratio uses the same scenario's asset fair value | C46: base | D46: =summary!$O$8 -> 0.1717611 | E46: =SUMIFS(nev_test!$D:$D,nev_test!$A:$A,meta!$B$3,nev_test!$B:$B,"internal") -> 0.1717611 | F46: =D46-E46 -> 0 | G46: 0.0001 | H46: =IF(ABS(F46)<=G46,"PASS","FAIL") -> PASS
A47: 5 | B47: NEV = asset FV - liability FV + off-balance (vs. nev_test) | C47: shock_p300 | D47: =summary!$N$11 -> 1478380.2 | E47: =SUMIFS(nev_test!$E:$E,nev_test!$A:$A,meta!$B$3,nev_test!$B:$B,"internal") -> 1478380.2 | F47: =D47-E47 -> 0 | G47: 1 | H47: =IF(ABS(F47)<=G47,"PASS","FAIL") -> PASS
A48: 5 | B48: NEV ratio uses the same scenario's asset fair value | C48: shock_p300 | D48: =summary!$O$11 -> 0.16520553 | E48: =SUMIFS(nev_test!$F:$F,nev_test!$A:$A,meta!$B$3,nev_test!$B:$B,"internal") -> 0.16520553 | F48: =D48-E48 -> 0 | G48: 0.0001 | H48: =IF(ABS(F48)<=G48,"PASS","FAIL") -> PASS
A49: 5 | B49: NEV = asset FV - liability FV + off-balance (vs. nev_test) | C49: ncua_nev_test | D49: =summary!$N$24 -> 362536.77 | E49: =SUMIFS(nev_test!$E:$E,nev_test!$A:$A,meta!$B$3,nev_test!$B:$B,"ncua_test") -> 362536.77 | F49: =D49-E49 -> 0 | G49: 1 | H49: =IF(ABS(F49)<=G49,"PASS","FAIL") -> PASS
A50: 5 | B50: NEV ratio uses the same scenario's asset fair value | C50: ncua_nev_test | D50: =summary!$O$24 -> 0.040512636 | E50: =SUMIFS(nev_test!$F:$F,nev_test!$A:$A,meta!$B$3,nev_test!$B:$B,"ncua_test") -> 0.040512636 | F50: =D50-E50 -> 0 | G50: 0.0001 | H50: =IF(ABS(F50)<=G50,"PASS","FAIL") -> PASS
A51: 6 | B51: Base Year 1 NII within 15% of trailing 12-month NII (warning only) | C51: base vs TTM | D51: =summary!$F$8 -> 327538.5 | E51: =SUMIFS(income_statement!$E:$E,income_statement!$A:$A,"2025-09-30",income_statement!$B:$B,"qtd",income_statement!$C:$C,"interest_income")-SUMIFS(income_statement!$E:$E,income_statement!$A:$A,"2025-09-30",income_statement!$B:$B,"qtd",income_statement!$C:$C,"interest_expense")+SUMIFS(income_statement!$E:$E,income_statement!$A:$A,"2025-12-31",income_statement!$B:$B,"qtd",income_statement!$C:$C,"interest_income")-SUMIFS(income_statement!$E:$E,income_statement!$A:$A,"2025-12-31",income_statement!$B:$B,"qtd",income_statement!$C:$C,"interest_expense")+SUMIFS(income_statement!$E:$E,income_statement!$A:$A,"2026-03-31",income_statement!$B:$B,"qtd",income_statement!$C:$C,"interest_income")-SUMIFS(income_statement!$E:$E,income_statement!$A:$A,"2026-03-31",income_statement!$B:$B,"qtd",income_statement!$C:$C,"interest_expense")+SUMIFS(income_statement!$E:$E,income_statement!$A:$A,"2026-06-30",income_statement!$B:$B,"qtd",income_statement!$C:$C,"interest_income")-SUMIFS(income_statement!$E:$E,income_statement!$A:$A,"2026-06-30",income_statement!$B:$B,"qtd",income_statement!$C:$C,"interest_expense") -> 292029.7 | F51: =D51/E51-1 -> 0.12159311 | G51: 0.15 | H51: =IF(ABS(F51)<=G51,"PASS","WARN") -> PASS
A52: 7 | B52: Every policy limit references an existing metric | C52: policy_limits | D52: =COUNTIF(policy_limits!$K$2:$K$40,"n") -> 0 | E52: 0 | F52: =D52-E52 -> 0 | G52: 0 | H52: =IF(D52=0,"PASS","FAIL") -> PASS
A53: 7 | B53: Every policy limit references an existing scenario | C53: policy_limits | D53: =COUNTIF(policy_limits!$L$2:$L$40,"n") -> 0 | E53: 0 | F53: =D53-E53 -> 0 | G53: 0 | H53: =IF(D53=0,"PASS","FAIL") -> PASS
A54: 8 | B54: No duplicate product keys per period | C54: loans | D54: =MAX(loans!$AI$2:$AI$15) -> 1 | E54: 1 | F54: =D54-E54 -> 0 | G54: 0 | H54: =IF(D54<=1,"PASS","FAIL") -> PASS
A55: 8 | B55: No duplicate product keys per period | C55: deposits | D55: =MAX(deposits!$W$2:$W$14) -> 1 | E55: 1 | F55: =D55-E55 -> 0 | G55: 0 | H55: =IF(D55<=1,"PASS","FAIL") -> PASS
A56: 8 | B56: No duplicate product keys per period | C56: investments | D56: =MAX(investments!$O$2:$O$11) -> 1 | E56: 1 | F56: =D56-E56 -> 0 | G56: 0 | H56: =IF(D56<=1,"PASS","FAIL") -> PASS
A57: 8 | B57: Mix shares sum to 100% | C57: loans | D57: =SUM(loans!$AJ$2:$AJ$15) -> 1 | E57: 1 | F57: =D57-E57 -> 0 | G57: 0.0001 | H57: =IF(ABS(F57)<=G57,"PASS","FAIL") -> PASS
A58: 8 | B58: Mix shares sum to 100% | C58: deposits | D58: =SUM(deposits!$X$2:$X$14) -> 1 | E58: 1 | F58: =D58-E58 -> 0 | G58: 0.0001 | H58: =IF(ABS(F58)<=G58,"PASS","FAIL") -> PASS
A59: 9 | B59: History has no missing quarters (every step = 1 quarter) | C59: history | D59: =MIN(history!$AF$3:$AF$24) -> 1 | E59: =MAX(history!$AF$3:$AF$24) -> 1 | F59: =E59-D59 -> 0 | G59: 0 | H59: =IF(AND(D59=1,E59=1),"PASS","FAIL") -> PASS
A60: 10 | B60: Rates dated after the as-of date (rate-drift chip) | C60: count of observations after as-of | D60: =SUMPRODUCT(--(rates_history!$A$2:$A$578>meta!$B$3)) -> 95 | E60: 0 | F60: =D60-E60 -> 95 | G60: 0 | H60: =IF(D60>0,"CHIP ON","CHIP OFF") -> CHIP ON
A61: 10 | B61: 10-year Treasury drift since as-of (bp) | C61: latest curve vs. as-of curve | D61: =(SUMIFS(rates_history!$C:$C,rates_history!$A:$A,meta!$B$13,rates_history!$B:$B,"10y")-SUMIFS(rates_history!$C:$C,rates_history!$A:$A,meta!$B$3,rates_history!$B:$B,"10y"))*10000 -> 82 | E61: 0 | F61: =D61-E61 -> 82 | G61: 0 | H61: ="info" -> info
A62: 11 | B62: AFS fair value (investments) = balance sheet AFS lines | C62: 2026-06-30 | D62: =SUMIFS(investments!$E:$E,investments!$A:$A,meta!$B$3,investments!$C:$C,"afs") -> 1958274.3 | E62: =SUMPRODUCT((balance_sheet!$A$2:$A$400=meta!$B$3)*(LEFT(balance_sheet!$O$2:$O$400,4)="afs_")*balance_sheet!$E$2:$E$400) -> 1958274.3 | F62: =D62-E62 -> 0 | G62: 0.001 | H62: =IF(ABS(F62)<=G62*ABS(E62),"PASS","FAIL") -> PASS
A63: 11 | B63: AFS fair value ties to call report ($1,958,274K) | C63: 2026-06-30 | D63: =SUMIFS(investments!$E:$E,investments!$A:$A,meta!$B$3,investments!$C:$C,"afs") -> 1958274.3 | E63: 1958274.3 | F63: =D63-E63 -> -1.107296e-05 | G63: 0.0001 | H63: =IF(ABS(F63)<=G63*ABS(E63),"PASS","FAIL") -> PASS
A64: 11 | B64: HTM amortized cost ties to call report ($1,348,404K) | C64: 2026-06-30 | D64: =SUMIFS(investments!$D:$D,investments!$A:$A,meta!$B$3,investments!$C:$C,"htm") -> 1348403.7 | E64: 1348403.7 | F64: =D64-E64 -> 0 | G64: 0.0001 | H64: =IF(ABS(F64)<=G64*ABS(E64),"PASS","FAIL") -> PASS
A65: 11 | B65: Certificate maturities = certificate + IRA certificate balances | C65: 2026-06-30 | D65: =SUM(cert_maturities!$C:$C) -> 1706878.8 | E65: =SUMIFS(deposits!$E:$E,deposits!$B:$B,"certificates")+SUMIFS(deposits!$E:$E,deposits!$D:$D,"ira_certificates") -> 1706878.8 | F65: =D65-E65 -> 0 | G65: 0.001 | H65: =IF(ABS(F65)<=G65*ABS(E65),"PASS","FAIL") -> PASS
A66: 11 | B66: Investment cash flows: principal + prepayments = securities book (ex-equity) | C66: 2026-06-30 | D66: =SUM(investment_cashflows!$B:$B)+SUM(investment_cashflows!$D:$D) -> 3563284.2 | E66: =SUMIFS(investments!$D:$D,investments!$A:$A,meta!$B$3,investments!$C:$C,"afs")+SUMIFS(investments!$D:$D,investments!$A:$A,meta!$B$3,investments!$C:$C,"htm") -> 3563284.2 | F66: =D66-E66 -> 0 | G66: 0.001 | H66: =IF(ABS(F66)<=G66*ABS(E66),"PASS","FAIL") -> PASS
A67: 11 | B67: Net worth ratio (4-quarter method) matches reported 12.1% (within 5bp) | C67: 2026-06-30 | D67: =summary!$C$43 -> 0.12095821 | E67: 0.121 | F67: =D67-E67 -> -4.1788306e-05 | G67: 0.0005 | H67: =IF(ABS(F67)<=G67,"PASS","FAIL") -> PASS
A68: 11 | B68: rate_scenarios rows = scenarios x 25 months x 14 tenors | C68: rate_scenarios | D68: =COUNTA(rate_scenarios!$A$2:$A$7001) -> 7000 | E68: =COUNTA(scenarios!$A$2:$A$100)*25*14 -> 7000 | F68: =D68-E68 -> 0 | G68: 0 | H68: =IF(F68=0,"PASS","FAIL") -> PASS
A69: 11 | B69: nii_simulation rows = scenarios x 24 months | C69: nii_simulation | D69: =COUNTA(nii_simulation!$A$2:$A$481) -> 480 | E69: =COUNTA(scenarios!$A$2:$A$100)*24 -> 480 | F69: =D69-E69 -> 0 | G69: 0 | H69: =IF(F69=0,"PASS","FAIL") -> PASS
A70: 11 | B70: Balance sheet equity = net worth + AOCI (capital tab) | C70: 2026-06-30 | D70: =SUMIFS(balance_sheet!$E:$E,balance_sheet!$A:$A,meta!$B$3,balance_sheet!$B:$B,"equity") -> 907826.51 | E70: =capital!$B$24+capital!$G$24 -> 907826.51 | F70: =D70-E70 -> 0 | G70: 0.001 | H70: =IF(ABS(F70)<=G70*ABS(E70),"PASS","FAIL") -> PASS
B72: Checks failed | D72: =COUNTIF(H5:H70,"FAIL") -> 0
B73: Warnings | D73: =COUNTIF(H5:H70,"WARN") -> 0
B74: Data status chip | D74: =IF(D72=0,"Validated",D72&" checks failed") -> Validated

Sheet meta
A1: key | B1: value | C1: description
A2: institution | B2: Desert Financial Credit Union (hypothetical concept; NCUA charter 68713) | C2: Subject institution. Hypothetical concept built from public data.
A3: as_of_date | B3: 2026-06-30 | C3: Balance sheet and model as-of date (latest call report)
A4: units | B4: USD thousands | C4: All dollar amounts are in thousands; rates and ratios are decimals
A5: nwr_method | B5: four_quarter_average | C5: Net worth / average of the current and three prior quarter-end total assets (matches reported 12.1% at June 30, 2026)
A6: capital_target_nwr | B6: 0.11 | C6: Board capital target (hypothetical)
A7: watch_pct_default | B7: 0.75 | C7: Utilization at which a maximum or max-decline limit turns Watch
A8: min_watch_buffer | B8: 0.1 | C8: A minimum limit turns Watch within this fraction above the minimum
A9: peer_group | B9: cu_5b_20b | C9: Default peer set in peers (hypothetical placeholder values)
A10: disclaimer | B10: Hypothetical concept built from public data. Not affiliated with or endorsed by Desert Financial Credit Union. | C10: Show on every page and export
A11: model_version | B11: DFCU ALM model v1.0 (built 2026-09-30) | C11: Python model in model/ (run build_all.py)
A12: data_cutoff | B12: 2026-09-29 | C12: Latest market data used (Treasury curve Sept 29, 2026)
A13: rate_drift_curve_date | B13: 2026-09-29 | C13: Curve newer than the as-of date (drives the rate-drift chip)
A14: cculr_elected | B14: y | C14: Complex credit union leverage ratio elected (CreditUnionsOnline)
A15: cculr_threshold | B15: 0.09 | C15: CCULR well-capitalized net worth ratio
A16: well_capitalized_nwr | B16: 0.07 | C16: Statutory well-capitalized NWR used in the MBL cap
A17: mbl_multiple | B17: 1.75 | C17: MBL cap multiple (12 CFR 723.8)
A18: nev_test_low_ratio | B18: 0.07 | C18: NEV Test: Low requires post-shock NEV ratio above 7%
A19: nev_test_high_ratio | B19: 0.04 | C19: NEV Test: High if post-shock NEV ratio below 4%
A20: nev_test_low_sensitivity | B20: 0.4 | C20: NEV Test: Low requires NEV decline under 40%
A21: nev_test_high_sensitivity | B21: 0.65 | C21: NEV Test: High if NEV decline exceeds 65%
A22: threshold_10b | B22: 10000000 | C22: Asset threshold for capital planning, Durbin coverage and CFPB ($K)
A23: nii_definition | B23: excludes Member Giveback Bonus | C23: NII = interest income - interest expense; the giveback is reported within dividends by DFCU but is its own category here
A24: giveback_recognition | B24: Q1 dividends when paid (inferred) | C24: See notes: consistent with the Q1 2026 earnings dip and dividend-cost dynamics
A25: scenario_start | B25: 2026-07-01 | C25: Month 1 of every scenario is July 2026
A26: fiscal_year_end | B26: 12-31 | C26: Calendar fiscal year

Sheet balance_sheet
A1: period | B1: section | C1: category | D1: line_item | E1: balance | F1: avg_balance | G1: rate | H1: rate_type | I1: index | J1: wal_years | K1: eff_duration | L1: eff_convexity | M1: provenance | N1: source | O1: line_key | P1: amortized_cost | Q1: fair_value_base
A2: 2020-12-31 | B2: asset | C2: cash | D2: Cash and cash equivalents | E2: 558933.19 | H2: none | I2: sofr | M2: audited | N2: Desert Financial 2021 Annual Report (audited FY2020)
A3: 2020-12-31 | B3: asset | C3: investments | D3: Equity securities | E3: 114014.09 | H3: none | I3: none | M3: audited | N3: Desert Financial 2021 Annual Report (audited FY2020)
A4: 2020-12-31 | B4: asset | C4: investments | D4: Securities available for sale (fair value) | E4: 1893344.8 | H4: none | I4: none | M4: audited | N4: Desert Financial 2021 Annual Report (audited FY2020)
A5: 2020-12-31 | B5: asset | C5: investments | D5: Securities held to maturity (amortized cost) | E5: 1447713.2 | H5: none | I5: none | M5: audited | N5: Desert Financial 2021 Annual Report (audited FY2020)
A6: 2020-12-31 | B6: asset | C6: investments | D6: FHLB stock | E6: 17250 | H6: none | I6: none | M6: audited | N6: Desert Financial 2021 Annual Report (audited FY2020)
A7: 2020-12-31 | B7: asset | C7: loans_hfs | D7: Loans held for sale | E7: 6015.74 | H7: none | I7: none | M7: audited | N7: Desert Financial 2021 Annual Report (audited FY2020)
A8: 2020-12-31 | B8: asset | C8: loans | D8: Loans, net of allowance for credit losses | E8: 2333705 | H8: fixed | I8: none | M8: audited | N8: Desert Financial 2021 Annual Report (audited FY2020)
A9: 2020-12-31 | B9: asset | C9: other_assets | D9: Accrued interest receivable | E9: 19853.458 | H9: none | I9: none | M9: audited | N9: Desert Financial 2021 Annual Report (audited FY2020)
A10: 2020-12-31 | B10: asset | C10: other_assets | D10: Prepaid expenses and other assets | E10: 43100.662 | H10: none | I10: none | M10: audited | N10: Desert Financial 2021 Annual Report (audited FY2020)
A11: 2020-12-31 | B11: asset | C11: other_assets | D11: Credit union-owned life insurance | E11: 74359.306 | H11: none | I11: none | M11: audited | N11: Desert Financial 2021 Annual Report (audited FY2020)
A12: 2020-12-31 | B12: asset | C12: other_assets | D12: Mortgage servicing rights | E12: 9131.968 | H12: none | I12: none | M12: audited | N12: Desert Financial 2021 Annual Report (audited FY2020)
A13: 2020-12-31 | B13: asset | C13: other_assets | D13: Premises and equipment, net | E13: 72862.061 | H13: none | I13: none | M13: audited | N13: Desert Financial 2021 Annual Report (audited FY2020)
... A20: 2020-12-31 | B20: equity | C20: equity | D20: Accumulated other comprehensive income (loss) | E20: 39342.022 | H20: none | I20: none | M20: audited | N20: Desert Financial 2021 Annual Report (audited FY2020)
A21: 2021-12-31 | B21: asset | C21: cash | D21: Cash and cash equivalents | E21: 601184.08 | F21: 580058.64 | H21: none | I21: sofr | M21: audited | N21: Desert Financial 2021 Annual Report (audited FY2021)
A22: 2021-12-31 | B22: asset | C22: investments | D22: Equity securities | E22: 1348.898 | F22: 57681.494 | H22: none | I22: none | M22: audited | N22: Desert Financial 2021 Annual Report (audited FY2021)
A23: 2021-12-31 | B23: asset | C23: investments | D23: Securities available for sale (fair value) | E23: 2791744.8 | F23: 2342544.8 | H23: none | I23: none | M23: audited | N23: Desert Financial 2021 Annual Report (audited FY2021)
A24: 2021-12-31 | B24: asset | C24: investments | D24: Securities held to maturity (amortized cost) | E24: 1684913.3 | F24: 1566313.2 | H24: none | I24: none | M24: audited | N24: Desert Financial 2021 Annual Report (audited FY2021)
A25: 2021-12-31 | B25: asset | C25: investments | D25: FHLB stock | E25: 17250 | F25: 17250 | H25: none | I25: none | M25: audited | N25: Desert Financial 2021 Annual Report (audited FY2021)
A26: 2021-12-31 | B26: asset | C26: loans_hfs | D26: Loans held for sale | E26: 4679.303 | F26: 5347.5215 | H26: none | I26: none | M26: audited | N26: Desert Financial 2021 Annual Report (audited FY2021)
A27: 2021-12-31 | B27: asset | C27: loans | D27: Loans, net of allowance for credit losses | E27: 2701948.3 | F27: 2517826.7 | G27: 0.037633095 | H27: fixed | I27: none | M27: audited | N27: Desert Financial 2021 Annual Report (audited FY2021)
A28: 2021-12-31 | B28: asset | C28: other_assets | D28: Accrued interest receivable | E28: 20506.772 | F28: 20180.115 | H28: none | I28: none | M28: audited | N28: Desert Financial 2021 Annual Report (audited FY2021)
A29: 2021-12-31 | B29: asset | C29: other_assets | D29: Prepaid expenses and other assets | E29: 62288.362 | F29: 52694.512 | H29: none | I29: none | M29: audited | N29: Desert Financial 2021 Annual Report (audited FY2021)
A30: 2021-12-31 | B30: asset | C30: other_assets | D30: Visa class B stock | E30: 42447.963 | F30: 21223.982 | H30: none | I30: none | M30: audited | N30: Desert Financial 2021 Annual Report (audited FY2021)
A31: 2021-12-31 | B31: asset | C31: other_assets | D31: Credit union-owned life insurance | E31: 134148.9 | F31: 104254.1 | H31: none | I31: none | M31: audited | N31: Desert Financial 2021 Annual Report (audited FY2021)
A32: 2021-12-31 | B32: asset | C32: other_assets | D32: Mortgage servicing rights | E32: 11573.593 | F32: 10352.781 | H32: none | I32: none | M32: audited | N32: Desert Financial 2021 Annual Report (audited FY2021)
A33: 2021-12-31 | B33: asset | C33: other_assets | D33: Premises and equipment, net | E33: 71768.086 | F33: 72315.073 | H33: none | I33: none | M33: audited | N33: Desert Financial 2021 Annual Report (audited FY2021)
A34: 2021-12-31 | B34: asset | C34: other_assets | D34: NCUSIF deposit | E34: 60571.032 | F34: 54118.654 | H34: none | I34: none | M34: audited | N34: Desert Financial 2021 Annual Report (audited FY2021)
A35: 2021-12-31 | B35: liability | C35: shares | D35: Members' shares and savings accounts | E35: 7140002 | F35: 6369503.9 | G35: 0.0025495468 | H35: variable | I35: none | M35: audited | N35: Desert Financial 2021 Annual Report (audited FY2021)
A36: 2021-12-31 | B36: liability | C36: borrowings | D36: Borrowed funds | E36: 200000 | F36: 202500 | G36: 0.019921121 | H36: fixed | I36: none | M36: audited | N36: Desert Financial 2021 Annual Report (audited FY2021)
A37: 2021-12-31 | B37: liability | C37: other_liabilities | D37: Accrued expenses and other liabilities | E37: 94329.952 | F37: 84210.221 | H37: none | I37: none | M37: audited | N37: Desert Financial 2021 Annual Report (audited FY2021)
A38: 2021-12-31 | B38: equity | C38: equity | D38: Regular reserve | E38: 29788.065 | F38: 29788.065 | H38: none | I38: none | M38: audited | N38: Desert Financial 2021 Annual Report (audited FY2021)
A39: 2021-12-31 | B39: equity | C39: equity | D39: Undivided earnings | E39: 778165.22 | F39: 734444.31 | H39: none | I39: none | M39: audited | N39: Desert Financial 2021 Annual Report (audited FY2021)
A40: 2021-12-31 | B40: equity | C40: equity | D40: Accumulated other comprehensive income (loss) | E40: -35911.86 | F40: 1715.081 | H40: none | I40: none | M40: audited | N40: Desert Financial 2021 Annual Report (audited FY2021)
A41: 2022-12-31 | B41: asset | C41: cash | D41: Cash and cash equivalents | E41: 196813.41 | F41: 398998.75 | H41: none | I41: sofr | M41: audited | N41: Desert Financial 2023 Annual Report (audited FY2022)
A42: 2022-12-31 | B42: asset | C42: investments | D42: Equity securities | E42: 1561.391 | F42: 1455.1445 | H42: none | I42: none | M42: audited | N42: Desert Financial 2023 Annual Report (audited FY2022)
A43: 2022-12-31 | B43: asset | C43: investments | D43: Securities available for sale (fair value) | E43: 2190628.8 | F43: 2491186.8 | H43: none | I43: none | M43: audited | N43: Desert Financial 2023 Annual Report (audited FY2022)
A44: 2022-12-31 | B44: asset | C44: investments | D44: Securities held to maturity (amortized cost) | E44: 1648865 | F44: 1666889.1 | H44: none | I44: none | M44: audited | N44: Desert Financial 2023 Annual Report (audited FY2022)
A45: 2022-12-31 | B45: asset | C45: investments | D45: FHLB stock | E45: 17250 | F45: 17250 | H45: none | I45: none | M45: audited | N45: Desert Financial 2023 Annual Report (audited FY2022)
A46: 2022-12-31 | B46: asset | C46: loans_hfs | D46: Loans held for sale | E46: 1434.25 | F46: 3056.7765 | H46: none | I46: none | M46: audited | N46: Desert Financial 2023 Annual Report (audited FY2022)
A47: 2022-12-31 | B47: asset | C47: loans | D47: Loans, net of allowance for credit losses | E47: 3745977.2 | F47: 3223962.7 | G47: 0.040259781 | H47: fixed | I47: none | M47: audited | N47: Desert Financial 2023 Annual Report (audited FY2022)
A48: 2022-12-31 | B48: asset | C48: other_assets | D48: Accrued interest receivable | E48: 21711.637 | F48: 21109.204 | H48: none | I48: none | M48: audited | N48: Desert Financial 2023 Annual Report (audited FY2022)
A49: 2022-12-31 | B49: asset | C49: other_assets | D49: Prepaid expenses and other assets | E49: 84679.897 | F49: 73484.129 | H49: none | I49: none | M49: audited | N49: Desert Financial 2023 Annual Report (audited FY2022)
A50: 2022-12-31 | B50: asset | C50: other_assets | D50: Visa class B stock | E50: 38541.33 | F50: 40494.647 | H50: none | I50: none | M50: audited | N50: Desert Financial 2023 Annual Report (audited FY2022)
A51: 2022-12-31 | B51: asset | C51: other_assets | D51: Credit union-owned life insurance | E51: 98168.96 | F51: 116158.93 | H51: none | I51: none | M51: audited | N51: Desert Financial 2023 Annual Report (audited FY2022)
A52: 2022-12-31 | B52: asset | C52: other_assets | D52: Mortgage servicing rights | E52: 10626.272 | F52: 11099.933 | H52: none | I52: none | M52: audited | N52: Desert Financial 2023 Annual Report (audited FY2022)
A53: 2022-12-31 | B53: asset | C53: other_assets | D53: Premises and equipment, net | E53: 64946.194 | F53: 68357.14 | H53: none | I53: none | M53: audited | N53: Desert Financial 2023 Annual Report (audited FY2022)
A54: 2022-12-31 | B54: asset | C54: other_assets | D54: NCUSIF deposit | E54: 71077.593 | F54: 65824.312 | H54: none | I54: none | M54: audited | N54: Desert Financial 2023 Annual Report (audited FY2022)
A55: 2022-12-31 | B55: liability | C55: shares | D55: Members' shares and savings accounts | E55: 7556395.9 | F55: 7348198.9 | G55: 0.0029679991 | H55: variable | I55: none | M55: audited | N55: Desert Financial 2023 Annual Report (audited FY2022)
A56: 2022-12-31 | B56: liability | C56: borrowings | D56: Borrowed funds | E56: 0 | F56: 100000 | H56: none | I56: none | M56: audited | N56: Desert Financial 2023 Annual Report (audited FY2022)
A57: 2022-12-31 | B57: liability | C57: other_liabilities | D57: Accrued expenses and other liabilities | E57: 133364.52 | F57: 113847.24 | H57: none | I57: none | M57: audited | N57: Desert Financial 2023 Annual Report (audited FY2022)
A58: 2022-12-31 | B58: liability | C58: other_liabilities | D58: Online and debit card clearing | E58: 33973.868 | F58: 16986.934 | H58: none | I58: none | M58: audited | N58: Desert Financial 2023 Annual Report (audited FY2022)
A59: 2022-12-31 | B59: equity | C59: equity | D59: Undivided earnings | E59: 893976.15 | F59: 836070.68 | H59: none | I59: none | M59: audited | N59: Desert Financial 2023 Annual Report (audited FY2022)
A60: 2022-12-31 | B60: equity | C60: equity | D60: Accumulated other comprehensive income (loss) | E60: -425428.55 | F60: -230670.21 | H60: none | I60: none | M60: audited | N60: Desert Financial 2023 Annual Report (audited FY2022)
A61: 2023-12-31 | B61: asset | C61: cash | D61: Cash and cash equivalents | E61: 669705.65 | F61: 433259.53 | H61: none | I61: sofr | M61: audited | N61: Desert Financial 2023 Annual Report (audited FY2023)
A62: 2023-12-31 | B62: asset | C62: investments | D62: Equity securities | E62: 2401.479 | F62: 1981.435 | H62: none | I62: none | M62: audited | N62: Desert Financial 2023 Annual Report (audited FY2023)
A63: 2023-12-31 | B63: asset | C63: investments | D63: Securities available for sale (fair value) | E63: 2041804.4 | F63: 2116216.6 | H63: none | I63: none | M63: audited | N63: Desert Financial 2023 Annual Report (audited FY2023)
A64: 2023-12-31 | B64: asset | C64: investments | D64: Securities held to maturity (amortized cost) | E64: 1528697.9 | F64: 1588781.5 | H64: none | I64: none | M64: audited | N64: Desert Financial 2023 Annual Report (audited FY2023)
A65: 2023-12-31 | B65: asset | C65: investments | D65: FHLB stock | E65: 17250 | F65: 17250 | H65: none | I65: none | M65: audited | N65: Desert Financial 2023 Annual Report (audited FY2023)
A66: 2023-12-31 | B66: asset | C66: loans_hfs | D66: Loans held for sale | E66: 2087.123 | F66: 1760.6865 | H66: none | I66: none | M66: audited | N66: Desert Financial 2023 Annual Report (audited FY2023)
A67: 2023-12-31 | B67: asset | C67: loans | D67: Loans, net of allowance for credit losses | E67: 3980284 | F67: 3863130.6 | G67: 0.051049567 | H67: fixed | I67: none | M67: audited | N67: Desert Financial 2023 Annual Report (audited FY2023)
A68: 2023-12-31 | B68: asset | C68: other_assets | D68: Accrued interest receivable | E68: 24428.991 | F68: 23070.314 | H68: none | I68: none | M68: audited | N68: Desert Financial 2023 Annual Report (audited FY2023)
A69: 2023-12-31 | B69: asset | C69: other_assets | D69: Prepaid expenses and other assets | E69: 119465.59 | F69: 102072.74 | H69: none | I69: none | M69: audited | N69: Desert Financial 2023 Annual Report (audited FY2023)
A70: 2023-12-31 | B70: asset | C70: other_assets | D70: Visa class B stock | E70: 48641.774 | F70: 43591.552 | H70: none | I70: none | M70: audited | N70: Desert Financial 2023 Annual Report (audited FY2023)
A71: 2023-12-31 | B71: asset | C71: other_assets | D71: Credit union-owned life insurance | E71: 68140.148 | F71: 83154.554 | H71: none | I71: none | M71: audited | N71: Desert Financial 2023 Annual Report (audited FY2023)
A72: 2023-12-31 | B72: asset | C72: other_assets | D72: Split-dollar life insurance arrangements | E72: 66871.083 | F72: 33435.541 | H72: none | I72: none | M72: audited | N72: Desert Financial 2023 Annual Report (audited FY2023)
A73: 2023-12-31 | B73: asset | C73: other_assets | D73: Mortgage servicing rights | E73: 8951.029 | F73: 9788.6505 | H73: none | I73: none | M73: audited | N73: Desert Financial 2023 Annual Report (audited FY2023)
A74: 2023-12-31 | B74: asset | C74: other_assets | D74: Premises and equipment, net | E74: 62080.668 | F74: 63513.431 | H74: none | I74: none | M74: audited | N74: Desert Financial 2023 Annual Report (audited FY2023)
A75: 2023-12-31 | B75: asset | C75: other_assets | D75: NCUSIF deposit | E75: 69753.949 | F75: 70415.771 | H75: none | I75: none | M75: audited | N75: Desert Financial 2023 Annual Report (audited FY2023)
A76: 2023-12-31 | B76: liability | C76: shares | D76: Members' shares and savings accounts | E76: 7303801.3 | F76: 7430098.6 | G76: 0.010853302 | H76: variable | I76: none | M76: audited | N76: Desert Financial 2023 Annual Report (audited FY2023)
A77: 2023-12-31 | B77: liability | C77: borrowings | D77: Borrowed funds | E77: 600000 | F77: 300000 | H77: none | I77: none | M77: audited | N77: Desert Financial 2023 Annual Report (audited FY2023)
A78: 2023-12-31 | B78: liability | C78: other_liabilities | D78: Accrued expenses and other liabilities | E78: 146677.68 | F78: 140021.1 | H78: none | I78: none | M78: audited | N78: Desert Financial 2023 Annual Report (audited FY2023)
A79: 2023-12-31 | B79: liability | C79: other_liabilities | D79: Online and debit card clearing | E79: 49601.112 | F79: 41787.49 | H79: none | I79: none | M79: audited | N79: Desert Financial 2023 Annual Report (audited FY2023)
A80: 2023-12-31 | B80: equity | C80: equity | D80: Undivided earnings | E80: 960070.69 | F80: 927023.42 | H80: none | I80: none | M80: audited | N80: Desert Financial 2023 Annual Report (audited FY2023)
A81: 2023-12-31 | B81: equity | C81: equity | D81: Accumulated other comprehensive income (loss) | E81: -349586.97 | F81: -387507.76 | H81: none | I81: none | M81: audited | N81: Desert Financial 2023 Annual Report (audited FY2023)
A82: 2024-12-31 | B82: asset | C82: cash | D82: Cash and cash equivalents | E82: 441895.49 | F82: 555800.57 | G82: 0.065861268 | H82: variable | I82: sofr | M82: audited | N82: Desert Financial 2025 Annual Report (audited FY2024)
A83: 2024-12-31 | B83: asset | C83: investments | D83: Securities available for sale (fair value) | E83: 2051268.5 | F83: 2046536.4 | H83: none | I83: none | M83: audited | N83: Desert Financial 2025 Annual Report (audited FY2024)
A84: 2024-12-31 | B84: asset | C84: investments | D84: Securities held to maturity (amortized cost) | E84: 1538373.2 | F84: 1533535.6 | H84: none | I84: none | M84: audited | N84: Desert Financial 2025 Annual Report (audited FY2024)
A85: 2024-12-31 | B85: asset | C85: investments | D85: FHLB stock | E85: 17250 | F85: 17250 | H85: none | I85: none | M85: audited | N85: Desert Financial 2025 Annual Report (audited FY2024)
A86: 2024-12-31 | B86: asset | C86: loans | D86: Loans, gross | E86: 4319422.9 | F86: 4169003.4 | G86: 0.059144791 | H86: fixed | I86: none | M86: audited | N86: Desert Financial 2025 Annual Report (audited FY2024) (loans net plus allowance)
A87: 2024-12-31 | B87: asset | C87: acl | D87: Allowance for credit losses | E87: -39273.608 | H87: none | I87: none | M87: audited | N87: Desert Financial 2025 Annual Report (audited FY2024)
A88: 2024-12-31 | B88: asset | C88: other_assets | D88: Accrued interest receivable | E88: 26575.986 | F88: 25502.488 | H88: none | I88: none | M88: audited | N88: Desert Financial 2025 Annual Report (audited FY2024)
A89: 2024-12-31 | B89: asset | C89: other_assets | D89: Prepaid expenses and other assets | E89: 85046.397 | F89: 102255.99 | H89: none | I89: none | M89: audited | N89: Desert Financial 2025 Annual Report (audited FY2024)
A90: 2024-12-31 | B90: asset | C90: other_assets | D90: Visa class B stock | E90: 33614.905 | F90: 41128.34 | H90: none | I90: none | M90: audited | N90: Desert Financial 2025 Annual Report (audited FY2024)
A91: 2024-12-31 | B91: asset | C91: other_assets | D91: Credit union-owned life insurance | E91: 71281.005 | F91: 69710.576 | H91: none | I91: none | M91: audited | N91: Desert Financial 2025 Annual Report (audited FY2024)
A92: 2024-12-31 | B92: asset | C92: other_assets | D92: Split-dollar life insurance arrangements | E92: 99589.211 | F92: 83230.147 | H92: none | I92: none | M92: audited | N92: Desert Financial 2025 Annual Report (audited FY2024)
A93: 2024-12-31 | B93: asset | C93: other_assets | D93: Mortgage servicing rights | E93: 7683.064 | F93: 8317.0465 | H93: none | I93: none | M93: audited | N93: Desert Financial 2025 Annual Report (audited FY2024)
A94: 2024-12-31 | B94: asset | C94: other_assets | D94: Premises and equipment, net | E94: 59883.833 | F94: 60982.251 | H94: none | I94: none | M94: audited | N94: Desert Financial 2025 Annual Report (audited FY2024)
A95: 2024-12-31 | B95: asset | C95: other_assets | D95: NCUSIF deposit | E95: 71015.879 | F95: 70384.914 | H95: none | I95: none | M95: audited | N95: Desert Financial 2025 Annual Report (audited FY2024)
A96: 2024-12-31 | B96: liability | C96: shares | D96: Members' shares and savings accounts | E96: 7963194.5 | F96: 7633497.9 | G96: 0.017809324 | H96: variable | I96: none | M96: audited | N96: Desert Financial 2025 Annual Report (audited FY2024)
A97: 2024-12-31 | B97: liability | C97: borrowings | D97: Borrowed funds | E97: 0 | F97: 300000 | H97: none | I97: none | M97: audited | N97: Desert Financial 2025 Annual Report (audited FY2024)
A98: 2024-12-31 | B98: liability | C98: other_liabilities | D98: Accrued expenses and other liabilities | E98: 115481.15 | F98: 131079.41 | H98: none | I98: none | M98: audited | N98: Desert Financial 2025 Annual Report (audited FY2024)
A99: 2024-12-31 | B99: liability | C99: other_liabilities | D99: Online and debit card clearing | E99: 19320.677 | F99: 34460.895 | H99: none | I99: none | M99: audited | N99: Desert Financial 2025 Annual Report (audited FY2024)
A100: 2024-12-31 | B100: equity | C100: equity | D100: Undivided earnings | E100: 1032287.8 | F100: 996179.25 | H100: none | I100: none | M100: audited | N100: Desert Financial 2025 Annual Report (audited FY2024)
A101: 2024-12-31 | B101: equity | C101: equity | D101: Accumulated other comprehensive income (loss) | E101: -346657.37 | F101: -348122.17 | H101: none | I101: none | M101: audited | N101: Desert Financial 2025 Annual Report (audited FY2024)
A102: 2025-12-31 | B102: asset | C102: cash | D102: Cash and cash equivalents | E102: 466601.3 | F102: 454248.39 | G102: 0.051577246 | H102: variable | I102: sofr | M102: audited | N102: Desert Financial 2025 Annual Report (audited FY2025)
A103: 2025-12-31 | B103: asset | C103: investments | D103: Securities available for sale (fair value) | E103: 2052971.7 | F103: 2052120.1 | H103: none | I103: none | M103: audited | N103: Desert Financial 2025 Annual Report (audited FY2025)
A104: 2025-12-31 | B104: asset | C104: investments | D104: Securities held to maturity (amortized cost) | E104: 1432733.2 | F104: 1485553.2 | H104: none | I104: none | M104: audited | N104: Desert Financial 2025 Annual Report (audited FY2025)
A105: 2025-12-31 | B105: asset | C105: investments | D105: FHLB stock | E105: 17250 | F105: 17250 | H105: none | I105: none | M105: audited | N105: Desert Financial 2025 Annual Report (audited FY2025)
A106: 2025-12-31 | B106: asset | C106: loans | D106: Loans, gross | E106: 4998963.5 | F106: 4659193.2 | G106: 0.063229759 | H106: fixed | I106: none | M106: audited | N106: Desert Financial 2025 Annual Report (audited FY2025) (loans net plus allowance)
...

Sheet income_statement
A1: period | B1: basis | C1: category | D1: line_item | E1: amount | F1: provenance | G1: source
A2: 2020-12-31 | B2: ytd | C2: interest_income | D2: Interest on loans | E2: 91018.771 | F2: audited | G2: Desert Financial 2021 Annual Report (audited FY2020)
A3: 2020-12-31 | B3: ytd | C3: interest_income | D3: Interest on investments (incl. cash) | E3: 66327.688 | F3: audited | G3: Desert Financial 2021 Annual Report (audited FY2020)
A4: 2020-12-31 | B4: ytd | C4: interest_expense | D4: Dividends on shares, excluding Member Giveback Bonus | E4: 23323.156 | F4: modeled | G4: Desert Financial 2021 Annual Report (audited FY2020); audited dividends less the giveback paid in the year (classification inferred)
A5: 2020-12-31 | B5: ytd | C5: interest_expense | D5: Interest on borrowed funds | E5: 1289.674 | F5: audited | G5: Desert Financial 2021 Annual Report (audited FY2020)
A6: 2020-12-31 | B6: ytd | C6: member_giveback | D6: Member Giveback Bonus (paid in February; within dividends as reported) | E6: 9000 | F6: modeled | G6: Desert Financial annual reports and press releases (amount); classification inferred
A7: 2020-12-31 | B7: ytd | C7: provision | D7: Provision for credit losses | E7: 13133.373 | F7: audited | G7: Desert Financial 2021 Annual Report (audited FY2020)
A8: 2020-12-31 | B8: ytd | C8: noninterest_income | D8: Fees and service charges | E8: 42216.268 | F8: audited | G8: Desert Financial 2021 Annual Report (audited FY2020)
A9: 2020-12-31 | B9: ytd | C9: noninterest_income | D9: Interchange income | E9: 36043.388 | F9: audited | G9: Desert Financial 2021 Annual Report (audited FY2020)
A10: 2020-12-31 | B10: ytd | C10: noninterest_income | D10: Gains on sales of loans | E10: 26115.984 | F10: audited | G10: Desert Financial 2021 Annual Report (audited FY2020)
A11: 2020-12-31 | B11: ytd | C11: noninterest_income | D11: Other miscellaneous income | E11: 14883.924 | F11: audited | G11: Desert Financial 2021 Annual Report (audited FY2020)
A12: 2020-12-31 | B12: ytd | C12: noninterest_income | D12: Sales of insurance and investment products | E12: 7165.058 | F12: audited | G12: Desert Financial 2021 Annual Report (audited FY2020)
A13: 2020-12-31 | B13: ytd | C13: noninterest_income | D13: Gains on capitalization of mortgage servicing rights | E13: 6423.329 | F13: audited | G13: Desert Financial 2021 Annual Report (audited FY2020)
... A188: 2026-06-30 | B188: qtd | C188: noninterest_expense | D188: Non-interest expense | E188: 79234.395 | F188: modeled | G188: Modeled quarterly allocation (smooth path to audited/public totals)

Sheet income_statement_totals
A1: period | B1: basis | C1: interest_income | D1: interest_expense_reported | E1: nii_reported | F1: member_giveback | G1: provision | H1: noninterest_income_reported | I1: noninterest_expense_reported | J1: net_income_reported | K1: provenance | L1: source | M1: nii_ex_giveback
A2: 2020-12-31 | B2: ytd | C2: 157346.46 | D2: 33612.83 | E2: 123733.63 | F2: 9000 | G2: 13133.373 | H2: 135581.87 | I2: 203640.65 | J2: 42541.475 | K2: audited | L2: Desert Financial 2021 Annual Report (audited FY2020) | M2: =E2+F2 -> 132733.63
A3: 2021-12-31 | B3: ytd | C3: 163305.95 | D3: 34273.375 | E3: 129032.57 | F3: 14000 | G3: -2212.344 | H3: 171090.61 | I3: 214893.7 | J3: 87441.822 | K3: audited | L3: Desert Financial 2021 Annual Report (audited FY2021) | M3: =E3+F3 -> 143032.57
A4: 2022-12-31 | B4: ytd | C4: 241417.76 | D4: 58141.748 | E4: 183276.02 | F4: 15000 | G4: -492.306 | H4: 136465.58 | I4: 234211.04 | J4: 86022.867 | K4: audited | L4: Desert Financial 2023 Annual Report (audited FY2022) | M4: =E4+F4 -> 198276.02
A5: 2023-12-31 | B5: ytd | C5: 303905.97 | D5: 108485.33 | E5: 195420.64 | F5: 17000 | G5: 15849.591 | H5: 151734.08 | I5: 246010.71 | J5: 85294.418 | K5: audited | L5: Desert Financial 2023 Annual Report (audited FY2023) | M5: =E5+F5 -> 212420.64
A6: 2024-12-31 | B6: ytd | C6: 370110.99 | D6: 172405.93 | E6: 197705.06 | F6: 20000 | G6: 16682.647 | H6: 160293.93 | I6: 269099.23 | J6: 72217.108 | K6: audited | L6: Desert Financial 2025 Annual Report (audited FY2024) | M6: =E6+F6 -> 217705.06
A7: 2025-12-31 | B7: ytd | C7: 408802.11 | D7: 167358.52 | E7: 241443.59 | F7: 16000 | G7: 20022.718 | H7: 153191 | I7: 300041.63 | J7: 74570.244 | K7: audited | L7: Desert Financial 2025 Annual Report (audited FY2025) | M7: =E7+F7 -> 257443.59
A8: 2026-06-30 | B8: ytd | C8: 221560.48 | D8: 81930.219 | E8: 139630.26 | F8: 16000 | G8: 11996.03 | H8: 81913.867 | I8: 154778.04 | J8: 54770.059 | K8: public | L8: NCUA 5300 call report, June 30, 2026 (ncuso.org/credit-union/68713/financials) | M8: =E8+F8 -> 155630.26
A9: 2025-03-31 | B9: qtd | C9: 99026.374 | D9: 56086.438 | E9: 42939.936 | F9: 16000 | G9: 4148.9102 | H9: 35459.007 | I9: 72566.837 | J9: 1683.1956 | K9: modeled | L9: Modeled quarterly allocation (smooth path to audited/public totals) | M9: =E9+F9 -> 58939.936
A10: 2025-06-30 | B10: qtd | C10: 100857.12 | D10: 38752.898 | E10: 62104.218 | F10: 0 | G10: 4635.8448 | H10: 40807.231 | I10: 74568.92 | J10: 23706.685 | K10: modeled | L10: Modeled quarterly allocation (smooth path to audited/public totals) | M10: =E10+F10 -> 62104.218
A11: 2025-09-30 | B11: qtd | C11: 103075.68 | D11: 37106.668 | E11: 65969.013 | F11: 0 | G11: 5300.4929 | H11: 37813.898 | I11: 76024.172 | J11: 22458.245 | K11: modeled | L11: Modeled quarterly allocation (smooth path to audited/public totals) | M11: =E11+F11 -> 65969.013
A12: 2025-12-31 | B12: qtd | C12: 105842.94 | D12: 35412.513 | E12: 70430.426 | F12: 0 | G12: 5937.4702 | H12: 39110.86 | I12: 76881.698 | J12: 26722.118 | K12: modeled | L12: Modeled quarterly allocation (smooth path to audited/public totals) | M12: =E12+F12 -> 70430.426
A13: 2026-03-31 | B13: qtd | C13: 110810.25 | D13: 49777.787 | E13: 61032.458 | F13: 16000 | G13: 6232.686 | H13: 42130.565 | I13: 75724.19 | J13: 21206.147 | K13: public | L13: NCUA 5300 call report, March 31, 2026 (partial: NCUSO summary and CUScore) (net income and provision); other lines modeled | M13: =E13+F13 -> 77032.458
... A15: 2026-06-30 | B15: qtd | C15: 110750.23 | D15: 32152.432 | E15: 78597.801 | F15: 0 | G15: 5763.344 | H15: 39963.85 | I15: 79234.395 | J15: 33563.912 | K15: modeled | L15: Modeled quarterly allocation (smooth path to audited/public totals) | M15: =E15+F15 -> 78597.801

Sheet loans
A1: period | B1: product_key | C1: product_label | D1: balance | E1: count | F1: yield | G1: pct_fixed | H1: index | I1: floor_rate | J1: cap_rate | K1: wal_years | L1: eff_duration | M1: prepay_base | N1: prepay_up | O1: prepay_down | P1: prepay_unit | Q1: delinq_30 | R1: delinq_60 | S1: nco_rate | T1: acl | U1: avg_fico | V1: avg_ltv_cltv | W1: originations_ytd | X1: indirect_share | Y1: unfunded_commitments | Z1: line_utilization | AA1: call_report_line | AB1: call_report_rate | AC1: offer_rate | AD1: disc_spread | AE1: eff_convexity | AF1: reprice_wal_years | AG1: provenance | AH1: source | AI1: dup_count | AJ1: mix_share
A2: 2026-06-30 | B2: heloc | C2: Home equity lines of credit (HELOC) | D2: 1515773.5 | E2: 29264 | F2: 0.0645 | G2: 0 | H2: prime | I2: 0.0375 | J2: 0.18 | K2: 3.871 | L2: -0.051 | M2: 0.2 | N2: 0.2 | O2: 0.2 | P2: cpr | Q2: 0.004339 | R2: 0.002712 | S2: 0.000417 | T2: 6553.1247 | U2: 774 | V2: 0.63 | W2: 323521.24 | X2: 0 | Y2: 1240000 | Z2: 0.55 | AA2: junior_lien_re | AB2: 0.064 | AC2: 0.0671 | AD2: 0.020614 | AE2: 1.069 | AF2: 0.083 | AG2: modeled | AH2: NCUA 5300 call report, June 30, 2026 (ncuso.org/credit-union/68713/financials) (balance and count by call report line); product split, yields, behavior and credit allocation modeled; avg_fico and avg_ltv_cltv hypothetical | AI2: =COUNTIFS($A$2:$A$200,A2,$B$2:$B$200,B2) -> 1 | AJ2: =D2/SUMIFS($D$2:$D$200,$A$2:$A$200,A2) -> 0.28570172
A3: 2026-06-30 | B3: he_fixed | C3: Home equity loans, fixed | D3: 589467.47 | E3: 9241 | F3: 0.0545 | G3: 1 | H3: treasury | K3: 4.865 | L3: 4.118 | M3: 0.0874 | N3: 0.055 | O3: 0.1996 | P3: cpr | Q3: 0.003944 | R3: 0.002465 | S3: 0.000417 | T3: 2831.5971 | U3: 768 | V3: 0.61 | W3: 97666.79 | X3: 0 | Y3: 0 | AA3: junior_lien_re | AB3: 0.064 | AC3: 0.0629 | AD3: 0.015355 | AE3: -14.8445 | AF3: 4.865 | AG3: modeled | AH3: NCUA 5300 call report, June 30, 2026 (ncuso.org/credit-union/68713/financials) (balance and count by call report line); product split, yields, behavior and credit allocation modeled; avg_fico and avg_ltv_cltv hypothetical | AI3: =COUNTIFS($A$2:$A$200,A3,$B$2:$B$200,B3) -> 1 | AJ3: =D3/SUMIFS($D$2:$D$200,$A$2:$A$200,A3) -> 0.11110623
A4: 2026-06-30 | B4: auto_used | C4: Used vehicle loans | D4: 1104190.9 | E4: 53898 | F4: 0.071 | G4: 1 | H4: treasury | K4: 1.874 | L4: 1.7126 | M4: 0.181 | N4: 0.14 | O4: 0.2465 | P4: cpr | Q4: 0.016049 | R4: 0.007642 | S4: 0.010002 | T4: 15382.035 | U4: 721 | V4: 0.97 | W4: 398806.06 | X4: 0.5 | Y4: 0 | AA4: used_vehicle | AB4: 0.0805 | AC4: 0.0805 | AD4: 0.029417 | AE4: -5.2589 | AF4: 1.874 | AG4: modeled | AH4: NCUA 5300 call report, June 30, 2026 (ncuso.org/credit-union/68713/financials) (balance and count by call report line); product split, yields, behavior and credit allocation modeled; avg_fico and avg_ltv_cltv hypothetical | AI4: =COUNTIFS($A$2:$A$200,A4,$B$2:$B$200,B4) -> 1 | AJ4: =D4/SUMIFS($D$2:$D$200,$A$2:$A$200,A4) -> 0.20812427
A5: 2026-06-30 | B5: auto_new | C5: New vehicle loans | D5: 476328.95 | E5: 17545 | F5: 0.0625 | G5: 1 | H5: treasury | K5: 1.989 | L5: 1.8378 | M5: 0.158 | N5: 0.12 | O5: 0.222 | P5: cpr | Q5: 0.009837 | R5: 0.004684 | S5: 0.005626 | T5: 4805.0497 | U5: 742 | V5: 0.92 | W5: 174986.33 | X5: 0.55 | Y5: 0 | AA5: new_vehicle | AB5: 0.0736 | AC5: 0.0735 | AD5: 0.023365 | AE5: -5.6686 | AF5: 1.989 | AG5: modeled | AH5: NCUA 5300 call report, June 30, 2026 (ncuso.org/credit-union/68713/financials) (balance and count by call report line); product split, yields, behavior and credit allocation modeled; avg_fico and avg_ltv_cltv hypothetical | AI5: =COUNTIFS($A$2:$A$200,A5,$B$2:$B$200,B5) -> 1 | AJ5: =D5/SUMIFS($D$2:$D$200,$A$2:$A$200,A5) -> 0.089781225
A6: 2026-06-30 | B6: mortgage_fixed | C6: First mortgages, fixed rate (portfolio) | D6: 374430.3 | E6: 1603 | F6: 0.043 | G6: 1 | H6: treasury | K6: 10.631 | L6: 7.2648 | M6: 0.035 | N6: 0.035 | O6: 0.0872 | P6: cpr | Q6: 0.004733 | R6: 0.002958 | S6: 0.000208 | T6: 1079.1799 | U6: 765 | V6: 0.66 | W6: 41711.858 | X6: 0 | Y6: 0 | AA6: first_mortgage | AB6: 0.0576 | AC6: 0.0649 | AD6: 0.016045 | AE6: 149.5557 | AF6: 10.631 | AG6: modeled | AH6: NCUA 5300 call report, June 30, 2026 (ncuso.org/credit-union/68713/financials) (balance and count by call report line); product split, yields, behavior and credit allocation modeled; avg_fico and avg_ltv_cltv hypothetical | AI6: =COUNTIFS($A$2:$A$200,A6,$B$2:$B$200,B6) -> 1 | AJ6: =D6/SUMIFS($D$2:$D$200,$A$2:$A$200,A6) -> 0.070574781
A7: 2026-06-30 | B7: mortgage_arm | C7: First mortgages, adjustable (hybrid ARM) | D7: 249620.2 | E7: 982 | F7: 0.059 | G7: 1 | H7: treasury | I7: 0.03 | J7: 0.105 | K7: 8.85 | L7: 1.9182 | M7: 0.0771 | N7: 0.065 | O7: 0.1946 | P7: cpr | Q7: 0.004339 | R7: 0.002712 | S7: 0.000208 | T7: 719.45327 | U7: 770 | V7: 0.68 | W7: 63076.469 | X7: 0 | Y7: 0 | AA7: first_mortgage | AB7: 0.0576 | AC7: 0.0574 | AD7: 0.013773 | AE7: 4.5411 | AF7: 2.185 | AG7: modeled | AH7: NCUA 5300 call report, June 30, 2026 (ncuso.org/credit-union/68713/financials) (balance and count by call report line); product split, yields, behavior and credit allocation modeled; avg_fico and avg_ltv_cltv hypothetical | AI7: =COUNTIFS($A$2:$A$200,A7,$B$2:$B$200,B7) -> 1 | AJ7: =D7/SUMIFS($D$2:$D$200,$A$2:$A$200,A7) -> 0.047049854
A8: 2026-06-30 | B8: cre_reset | C8: Commercial real estate, fixed-to-reset | D8: 720674.9 | E8: 547 | F8: 0.0595 | G8: 1 | H8: treasury | I8: 0.04 | K8: 7.791 | L8: 1.9496 | M8: 0.0651 | N8: 0.04 | O8: 0.1504 | P8: cpr | Q8: 0.008678 | R8: 0.005424 | S8: 0.000834 | T8: 9000.8673 | V8: 0.6 | W8: 113944.59 | X8: 0 | Y8: 45000 | AA8: commercial_re | AB8: 0.0641 | AC8: 0.0644 | AD8: 0.016879 | AE8: 1.1211 | AF8: 2.184 | AG8: modeled | AH8: NCUA 5300 call report, June 30, 2026 (ncuso.org/credit-union/68713/financials) (balance and count by call report line); product split, yields, behavior and credit allocation modeled; avg_fico and avg_ltv_cltv hypothetical | AI8: =COUNTIFS($A$2:$A$200,A8,$B$2:$B$200,B8) -> 1 | AJ8: =D8/SUMIFS($D$2:$D$200,$A$2:$A$200,A8) -> 0.13583696
A9: 2026-06-30 | B9: cre_float | C9: Commercial real estate, floating | D9: 127177.92 | E9: 104 | F9: 0.07 | G9: 0 | H9: prime | I9: 0.05 | K9: 5.747 | L9: -0.0674 | M9: 0.12 | N9: 0.12 | O9: 0.12 | P9: cpr | Q9: 0.008678 | R9: 0.005424 | S9: 0.000834 | T9: 1588.3883 | V9: 0.58 | W9: 19329.886 | X9: 0 | Y9: 30000 | Z9: 0.72 | AA9: commercial_re | AB9: 0.0641 | AC9: 0.071 | AD9: 0.02557 | AE9: 1.3815 | AF9: 0.083 | AG9: modeled | AH9: NCUA 5300 call report, June 30, 2026 (ncuso.org/credit-union/68713/financials) (balance and count by call report line); product split, yields, behavior and credit allocation modeled; avg_fico and avg_ltv_cltv hypothetical | AI9: =COUNTIFS($A$2:$A$200,A9,$B$2:$B$200,B9) -> 1 | AJ9: =D9/SUMIFS($D$2:$D$200,$A$2:$A$200,A9) -> 0.023971228
A10: 2026-06-30 | B10: commercial_non_re | C10: Commercial and industrial (non-RE) | D10: 20543.822 | E10: 193 | F10: 0.076 | G10: 0 | H10: prime | I10: 0.055 | K10: 1.917 | L10: -0.0239 | M10: 0.2 | N10: 0.2 | O10: 0.2 | P10: cpr | Q10: 0.022779 | R10: 0.010847 | S10: 0.006251 | T10: 394.74155 | W10: 7630.218 | X10: 0 | Y10: 18000 | Z10: 0.53 | AA10: commercial_non_re | AB10: 0.0776 | AC10: 0.0775 | AD10: 0.033481 | AE10: 0.6475 | AF10: 0.083 | AG10: modeled | AH10: NCUA 5300 call report, June 30, 2026 (ncuso.org/credit-union/68713/financials) (balance and count by call report line); product split, yields, behavior and credit allocation modeled; avg_fico and avg_ltv_cltv hypothetical | AI10: =COUNTIFS($A$2:$A$200,A10,$B$2:$B$200,B10) -> 1 | AJ10: =D10/SUMIFS($D$2:$D$200,$A$2:$A$200,A10) -> 0.0038722179
A11: 2026-06-30 | B11: unsecured_fixed | C11: Personal loans, unsecured fixed | D11: 62649.693 | E11: 16887 | F11: 0.119 | G11: 1 | H11: treasury | K11: 1.248 | L11: 1.115 | M11: 0.25 | N11: 0.25 | O11: 0.25 | P11: cpr | Q11: 0.035204 | R11: 0.016764 | S11: 0.035424 | T11: 3009.4737 | U11: 718 | W11: 34590.322 | X11: 0 | Y11: 0 | AA11: unsecured_other | AB11: 0.1379 | AC11: 0.1265 | AD11: 0.072908 | AE11: 2.3948 | AF11: 1.248 | AG11: modeled | AH11: NCUA 5300 call report, June 30, 2026 (ncuso.org/credit-union/68713/financials) (balance and count by call report line); product split, yields, behavior and credit allocation modeled; avg_fico and avg_ltv_cltv hypothetical | AI11: =COUNTIFS($A$2:$A$200,A11,$B$2:$B$200,B11) -> 1 | AJ11: =D11/SUMIFS($D$2:$D$200,$A$2:$A$200,A11) -> 0.011808575
A12: 2026-06-30 | B12: unsecured_loc | C12: Personal lines of credit | D12: 41766.462 | E12: 20639 | F12: 0.1415 | G12: 0 | H12: prime | I12: 0.09 | J12: 0.18 | K12: 1.664 | L12: -0.0135 | M12: 0.3 | N12: 0.3 | O12: 0.3 | P12: cpr | Q12: 0.032098 | R12: 0.015285 | S12: 0.031257 | T12: 1805.6842 | U12: 712 | W12: 11699.668 | X12: 0 | Y12: 36000 | Z12: 0.54 | AA12: unsecured_other | AB12: 0.1379 | AC12: 0.1415 | AD12: 0.08522 | AE12: 0.5404 | AF12: 0.083 | AG12: modeled | AH12: NCUA 5300 call report, June 30, 2026 (ncuso.org/credit-union/68713/financials) (balance and count by call report line); product split, yields, behavior and credit allocation modeled; avg_fico and avg_ltv_cltv hypothetical | AI12: =COUNTIFS($A$2:$A$200,A12,$B$2:$B$200,B12) -> 1 | AJ12: =D12/SUMIFS($D$2:$D$200,$A$2:$A$200,A12) -> 0.0078723834
A13: 2026-06-30 | B13: other_secured | C13: Other secured consumer (RV, boat, share-secured) | D13: 21376.155 | E13: 958 | F13: 0.092 | G13: 1 | H13: treasury | K13: 2.383 | L13: 2.0183 | M13: 0.15 | N13: 0.15 | O13: 0.15 | P13: cpr | Q13: 0.016567 | R13: 0.007889 | S13: 0.006251 | T13: 328.58761 | U13: 735 | V13: 0.85 | W13: 8138.8992 | X13: 0.1 | Y13: 0 | AA13: other_secured | AB13: 0.1008 | AC13: 0.1009 | AD13: 0.050197 | AE13: 7.2815 | AF13: 2.383 | AG13: modeled | AH13: NCUA 5300 call report, June 30, 2026 (ncuso.org/credit-union/68713/financials) (balance and count by call report line); product split, yields, behavior and credit allocation modeled; avg_fico and avg_ltv_cltv hypothetical | AI13: =COUNTIFS($A$2:$A$200,A13,$B$2:$B$200,B13) -> 1 | AJ13: =D13/SUMIFS($D$2:$D$200,$A$2:$A$200,A13) -> 0.0040291009
A14: 2026-06-30 | B14: student | C14: Private student loans | D14: 1397.217 | E14: 60 | F14: 0.095 | G14: 1 | H14: treasury | K14: 3.774 | L14: 2.9167 | M14: 0.08 | N14: 0.08 | O14: 0.08 | P14: cpr | Q14: 0.031063 | R14: 0.014792 | S14: 0.012503 | T14: 53.693963 | U14: 730 | W14: 101.73624 | X14: 0 | Y14: 0 | AA14: student | AB14: 0.1125 | AC14: 0.1124 | AD14: 0.060516 | AE14: 14.5666 | AF14: 3.774 | AG14: modeled | AH14: NCUA 5300 call report, June 30, 2026 (ncuso.org/credit-union/68713/financials) (balance and count by call report line); product split, yields, behavior and credit allocation modeled; avg_fico and avg_ltv_cltv hypothetical | AI14: =COUNTIFS($A$2:$A$200,A14,$B$2:$B$200,B14) -> 1 | AJ14: =D14/SUMIFS($D$2:$D$200,$A$2:$A$200,A14) -> 0.00026335551
A15: 2026-06-30 | B15: other_re | C15: Other real estate loans | D15: 42.972 | E15: 2 | F15: 0.0575 | G15: 1 | H15: treasury | K15: 6.225 | L15: 4.6923 | M15: 0.08 | N15: 0.08 | O15: 0.08 | P15: cpr | Q15: 0 | R15: 0 | S15: 0 | T15: 0.12385354 | W15: 0 | X15: 0 | Y15: 0 | AA15: other_re | AB15: 0.0575 | AC15: 0.0649 | AD15: 0.018308 | AE15: 39.0319 | AF15: 6.225 | AG15: modeled | AH15: NCUA 5300 call report, June 30, 2026 (ncuso.org/credit-union/68713/financials) (balance and count by call report line); product split, yields, behavior and credit allocation modeled; avg_fico and avg_ltv_cltv hypothetical | AI15: =COUNTIFS($A$2:$A$200,A15,$B$2:$B$200,B15) -> 1 | AJ15: =D15/SUMIFS($D$2:$D$200,$A$2:$A$200,A15) -> 8.0996102e-06

Sheet deposits
A1: period | B1: product_key | C1: product_label | D1: tier | E1: balance | F1: accounts | G1: rate | H1: beta_up | I1: beta_down | J1: beta_lag_months | K1: decay_wal_years | L1: insured_share_est | M1: cert_rollover_base | N1: cert_rollover_stress | O1: decay_rate | P1: rate_floor | Q1: servicing_cost | R1: migration_per_100bp | S1: eff_duration | T1: fair_value_base | U1: provenance | V1: source | W1: dup_count | X1: mix_share
A2: 2026-06-30 | B2: share_drafts | C2: Share drafts (checking), consumer | D2: consumer | E2: 1551679.6 | F2: 398000 | G2: 0.0006 | H2: 0.02 | I2: 0.02 | J2: 0 | K2: 6.6 | L2: 0.97 | O2: 0.14 | P2: 0.0002 | Q2: 0.0075 | R2: 0.01 | S2: 4.8098 | T2: 1240835.9 | U2: modeled | V2: NCUA 5300 call report, June 30, 2026 (ncuso.org/credit-union/68713/financials) (product totals); tiers, rates and behavior modeled | W2: =COUNTIFS($A$2:$A$200,A2,$B$2:$B$200,B2,$D$2:$D$200,D2) -> 1 | X2: =E2/SUMIFS($E$2:$E$200,$A$2:$A$200,A2) -> 0.17522015
A3: 2026-06-30 | B3: share_drafts | C3: Share drafts (checking), business | D3: business | E3: 330000 | F3: 24500 | G3: 0.0015 | H3: 0.1 | I3: 0.08 | J3: 1 | K3: 4.518 | L3: 0.6 | O3: 0.2 | P3: 0.0005 | Q3: 0.006 | R3: 0.02 | S3: 3.2594 | T3: 281801.82 | U3: modeled | V3: NCUA 5300 call report, June 30, 2026 (ncuso.org/credit-union/68713/financials) (product totals); tiers, rates and behavior modeled | W3: =COUNTIFS($A$2:$A$200,A3,$B$2:$B$200,B3,$D$2:$D$200,D3) -> 1 | X3: =E3/SUMIFS($E$2:$E$200,$A$2:$A$200,A3) -> 0.037264554
A4: 2026-06-30 | B4: regular_shares | C4: Regular shares (savings), consumer | D4: consumer | E4: 1462571.8 | F4: 515000 | G4: 0.001 | H4: 0.05 | I4: 0.05 | J4: 3 | K4: 6.6 | L4: 0.99 | O4: 0.14 | P4: 0.0005 | Q4: 0.005 | R4: 0.02 | S4: 4.6275 | T4: 1154074.4 | U4: modeled | V4: NCUA 5300 call report, June 30, 2026 (ncuso.org/credit-union/68713/financials) (product totals); tiers, rates and behavior modeled | W4: =COUNTIFS($A$2:$A$200,A4,$B$2:$B$200,B4,$D$2:$D$200,D4) -> 1 | X4: =E4/SUMIFS($E$2:$E$200,$A$2:$A$200,A4) -> 0.16515783
A5: 2026-06-30 | B5: regular_shares | C5: Regular shares (savings), business | D5: business | E5: 50000 | F5: 21000 | G5: 0.001 | H5: 0.08 | I5: 0.06 | J5: 2 | K5: 4.518 | L5: 0.85 | O5: 0.2 | P5: 0.0005 | Q5: 0.004 | R5: 0.02 | S5: 3.3505 | T5: 42230.402 | U5: modeled | V5: NCUA 5300 call report, June 30, 2026 (ncuso.org/credit-union/68713/financials) (product totals); tiers, rates and behavior modeled | W5: =COUNTIFS($A$2:$A$200,A5,$B$2:$B$200,B5,$D$2:$D$200,D5) -> 1 | X5: =E5/SUMIFS($E$2:$E$200,$A$2:$A$200,A5) -> 0.0056461446
A6: 2026-06-30 | B6: money_market | C6: Money market, under $25K | D6: t1_under_25k | E6: 1000000 | F6: 112000 | G6: 0.0055 | H6: 0.15 | I6: 0.1 | J6: 3 | K6: 4.518 | L6: 1 | O6: 0.2 | P6: 0.001 | Q6: 0.0025 | R6: 0.02 | S6: 3.1326 | T6: 855812.27 | U6: modeled | V6: NCUA 5300 call report, June 30, 2026 (ncuso.org/credit-union/68713/financials) (product totals); tiers, rates and behavior modeled | W6: =COUNTIFS($A$2:$A$200,A6,$B$2:$B$200,B6,$D$2:$D$200,D6) -> 1 | X6: =E6/SUMIFS($E$2:$E$200,$A$2:$A$200,A6) -> 0.11292289
A7: 2026-06-30 | B7: money_market | C7: Money market, $25K to $100K | D7: t2_25k_100k | E7: 1100000 | F7: 23500 | G7: 0.0145 | H7: 0.4 | I7: 0.3 | J7: 2 | K7: 3.517 | L7: 1 | O7: 0.25 | P7: 0.0025 | Q7: 0.0025 | R7: 0.03 | S7: 1.8385 | T7: 1003659.2 | U7: modeled | V7: NCUA 5300 call report, June 30, 2026 (ncuso.org/credit-union/68713/financials) (product totals); tiers, rates and behavior modeled | W7: =COUNTIFS($A$2:$A$200,A7,$B$2:$B$200,B7,$D$2:$D$200,D7) -> 1 | X7: =E7/SUMIFS($E$2:$E$200,$A$2:$A$200,A7) -> 0.12421518
A8: 2026-06-30 | B8: money_market | C8: Money market, $100K to $250K | D8: t3_100k_250k | E8: 800000 | F8: 5300 | G8: 0.0225 | H8: 0.55 | I8: 0.45 | J8: 1 | K8: 2.845 | L8: 0.99 | O8: 0.3 | P8: 0.005 | Q8: 0.002 | R8: 0.04 | S8: 1.1424 | T8: 757831.78 | U8: modeled | V8: NCUA 5300 call report, June 30, 2026 (ncuso.org/credit-union/68713/financials) (product totals); tiers, rates and behavior modeled | W8: =COUNTIFS($A$2:$A$200,A8,$B$2:$B$200,B8,$D$2:$D$200,D8) -> 1 | X8: =E8/SUMIFS($E$2:$E$200,$A$2:$A$200,A8) -> 0.090338314
A9: 2026-06-30 | B9: money_market | C9: Money market, $250K and over (incl. business) | D9: t4_250k_plus | E9: 765287.68 | F9: 1550 | G9: 0.0285 | H9: 0.7 | I9: 0.6 | J9: 1 | K9: 2 | L9: 0.5 | O9: 0.4 | P9: 0.0075 | Q9: 0.0015 | R9: 0.05 | S9: 0.5771 | T9: 744566.85 | U9: modeled | V9: NCUA 5300 call report, June 30, 2026 (ncuso.org/credit-union/68713/financials) (product totals); tiers, rates and behavior modeled | W9: =COUNTIFS($A$2:$A$200,A9,$B$2:$B$200,B9,$D$2:$D$200,D9) -> 1 | X9: =E9/SUMIFS($E$2:$E$200,$A$2:$A$200,A9) -> 0.086418498
A10: 2026-06-30 | B10: ira | C10: IRA/Keogh savings | D10: ira_savings | E10: 74688.36 | F10: 6200 | G10: 0.012 | H10: 0.2 | I10: 0.15 | J10: 2 | K10: 9.129 | L10: 1 | O10: 0.1 | P10: 0.001 | Q10: 0.003 | R10: 0.02 | S10: 4.9181 | T10: 58393.565 | U10: modeled | V10: NCUA 5300 call report, June 30, 2026 (ncuso.org/credit-union/68713/financials) (product totals); tiers, rates and behavior modeled | W10: =COUNTIFS($A$2:$A$200,A10,$B$2:$B$200,B10,$D$2:$D$200,D10) -> 1 | X10: =E10/SUMIFS($E$2:$E$200,$A$2:$A$200,A10) -> 0.0084340257
A11: 2026-06-30 | B11: other_shares | C11: Other shares (club, escrow, HSA) | D11: all | E11: 14494.065 | F11: 9800 | G11: 0.004 | H11: 0.1 | I11: 0.1 | J11: 3 | K11: 3.517 | L11: 1 | O11: 0.25 | P11: 0.0005 | Q11: 0.005 | R11: 0 | S11: 2.6436 | T11: 12873.471 | U11: modeled | V11: NCUA 5300 call report, June 30, 2026 (ncuso.org/credit-union/68713/financials) (product totals); tiers, rates and behavior modeled | W11: =COUNTIFS($A$2:$A$200,A11,$B$2:$B$200,B11,$D$2:$D$200,D11) -> 1 | X11: =E11/SUMIFS($E$2:$E$200,$A$2:$A$200,A11) -> 0.0016367117
A12: 2026-06-30 | B12: certificates | C12: Share certificates, under $100K | D12: under_100k | E12: 734544.64 | F12: 31500 | G12: 0.037835 | H12: 1 | I12: 1 | J12: 9.3 | K12: 0.771 | L12: 1 | M12: 0.85 | N12: 0.65 | S12: 0.7337 | T12: 733335.07 | U12: modeled | V12: NCUA 5300 call report, June 30, 2026 (ncuso.org/credit-union/68713/financials) (certificate totals, $100K+ split); maturity ladder and rates modeled | W12: =COUNTIFS($A$2:$A$200,A12,$B$2:$B$200,B12,$D$2:$D$200,D12) -> 1 | X12: =E12/SUMIFS($E$2:$E$200,$A$2:$A$200,A12) -> 0.082946905
A13: 2026-06-30 | B13: certificates | C13: Share certificates, $100K and over | D13: 100k_plus | E13: 860301.67 | F13: 5600 | G13: 0.038936 | H13: 1 | I13: 1 | J13: 9.3 | K13: 0.771 | L13: 0.8 | M13: 0.8 | N13: 0.55 | S13: 0.7337 | T13: 859591.34 | U13: modeled | V13: NCUA 5300 call report, June 30, 2026 (ncuso.org/credit-union/68713/financials) (certificate totals, $100K+ split); maturity ladder and rates modeled | W13: =COUNTIFS($A$2:$A$200,A13,$B$2:$B$200,B13,$D$2:$D$200,D13) -> 1 | X13: =E13/SUMIFS($E$2:$E$200,$A$2:$A$200,A13) -> 0.097147753
A14: 2026-06-30 | B14: ira | C14: IRA/Keogh certificates | D14: ira_certificates | E14: 112032.54 | F14: 4300 | G14: 0.038925 | H14: 1 | I14: 1 | J14: 17.9 | K14: 1.492 | L14: 1 | M14: 0.9 | N14: 0.75 | S14: 1.3971 | T14: 111800.89 | U14: modeled | V14: NCUA 5300 call report, June 30, 2026 (ncuso.org/credit-union/68713/financials) (certificate totals, $100K+ split); maturity ladder and rates modeled | W14: =COUNTIFS($A$2:$A$200,A14,$B$2:$B$200,B14,$D$2:$D$200,D14) -> 1 | X14: =E14/SUMIFS($E$2:$E$200,$A$2:$A$200,A14) -> 0.012651038

Sheet cert_maturities
A1: period | B1: month_bucket | C1: balance | D1: rate | E1: maturity_month | F1: balance_under_100k | G1: balance_100k_plus | H1: balance_ira
A2: 2026-06-30 | B2: 1 | C2: 150927.08 | D2: 0.03998 | E2: 2026-07-31 | F2: 67578.107 | G2: 79147.754 | H2: 4201.2203
A3: 2026-06-30 | B3: 2 | C3: 150927.08 | D3: 0.03998 | E3: 2026-08-31 | F3: 67578.107 | G3: 79147.754 | H3: 4201.2203
A4: 2026-06-30 | B4: 3 | C4: 150927.08 | D4: 0.03998 | E4: 2026-09-30 | F4: 67578.107 | G4: 79147.754 | H4: 4201.2203
A5: 2026-06-30 | B5: 4 | C5: 130725.69 | D5: 0.03901 | E5: 2026-10-31 | F5: 58273.875 | G5: 68250.599 | H5: 4201.2203
A6: 2026-06-30 | B6: 5 | C6: 130725.69 | D6: 0.03901 | E6: 2026-11-30 | F6: 58273.875 | G6: 68250.599 | H6: 4201.2203
A7: 2026-06-30 | B7: 6 | C7: 130725.69 | D7: 0.03901 | E7: 2026-12-31 | F7: 58273.875 | G7: 68250.599 | H7: 4201.2203
A8: 2026-06-30 | B8: 7 | C8: 90854.536 | D8: 0.037586 | E8: 2027-01-31 | F8: 39910.259 | G8: 46743.057 | H8: 4201.2203
A9: 2026-06-30 | B9: 8 | C9: 90854.536 | D9: 0.037586 | E9: 2027-02-28 | F9: 39910.259 | G9: 46743.057 | H9: 4201.2203
A10: 2026-06-30 | B10: 9 | C10: 90854.536 | D10: 0.037586 | E10: 2027-03-31 | F10: 39910.259 | G10: 46743.057 | H10: 4201.2203
A11: 2026-06-30 | B11: 10 | C11: 74374.458 | D11: 0.036663 | E11: 2027-04-30 | F11: 32319.964 | G11: 37853.273 | H11: 4201.2203
A12: 2026-06-30 | B12: 11 | C12: 74374.458 | D12: 0.036663 | E12: 2027-05-31 | F12: 32319.964 | G12: 37853.273 | H12: 4201.2203
A13: 2026-06-30 | B13: 12 | C13: 74374.458 | D13: 0.036663 | E13: 2027-06-30 | F13: 32319.964 | G13: 37853.273 | H13: 4201.2203
... A61: 2026-06-30 | B61: 60 | C61: 2327.4563 | D61: 0.034396 | E61: 2031-06-30 | F61: 856.96875 | G61: 1003.6853 | H61: 466.80225

Sheet investments
A1: period | B1: group | C1: classification | D1: book | E1: market | F1: yield | G1: eff_duration | H1: eff_convexity | I1: wal_years | J1: pledged | K1: label | L1: provenance | M1: source | N1: unrealized_gain_loss | O1: dup_count
A2: 2026-06-30 | B2: other | C2: equity | D2: 24065.482 | E2: 24065.482 | G2: 0 | H2: 0 | J2: 0 | K2: Equity securities (deferred compensation funds) | L2: public | M2: NCUA 5300 call report, June 30, 2026 (ncuso.org/credit-union/68713/financials) | N2: =E2-D2 -> 0 | O2: =COUNTIFS($A$2:$A$100,A2,$B$2:$B$100,B2,$C$2:$C$100,C2) -> 1
A3: 2026-06-30 | B3: ust | C3: afs | D3: 150000 | E3: 150051.43 | F3: 0.0408 | G3: 1.9386 | H3: 5.9199 | I3: 2.083 | J3: 0 | K3: U.S. Treasury notes | L3: modeled | M3: NCUA 5300 call report, June 30, 2026 (ncuso.org/credit-union/68713/financials); AFS fair value total ties to call report; composition modeled | N3: =E3-D3 -> 51.434903 | O3: =COUNTIFS($A$2:$A$100,A3,$B$2:$B$100,B3,$C$2:$C$100,C3) -> 1
A4: 2026-06-30 | B4: agency | C4: afs | D4: 400000 | E4: 367549.24 | F4: 0.011375 | G4: 2.8165 | H4: 11.3748 | I4: 3 | J4: 0 | K4: Agency debentures (non-callable and seasoned callables) | L4: modeled | M4: NCUA 5300 call report, June 30, 2026 (ncuso.org/credit-union/68713/financials); AFS fair value total ties to call report; composition modeled | N4: =E4-D4 -> -32450.758 | O4: =COUNTIFS($A$2:$A$100,A4,$B$2:$B$100,B4,$C$2:$C$100,C4) -> 1
A5: 2026-06-30 | B5: agency_mbs | C5: afs | D5: 1000000 | E5: 853908.47 | F5: 0.02975 | G5: 6.956 | H5: 57.4124 | I5: 9.584 | J5: 0 | K5: Agency MBS pass-throughs, 2020-2021 vintage (2.0% coupon); Agency MBS pass-throughs, 2023-2024 vintage (5.25% coupon) | L5: modeled | M5: NCUA 5300 call report, June 30, 2026 (ncuso.org/credit-union/68713/financials); AFS fair value total ties to call report; composition modeled | N5: =E5-D5 -> -146091.53 | O5: =COUNTIFS($A$2:$A$100,A5,$B$2:$B$100,B5,$C$2:$C$100,C5) -> 1
A6: 2026-06-30 | B6: cmo | C6: afs | D6: 400000 | E6: 352414.48 | F6: 0.025 | G6: 5.0754 | H6: 76.4512 | I6: 6.085 | J6: 0 | K6: Agency CMOs (sequential and PAC tranches) | L6: modeled | M6: NCUA 5300 call report, June 30, 2026 (ncuso.org/credit-union/68713/financials); AFS fair value total ties to call report; composition modeled | N6: =E6-D6 -> -47585.519 | O6: =COUNTIFS($A$2:$A$100,A6,$B$2:$B$100,B6,$C$2:$C$100,C6) -> 1
A7: 2026-06-30 | B7: muni | C7: afs | D7: 164880.48 | E7: 136497.17 | F7: 0.020015 | G7: 6.4141 | H7: 48.2931 | I7: 7.151 | J7: 0 | K7: Taxable municipal bonds | L7: modeled | M7: NCUA 5300 call report, June 30, 2026 (ncuso.org/credit-union/68713/financials); AFS fair value total ties to call report; composition modeled | N7: =E7-D7 -> -28383.316 | O7: =COUNTIFS($A$2:$A$100,A7,$B$2:$B$100,B7,$C$2:$C$100,C7) -> 1
A8: 2026-06-30 | B8: other | C8: afs | D8: 100000 | E8: 97853.516 | F8: 0.0425 | G8: -0.1097 | H8: 1.334 | I8: 4.71 | J8: 0 | K8: SBA 7(a) pools (prime-indexed floaters) | L8: modeled | M8: NCUA 5300 call report, June 30, 2026 (ncuso.org/credit-union/68713/financials); AFS fair value total ties to call report; composition modeled | N8: =E8-D8 -> -2146.4839 | O8: =COUNTIFS($A$2:$A$100,A8,$B$2:$B$100,B8,$C$2:$C$100,C8) -> 1
A9: 2026-06-30 | B9: agency_mbs | C9: htm | D9: 1000000 | E9: 863099.23 | F9: 0.0205 | G9: 4.993 | H9: 40.687 | I9: 6.029 | J9: 0 | K9: Agency MBS pass-throughs, 15/20-year (1.9% coupon); Agency multifamily CMBS (DUS), bullet-like | L9: modeled | M9: NCUA 5300 call report, June 30, 2026 (ncuso.org/credit-union/68713/financials); HTM amortized cost total ties to call report; composition and fair value modeled | N9: =E9-D9 -> -136900.77 | O9: =COUNTIFS($A$2:$A$100,A9,$B$2:$B$100,B9,$C$2:$C$100,C9) -> 1
A10: 2026-06-30 | B10: muni | C10: htm | D10: 200000 | E10: 169099.28 | F10: 0.026 | G10: 7.0554 | H10: 58.784 | I10: 8.125 | J10: 0 | K10: Municipal bonds (HTM) | L10: modeled | M10: NCUA 5300 call report, June 30, 2026 (ncuso.org/credit-union/68713/financials); HTM amortized cost total ties to call report; composition and fair value modeled | N10: =E10-D10 -> -30900.716 | O10: =COUNTIFS($A$2:$A$100,A10,$B$2:$B$100,B10,$C$2:$C$100,C10) -> 1
A11: 2026-06-30 | B11: agency | C11: htm | D11: 148403.71 | E11: 150178.33 | F11: 0.046 | G11: 2.7542 | H11: 9.2631 | I11: 3 | J11: 0 | K11: Agency debentures (HTM, 2024 purchase) | L11: modeled | M11: NCUA 5300 call report, June 30, 2026 (ncuso.org/credit-union/68713/financials); HTM amortized cost total ties to call report; composition and fair value modeled | N11: =E11-D11 -> 1774.6212 | O11: =COUNTIFS($A$2:$A$100,A11,$B$2:$B$100,B11,$C$2:$C$100,C11) -> 1

Sheet securities_detail
A1: period | B1: security_key | C1: label | D1: group | E1: classification | F1: book | G1: market | H1: price | I1: book_yield | J1: eff_duration | K1: eff_convexity | L1: wal_years | M1: cpr_base | N1: disc_spread | O1: fv_plus300 | P1: fv_minus300 | Q1: fv_q3_actual | R1: provenance | S1: source
A2: 2026-06-30 | B2: afs_ust | C2: U.S. Treasury notes | D2: ust | E2: afs | F2: 150000 | G2: 150051.43 | H2: 1.000343 | I2: 0.0408 | J2: 1.9386 | K2: 5.9199 | L2: 2.083 | N2: -0.000889 | O2: 141709.97 | P2: 159193.38 | Q2: 147852.17 | R2: modeled | S2: DFCU ALM model v1.0 (hypothetical; model/run_model.py)
A3: 2026-06-30 | B3: afs_agency | C3: Agency debentures (non-callable and seasoned callables) | D3: agency | E3: afs | F3: 400000 | G3: 367549.24 | H3: 0.918873 | I3: 0.011375 | J3: 2.8165 | K3: 11.3748 | L3: 3 | N3: 0.000611 | O3: 338286.92 | P3: 400582.12 | Q3: 359211.57 | R3: modeled | S3: DFCU ALM model v1.0 (hypothetical; model/run_model.py)
A4: 2026-06-30 | B4: afs_mbs_low | C4: Agency MBS pass-throughs, 2020-2021 vintage (2.0% coupon) | D4: agency_mbs | E4: afs | F4: 700000 | G4: 548633.75 | H4: 0.783763 | I4: 0.02 | J4: 7.3241 | K4: 91.3318 | L4: 9.929 | M4: 0.035 | N4: 0.004611 | O4: 447590.72 | P4: 697526.77 | Q4: 519088.34 | R4: modeled | S4: DFCU ALM model v1.0 (hypothetical; model/run_model.py)
A5: 2026-06-30 | B5: afs_mbs_high | C5: Agency MBS pass-throughs, 2023-2024 vintage (5.25% coupon) | D5: agency_mbs | E5: afs | F5: 300000 | G5: 305274.72 | H5: 1.017582 | I5: 0.0525 | J5: 6.2944 | K5: -3.5469 | L5: 8.779 | M5: 0.0746 | N5: 0.004611 | O5: 249154.03 | P5: 321993.78 | Q5: 290273.1 | R5: modeled | S5: DFCU ALM model v1.0 (hypothetical; model/run_model.py)
A6: 2026-06-30 | B6: afs_cmo | C6: Agency CMOs (sequential and PAC tranches) | D6: cmo | E6: afs | F6: 400000 | G6: 352414.48 | H6: 0.881036 | I6: 0.025 | J6: 5.0754 | K6: 76.4512 | L6: 6.085 | M6: 0.056 | N6: 0.005611 | O6: 305668.86 | P6: 411854.54 | Q6: 338570.88 | R6: modeled | S6: DFCU ALM model v1.0 (hypothetical; model/run_model.py)
A7: 2026-06-30 | B7: afs_muni | C7: Taxable municipal bonds | D7: muni | E7: afs | F7: 164880.48 | G7: 136497.17 | H7: 0.827855 | I7: 0.020015 | J7: 6.4141 | K7: 48.2931 | L7: 7.151 | N7: 0.006111 | O7: 112972.92 | P7: 165987.08 | Q7: 129270.02 | R7: modeled | S7: DFCU ALM model v1.0 (hypothetical; model/run_model.py)
A8: 2026-06-30 | B8: afs_sba | C8: SBA 7(a) pools (prime-indexed floaters) | D8: other | E8: afs | F8: 100000 | G8: 97853.516 | H8: 0.978535 | I8: 0.0425 | J8: -0.1097 | K8: 1.334 | L8: 4.71 | M8: 0.12 | N8: 0.005111 | O8: 98229.599 | P8: 97595.133 | Q8: 95781.772 | R8: modeled | S8: DFCU ALM model v1.0 (hypothetical; model/run_model.py)
A9: 2026-06-30 | B9: htm_mbs | C9: Agency MBS pass-throughs, 15/20-year (1.9% coupon) | D9: agency_mbs | E9: htm | F9: 700000 | G9: 586409.09 | H9: 0.837727 | I9: 0.019 | J9: 5.5966 | K9: 52.0346 | L9: 6.899 | M9: 0.045 | N9: 0.004611 | O9: 500273.9 | P9: 700874.76 | Q9: 560906.88 | R9: modeled | S9: DFCU ALM model v1.0 (hypothetical; model/run_model.py)
A10: 2026-06-30 | B10: htm_cmbs | C10: Agency multifamily CMBS (DUS), bullet-like | D10: agency_mbs | E10: htm | F10: 300000 | G10: 276690.13 | H10: 0.9223 | I10: 0.024 | J10: 3.7137 | K10: 16.6371 | L10: 4 | N10: 0.004111 | O10: 247836.29 | P10: 309695.9 | Q10: 268055.11 | R10: modeled | S10: DFCU ALM model v1.0 (hypothetical; model/run_model.py)
A11: 2026-06-30 | B11: htm_muni | C11: Municipal bonds (HTM) | D11: muni | E11: htm | F11: 200000 | G11: 169099.28 | H11: 0.845496 | I11: 0.026 | J11: 7.0554 | K11: 58.784 | L11: 8.125 | N11: 0.006111 | O11: 137408.72 | P11: 209796.04 | Q11: 159415.04 | R11: modeled | S11: DFCU ALM model v1.0 (hypothetical; model/run_model.py)
A12: 2026-06-30 | B12: htm_agency | C12: Agency debentures (HTM, 2024 purchase) | D12: agency | E12: htm | F12: 148403.71 | G12: 150178.33 | H12: 1.011958 | I12: 0.046 | J12: 2.7542 | K12: 9.2631 | L12: 3 | N12: 0.000611 | O12: 138372.84 | P12: 163237.38 | Q12: 146792.16 | R12: modeled | S12: DFCU ALM model v1.0 (hypothetical; model/run_model.py)

Sheet investment_cashflows
A1: month | B1: principal | C1: interest | D1: prepayments | E1: total_cash_flow
A2: 1 | B2: 7496.1553 | C2: 7541.385 | D2: 9631.2902 | E2: =B2+C2+D2 -> 24668.831
A3: 2 | B3: 7478.3406 | C3: 7502.6975 | D3: 9549.6757 | E3: =B3+C3+D3 -> 24530.714
A4: 3 | B4: 7460.5796 | C4: 7464.2599 | D4: 9468.6159 | E4: =B4+C4+D4 -> 24393.455
A5: 4 | B5: 7442.8721 | C5: 7426.0707 | D5: 9388.1068 | E5: =B5+C5+D5 -> 24257.05
A6: 5 | B6: 7425.2177 | C6: 7388.1281 | D6: 9308.1443 | E6: =B6+C6+D6 -> 24121.49
A7: 6 | B7: 7407.6163 | C7: 7350.4303 | D7: 9228.7243 | E7: =B7+C7+D7 -> 23986.771
A8: 7 | B8: 7390.0677 | C8: 7312.9758 | D8: 9149.8429 | E8: =B8+C8+D8 -> 23852.886
A9: 8 | B9: 7372.5717 | C9: 7275.7628 | D9: 9071.496 | E9: =B9+C9+D9 -> 23719.83
A10: 9 | B10: 57355.128 | C10: 7238.7896 | D10: 8993.6797 | E10: =B10+C10+D10 -> 73587.597
A11: 10 | B11: 7337.7364 | C11: 7024.9712 | D11: 8916.3901 | E11: =B11+C11+D11 -> 23279.098
A12: 11 | B12: 7320.3967 | C12: 6988.4728 | D12: 8839.6233 | E12: =B12+C12+D12 -> 23148.493
A13: 12 | B13: 7303.1088 | C13: 6952.2093 | D13: 8763.3755 | E13: =B13+C13+D13 -> 23018.694
... A331: 330 | B331: 204.37311 | C331: 0.89413234 | D331: -5.1835838e-15 | E331: =B331+C331+D331 -> 205.26724

Sheet repricing_gap
A1: period | B1: bucket | C1: side | D1: amount
A2: 2026-06-30 | B2: 0_3m | C2: asset | D2: 2751903.5
A3: 2026-06-30 | B3: 3_12m | C3: asset | D3: 847849.95
A4: 2026-06-30 | B4: 1_3y | C4: asset | D4: 2132570.2
A5: 2026-06-30 | B5: 3_5y | C5: asset | D5: 1542013.5
A6: 2026-06-30 | B6: 5_10y | C6: asset | D6: 1122748
A7: 2026-06-30 | B7: 10y_plus | C7: asset | D7: 871798.21
A8: 2026-06-30 | B8: nonrate | C8: asset | D8: 618961.62
A9: 2026-06-30 | B9: 0_3m | C9: liability | D9: 2230363.4
A10: 2026-06-30 | B10: 3_12m | C10: liability | D10: 1853615.7
A11: 2026-06-30 | B11: 1_3y | C11: liability | D11: 1753396.9
A12: 2026-06-30 | B12: 3_5y | C12: liability | D12: 984960.76
A13: 2026-06-30 | B13: 5_10y | C13: liability | D13: 1190866.1
... A29: 2026-06-30 | B29: nonrate | C29: off_balance | D29: 0

Sheet repricing_gap_detail
A1: line_key | B1: side | C1: bucket | D1: amount
A2: cash_fed | B2: asset | C2: 0_3m | D2: 654788.14
A3: cash_fed | B3: asset | C3: 3_12m | D3: 0
A4: cash_fed | B4: asset | C4: 1_3y | D4: 0
A5: cash_fed | B5: asset | C5: 3_5y | D5: 0
A6: cash_fed | B6: asset | C6: 5_10y | D6: 0
A7: cash_fed | B7: asset | C7: 10y_plus | D7: 0
A8: cash_vault | B8: asset | C8: nonrate | D8: 40466.353
A9: equity_securities | B9: asset | C9: nonrate | D9: 24065.482
A10: pcc | B10: asset | C10: nonrate | D10: 656.25
A11: loans_hfs | B11: asset | C11: 0_3m | D11: 1976.718
A12: loans_hfs | B12: asset | C12: 3_12m | D12: 0
A13: loans_hfs | B13: asset | C13: 1_3y | D13: 0
... A258: ira__ira_certificates | B258: liability | C258: 10y_plus | D258: 0

Sheet scenarios
A1: scenario_key | B1: scenario_label | C1: type | D1: sort_order | E1: nev_applicable | F1: description | G1: shift_2y_bp_month0 | H1: shift_10y_bp_month0 | I1: shift_2y_bp_month12 | J1: shift_10y_bp_month12 | K1: fed_funds_shift_bp_month12 | L1: credit_stress
A2: shock_m300 | B2: -300bp shock | C2: shock | D2: 1 | E2: y | F2: Instantaneous, sustained parallel shift of -300bp (rates floored at 0.01%) | G2: -300 | H2: -300 | I2: -300 | J2: -300 | K2: -300 | L2: none
A3: shock_m200 | B3: -200bp shock | C3: shock | D3: 2 | E3: y | F3: Instantaneous, sustained parallel shift of -200bp (rates floored at 0.01%) | G3: -200 | H3: -200 | I3: -200 | J3: -200 | K3: -200 | L3: none
A4: shock_m100 | B4: -100bp shock | C4: shock | D4: 3 | E4: y | F4: Instantaneous, sustained parallel shift of -100bp (rates floored at 0.01%) | G4: -100 | H4: -100 | I4: -100 | J4: -100 | K4: -100 | L4: none
A5: base | B5: Base (flat rates) | C5: shock | D5: 4 | E5: y | F5: Rates held flat at the June 30, 2026 curve | G5: 0 | H5: 0 | I5: 0 | J5: 0 | K5: 0 | L5: none
A6: shock_p100 | B6: +100bp shock | C6: shock | D6: 5 | E6: y | F6: Instantaneous, sustained parallel shift of +100bp | G6: 100 | H6: 100 | I6: 100 | J6: 100 | K6: 100 | L6: none
A7: shock_p200 | B7: +200bp shock | C7: shock | D7: 6 | E7: y | F7: Instantaneous, sustained parallel shift of +200bp | G7: 200 | H7: 200 | I7: 200 | J7: 200 | K7: 200 | L7: none
A8: shock_p300 | B8: +300bp shock | C8: shock | D8: 7 | E8: y | F8: Instantaneous, sustained parallel shift of +300bp | G8: 300 | H8: 300 | I8: 300 | J8: 300 | K8: 300 | L8: none
A9: shock_p400 | B9: +400bp shock | C9: shock | D9: 8 | E9: y | F9: Instantaneous, sustained parallel shift of +400bp | G9: 400 | H9: 400 | I9: 400 | J9: 400 | K9: 400 | L9: none
A10: ramp_m200 | B10: -200bp ramp (12 mo) | C10: ramp | D10: 9 | E10: n | F10: Parallel -200bp phased in evenly over 12 months, then held | G10: 0 | H10: 0 | I10: -200 | J10: -200 | K10: -200 | L10: none
A11: ramp_m100 | B11: -100bp ramp (12 mo) | C11: ramp | D11: 10 | E11: n | F11: Parallel -100bp phased in evenly over 12 months, then held | G11: 0 | H11: 0 | I11: -100 | J11: -100 | K11: -100 | L11: none
A12: ramp_p100 | B12: +100bp ramp (12 mo) | C12: ramp | D12: 11 | E12: n | F12: Parallel +100bp phased in evenly over 12 months, then held | G12: 0 | H12: 0 | I12: 100 | J12: 100 | K12: 100 | L12: none
A13: ramp_p200 | B13: +200bp ramp (12 mo) | C13: ramp | D13: 12 | E13: n | F13: Parallel +200bp phased in evenly over 12 months, then held | G13: 0 | H13: 0 | I13: 200 | J13: 200 | K13: 200 | L13: none
... A21: ncua_nev_test | B21: NCUA NEV Test (+300, standardized NMS) | C21: supervisory | D21: 20 | E21: y | F21: +300bp instantaneous shock with NCUA standardized non-maturity share values (approximated as a 1% premium at base and 5% after the shock) | G21: 300 | H21: 300 | I21: 300 | J21: 300 | K21: 300 | L21: none

Sheet rate_scenarios
A1: scenario_key | B1: scenario_label | C1: type | D1: sort_order | E1: month | F1: tenor | G1: rate
A2: shock_m300 | B2: -300bp shock | C2: shock | D2: 1 | E2: 0 | F2: fed_funds | G2: 0.0063
A3: shock_m300 | B3: -300bp shock | C3: shock | D3: 1 | E3: 0 | F3: prime | G3: 0.0375
A4: shock_m300 | B4: -300bp shock | C4: shock | D4: 1 | E4: 0 | F4: sofr | G4: 0.0061
A5: shock_m300 | B5: -300bp shock | C5: shock | D5: 1 | E5: 0 | F5: 3m | G5: 0.0087
A6: shock_m300 | B6: -300bp shock | C6: shock | D6: 1 | E6: 0 | F6: 6m | G6: 0.0101
A7: shock_m300 | B7: -300bp shock | C7: shock | D7: 1 | E7: 0 | F7: 1y | G7: 0.0098
A8: shock_m300 | B8: -300bp shock | C8: shock | D8: 1 | E8: 0 | F8: 2y | G8: 0.0114
A9: shock_m300 | B9: -300bp shock | C9: shock | D9: 1 | E9: 0 | F9: 3y | G9: 0.0115
A10: shock_m300 | B10: -300bp shock | C10: shock | D10: 1 | E10: 0 | F10: 5y | G10: 0.0119
A11: shock_m300 | B11: -300bp shock | C11: shock | D11: 1 | E11: 0 | F11: 7y | G11: 0.013
A12: shock_m300 | B12: -300bp shock | C12: shock | D12: 1 | E12: 0 | F12: 10y | G12: 0.0144
A13: shock_m300 | B13: -300bp shock | C13: shock | D13: 1 | E13: 0 | F13: 20y | G13: 0.0193
... A7001: ncua_nev_test | B7001: NCUA NEV Test (+300, standardized NMS) | C7001: supervisory | D7001: 20 | E7001: 24 | F7001: mortgage_30y | G7001: 0.0949

Sheet nii_simulation
A1: scenario_key | B1: month | C1: interest_income | D1: interest_expense | E1: nii | F1: fee_income_rate_sensitive | G1: net_income | H1: noninterest_income_other | I1: noninterest_expense | J1: provision | K1: member_giveback
A2: shock_m300 | B2: 1 | C2: 31767.664 | D2: 10848.487 | E2: =C2-D2 -> 20919.177 | F2: 855 | G2: =E2+F2+H2-I2-J2-K2 -> 7512.0949 | H2: 13202.311 | I2: 25860.83 | J2: 1603.5628 | K2: 0
A3: shock_m300 | B3: 2 | C3: 31521.01 | D3: 8387.1903 | E3: =C3-D3 -> 23133.82 | F3: 855 | G3: =E3+F3+H3-I3-J3-K3 -> 9662.2471 | H3: 13202.311 | I3: 25925.321 | J3: 1603.5628 | K3: 0
A4: shock_m300 | B4: 3 | C4: 31276.283 | D4: 7146.2331 | E4: =C4-D4 -> 24130.05 | F4: 855 | G4: =E4+F4+H4-I4-J4-K4 -> 10593.986 | H4: 13202.311 | I4: 25989.812 | J4: 1603.5628 | K4: 0
A5: shock_m300 | B5: 4 | C5: 31043.214 | D5: 6445.8035 | E5: =C5-D5 -> 24597.411 | F5: 855 | G5: =E5+F5+H5-I5-J5-K5 -> 10996.856 | H5: 13202.311 | I5: 26054.303 | J5: 1603.5628 | K5: 0
A6: shock_m300 | B6: 5 | C6: 30816.665 | D6: 6122.1523 | E6: =C6-D6 -> 24694.513 | F6: 855 | G6: =E6+F6+H6-I6-J6-K6 -> 11029.467 | H6: 13202.311 | I6: 26118.794 | J6: 1603.5628 | K6: 0
A7: shock_m300 | B7: 6 | C7: 30596.459 | D7: 5798.501 | E7: =C7-D7 -> 24797.958 | F7: 855 | G7: =E7+F7+H7-I7-J7-K7 -> 11068.422 | H7: 13202.311 | I7: 26183.285 | J7: 1603.5628 | K7: 0
A8: shock_m300 | B8: 7 | C8: 30382.427 | D8: 5474.8498 | E8: =C8-D8 -> 24907.577 | F8: 855 | G8: =E8+F8+H8-I8-J8-K8 -> 11113.55 | H8: 13202.311 | I8: 26247.775 | J8: 1603.5628 | K8: 0
A9: shock_m300 | B9: 8 | C9: 30174.402 | D9: 5260.6893 | E9: =C9-D9 -> 24913.713 | F9: 855 | G9: =E9+F9+H9-I9-J9-K9 -> -4944.8048 | H9: 13202.311 | I9: 26312.266 | J9: 1603.5628 | K9: 16000
A10: shock_m300 | B10: 9 | C10: 29972.224 | D10: 5046.5289 | E10: =C10-D10 -> 24925.695 | F10: 855 | G10: =E10+F10+H10-I10-J10-K10 -> 11002.686 | H10: 13202.311 | I10: 26376.757 | J10: 1603.5628 | K10: 0
A11: shock_m300 | B11: 10 | C11: 29646.15 | D11: 4832.3684 | E11: =C11-D11 -> 24813.782 | F11: 855 | G11: =E11+F11+H11-I11-J11-K11 -> 10826.282 | H11: 13202.311 | I11: 26441.248 | J11: 1603.5628 | K11: 0
A12: shock_m300 | B12: 11 | C12: 29455.197 | D12: 4662.7747 | E12: =C12-D12 -> 24792.422 | F12: 855 | G12: =E12+F12+H12-I12-J12-K12 -> 10740.431 | H12: 13202.311 | I12: 26505.739 | J12: 1603.5628 | K12: 0
A13: shock_m300 | B13: 12 | C13: 29269.631 | D13: 4493.1811 | E13: =C13-D13 -> 24776.449 | F13: 855 | G13: =E13+F13+H13-I13-J13-K13 -> 10659.968 | H13: 13202.311 | I13: 26570.23 | J13: 1603.5628 | K13: 0
... A481: ncua_nev_test | B481: 24 | C481: 50695.76 | D481: 21163.817 | E481: =C481-D481 -> 29531.943 | F481: 112.5 | G481: =E481+F481+H481-I481-J481-K481 -> 13899.071 | H481: 13202.311 | I481: 27344.12 | J481: 1603.5628 | K481: 0

Sheet nii_attribution
A1: scenario_key | B1: horizon | C1: line_item | D1: nii_change
A2: shock_m300 | B2: y1 | C2: Cash and equivalents | D2: -19643.644
A3: shock_m300 | B3: y1 | C3: Securities, fixed rate | D3: -4320.3316
A4: shock_m300 | B4: y1 | C4: Securities, floating (SBA pools) | D4: -3000
A5: shock_m300 | B5: y1 | C5: HELOC | D5: -44866.896
A6: shock_m300 | B6: y1 | C6: Home equity loans, fixed | D6: -1869.3875
A7: shock_m300 | B7: y1 | C7: Vehicle loans | D7: -8534.9502
A8: shock_m300 | B8: y1 | C8: First mortgages | D8: -1869.183
A9: shock_m300 | B9: y1 | C9: Commercial real estate | D9: -6047.9594
A10: shock_m300 | B10: y1 | C10: Commercial and industrial | D10: -462.236
A11: shock_m300 | B11: y1 | C11: Consumer, other | D11: -1819.8241
A12: shock_m300 | B12: y1 | C12: FHLB stock dividends | D12: 0
A13: shock_m300 | B13: y1 | C13: Checking, savings and other shares | D13: 1525.0812
... A571: ncua_nev_test | B571: y2 | C571: Money market migration to certificates | D571: -36824.575

Sheet nev
A1: scenario_key | B1: category | C1: side | D1: book | E1: fair_value | F1: eff_duration | G1: group | H1: eff_convexity | I1: method
A2: shock_m300 | B2: Cash and cash equivalents | C2: asset | D2: 695254.49 | E2: 695254.49 | F2: 0 | G2: Cash | H2: 0 | I2: internal
A3: shock_m300 | B3: AFS: U.S. Treasury notes | C3: asset | D3: 150051.43 | E3: 159193.38 | F3: 2.0048 | G3: Securities | H3: 6.2727 | I3: internal
A4: shock_m300 | B4: AFS: Agency debentures | C4: asset | D4: 367549.24 | E4: 400582.12 | F4: 2.9222 | G4: Securities | H4: 12.1376 | I4: internal
A5: shock_m300 | B5: AFS: Agency MBS, 2.0% coupon | C5: asset | D5: 548633.75 | E5: 697526.77 | F5: 8.0772 | G5: Securities | H5: 52.978 | I5: internal
A6: shock_m300 | B6: AFS: Agency MBS, 5.25% coupon | C6: asset | D6: 305274.72 | E6: 321993.78 | F6: -0.978 | G6: Securities | H6: 4.8513 | I6: internal
A7: shock_m300 | B7: AFS: Agency CMOs | C7: asset | D7: 352414.48 | E7: 411854.54 | F7: 5.0004 | G7: Securities | H7: 20.0322 | I7: internal
A8: shock_m300 | B8: AFS: Taxable municipals | C8: asset | D8: 136497.17 | E8: 165987.08 | F8: 6.6302 | G8: Securities | H8: 51.1766 | I8: internal
A9: shock_m300 | B9: AFS: SBA floating pools | C9: asset | D9: 97853.516 | E9: 97595.133 | F9: -0.0646 | G9: Securities | H9: 1.6947 | I9: internal
A10: shock_m300 | B10: HTM: Agency MBS | C10: asset | D10: 700000 | E10: 700874.76 | F10: 5.9906 | G10: Securities | H10: 29.0247 | I10: internal
A11: shock_m300 | B11: HTM: Agency multifamily CMBS | C11: asset | D11: 300000 | E11: 309695.9 | F11: 3.8003 | G11: Securities | H11: 17.3637 | I11: internal
A12: shock_m300 | B12: HTM: Municipals | C12: asset | D12: 200000 | E12: 209796.04 | F12: 7.3258 | G12: Securities | H12: 62.6324 | I12: internal
A13: shock_m300 | B13: HTM: Agency debentures | C13: asset | D13: 148403.71 | E13: 163237.38 | F13: 2.8051 | G13: Securities | H13: 9.5831 | I13: internal
... A47: shock_m300 | B47: Other liabilities | C47: liability | D47: 124418.2 | E47: 124418.2 | F47: 0 | G47: Other liabilities | H47: 0 | I47: internal
A48: shock_m300 | B48: Fixed-rate loan commitments (pipeline) | C48: off_balance | D48: 0 | E48: 2700 | G48: Off-balance sheet | I48: internal
A49: shock_m200 | B49: Cash and cash equivalents | C49: asset | D49: 695254.49 | E49: 695254.49 | F49: 0 | G49: Cash | H49: 0 | I49: internal
A50: shock_m200 | B50: AFS: U.S. Treasury notes | C50: asset | D50: 150051.43 | E50: 156051.27 | F50: 1.9824 | G50: Securities | H50: 6.1526 | I50: internal
A51: shock_m200 | B51: AFS: Agency debentures | C51: asset | D51: 367549.24 | E51: 389116.47 | F51: 2.8864 | G51: Securities | H51: 11.8775 | I51: internal
A52: shock_m200 | B52: AFS: Agency MBS, 2.0% coupon | C52: asset | D52: 548633.75 | E52: 642996.77 | F52: 8.2103 | G52: Securities | H52: 52.9651 | I52: internal
A53: shock_m200 | B53: AFS: Agency MBS, 5.25% coupon | C53: asset | D53: 305274.72 | E53: 325131.77 | F53: -0.8162 | G53: Securities | H53: -53.4188 | I53: internal
A54: shock_m200 | B54: AFS: Agency CMOs | C54: asset | D54: 352414.48 | E54: 391547.37 | F54: 5.145 | G54: Securities | H54: 8.2809 | I54: internal
A55: shock_m200 | B55: AFS: Taxable municipals | C55: asset | D55: 136497.17 | E55: 155397.7 | F55: 6.5579 | G55: Securities | H55: 50.2018 | I55: internal
A56: shock_m200 | B56: AFS: SBA floating pools | C56: asset | D56: 97853.516 | E56: 97666.295 | F56: -0.0809 | G56: Securities | H56: 1.5718 | I56: internal
A57: shock_m200 | B57: HTM: Agency MBS | C57: asset | D57: 700000 | E57: 659889.84 | F57: 6.0635 | G57: Securities | H57: 29.0241 | I57: internal
A58: shock_m200 | B58: HTM: Agency multifamily CMBS | C58: asset | D58: 300000 | E58: 298192.04 | F58: 3.7712 | G58: Securities | H58: 17.1175 | I58: internal
A59: shock_m200 | B59: HTM: Municipals | C59: asset | D59: 200000 | E59: 195068.75 | F59: 7.2358 | G59: Securities | H59: 61.3348 | I59: internal
A60: shock_m200 | B60: HTM: Agency debentures | C60: asset | D60: 148403.71 | E60: 158735.87 | F60: 2.788 | G60: Securities | H60: 9.475 | I60: internal
... A94: shock_m200 | B94: Other liabilities | C94: liability | D94: 124418.2 | E94: 124418.2 | F94: 0 | G94: Other liabilities | H94: 0 | I94: internal
A95: shock_m200 | B95: Fixed-rate loan commitments (pipeline) | C95: off_balance | D95: 0 | E95: 1800 | G95: Off-balance sheet | I95: internal
A96: shock_m100 | B96: Cash and cash equivalents | C96: asset | D96: 695254.49 | E96: 695254.49 | F96: 0 | G96: Cash | H96: 0 | I96: internal
A97: shock_m100 | B97: AFS: U.S. Treasury notes | C97: asset | D97: 150051.43 | E97: 153005.18 | F97: 1.9604 | G97: Securities | H97: 6.035 | I97: internal
A98: shock_m100 | B98: AFS: Agency debentures | C98: asset | D98: 367549.24 | E98: 378113.07 | F98: 2.8512 | G98: Securities | H98: 11.6233 | I98: internal
A99: shock_m100 | B99: AFS: Agency MBS, 2.0% coupon | C99: asset | D99: 548633.75 | E99: 591874.03 | F99: 8.055 | G99: Securities | H99: 177.7279 | I99: internal
A100: shock_m100 | B100: AFS: Agency MBS, 5.25% coupon | C100: asset | D100: 305274.72 | E100: 324902.03 | F100: 3.5003 | G100: Securities | H100: -1070.3269 | I100: internal
A101: shock_m100 | B101: AFS: Agency CMOs | C101: asset | D101: 352414.48 | E101: 371564.41 | F101: 5.3344 | G101: Securities | H101: 8.7289 | I101: internal
A102: shock_m100 | B102: AFS: Taxable municipals | C102: asset | D102: 136497.17 | E102: 145588.81 | F102: 6.4859 | G102: Securities | H102: 49.2406 | I102: internal
A103: shock_m100 | B103: AFS: SBA floating pools | C103: asset | D103: 97853.516 | E103: 97752.811 | F103: -0.0959 | G103: Securities | H103: 1.4514 | I103: internal
A104: shock_m100 | B104: HTM: Agency MBS | C104: asset | D104: 700000 | E104: 620820.68 | F104: 5.9474 | G104: Securities | H104: 108.3409 | I104: internal
A105: shock_m100 | B105: HTM: Agency multifamily CMBS | C105: asset | D105: 300000 | E105: 287198.71 | F105: 3.7423 | G105: Securities | H105: 16.8754 | I105: internal
A106: shock_m100 | B106: HTM: Municipals | C106: asset | D106: 200000 | E106: 181538.61 | F106: 7.1456 | G106: Securities | H106: 60.0521 | I106: internal
A107: shock_m100 | B107: HTM: Agency debentures | C107: asset | D107: 148403.71 | E107: 154384.78 | F107: 2.771 | G107: Securities | H107: 9.3683 | I107: internal
... A141: shock_m100 | B141: Other liabilities | C141: liability | D141: 124418.2 | E141: 124418.2 | F141: 0 | G141: Other liabilities | H141: 0 | I141: internal
A142: shock_m100 | B142: Fixed-rate loan commitments (pipeline) | C142: off_balance | D142: 0 | E142: 900 | G142: Off-balance sheet | I142: internal
A143: base | B143: Cash and cash equivalents | C143: asset | D143: 695254.49 | E143: 695254.49 | F143: 0 | G143: Cash | H143: 0 | I143: internal
A144: base | B144: AFS: U.S. Treasury notes | C144: asset | D144: 150051.43 | E144: 150051.43 | F144: 1.9386 | G144: Securities | H144: 5.9199 | I144: internal
A145: base | B145: AFS: Agency debentures | C145: asset | D145: 367549.24 | E145: 367549.24 | F145: 2.8165 | G145: Securities | H145: 11.3748 | I145: internal
A146: base | B146: AFS: Agency MBS, 2.0% coupon | C146: asset | D146: 548633.75 | E146: 548633.75 | F146: 7.3241 | G146: Securities | H146: 91.3318 | I146: internal
A147: base | B147: AFS: Agency MBS, 5.25% coupon | C147: asset | D147: 305274.72 | E147: 305274.72 | F147: 6.2944 | G147: Securities | H147: -3.5469 | I147: internal
A148: base | B148: AFS: Agency CMOs | C148: asset | D148: 352414.48 | E148: 352414.48 | F148: 5.0754 | G148: Securities | H148: 76.4512 | I148: internal
A149: base | B149: AFS: Taxable municipals | C149: asset | D149: 136497.17 | E149: 136497.17 | F149: 6.4141 | G149: Securities | H149: 48.2931 | I149: internal
A150: base | B150: AFS: SBA floating pools | C150: asset | D150: 97853.516 | E150: 97853.516 | F150: -0.1097 | G150: Securities | H150: 1.334 | I150: internal
A151: base | B151: HTM: Agency MBS | C151: asset | D151: 700000 | E151: 586409.09 | F151: 5.5966 | G151: Securities | H151: 52.0346 | I151: internal
A152: base | B152: HTM: Agency multifamily CMBS | C152: asset | D152: 300000 | E152: 276690.13 | F152: 3.7137 | G152: Securities | H152: 16.6371 | I152: internal
A153: base | B153: HTM: Municipals | C153: asset | D153: 200000 | E153: 169099.28 | F153: 7.0554 | G153: Securities | H153: 58.784 | I153: internal
A154: base | B154: HTM: Agency debentures | C154: asset | D154: 148403.71 | E154: 150178.33 | F154: 2.7542 | G154: Securities | H154: 9.2631 | I154: internal
... A188: base | B188: Other liabilities | C188: liability | D188: 124418.2 | E188: 124418.2 | F188: 0 | G188: Other liabilities | H188: 0 | I188: internal
A189: base | B189: Fixed-rate loan commitments (pipeline) | C189: off_balance | D189: 0 | E189: 0 | G189: Off-balance sheet | I189: internal
A190: shock_p100 | B190: Cash and cash equivalents | C190: asset | D190: 695254.49 | E190: 695254.49 | F190: 0 | G190: Cash | H190: 0 | I190: internal
A191: shock_p100 | B191: AFS: U.S. Treasury notes | C191: asset | D191: 150051.43 | E191: 147186.53 | F191: 1.9171 | G191: Securities | H191: 5.8073 | I191: internal
A192: shock_p100 | B192: AFS: Agency debentures | C192: asset | D192: 367549.24 | E192: 357403.57 | F192: 2.7824 | G192: Securities | H192: 11.132 | I192: internal
A193: shock_p100 | B193: AFS: Agency MBS, 2.0% coupon | C193: asset | D193: 548633.75 | E193: 510862.03 | F193: 6.9573 | G193: Securities | H193: 83.8957 | I193: internal
A194: shock_p100 | B194: AFS: Agency MBS, 5.25% coupon | C194: asset | D194: 305274.72 | E194: 286007.93 | F194: 6.7527 | G194: Securities | H194: -3.0677 | I194: internal
A195: shock_p100 | B195: AFS: Agency CMOs | C195: asset | D195: 352414.48 | E195: 335550.2 | F195: 4.8232 | G195: Securities | H195: 39.4718 | I195: internal
A196: shock_p100 | B196: AFS: Taxable municipals | C196: asset | D196: 136497.17 | E196: 128065.02 | F196: 6.3425 | G196: Securities | H196: 47.3589 | I196: internal
A197: shock_p100 | B197: AFS: SBA floating pools | C197: asset | D197: 97853.516 | E197: 97967.277 | F197: -0.1224 | G197: Securities | H197: 1.22 | I197: internal
A198: shock_p100 | B198: HTM: Agency MBS | C198: asset | D198: 700000 | E198: 555072.98 | F198: 5.3932 | G198: Securities | H198: 48.9862 | I198: internal
A199: shock_p100 | B199: HTM: Agency multifamily CMBS | C199: asset | D199: 300000 | E199: 266641.97 | F199: 3.6853 | G199: Securities | H199: 16.4028 | I199: internal
A200: shock_p100 | B200: HTM: Municipals | C200: asset | D200: 200000 | E200: 157654.56 | F200: 6.965 | G200: Securities | H200: 57.5305 | I200: internal
A201: shock_p100 | B201: HTM: Agency debentures | C201: asset | D201: 148403.71 | E201: 146111.01 | F201: 2.7375 | G201: Securities | H201: 9.1593 | I201: internal
... A235: shock_p100 | B235: Other liabilities | C235: liability | D235: 124418.2 | E235: 124418.2 | F235: 0 | G235: Other liabilities | H235: 0 | I235: internal
A236: shock_p100 | B236: Fixed-rate loan commitments (pipeline) | C236: off_balance | D236: 0 | E236: -1440 | G236: Off-balance sheet | I236: internal
A237: shock_p200 | B237: Cash and cash equivalents | C237: asset | D237: 695254.49 | E237: 695254.49 | F237: 0 | G237: Cash | H237: 0 | I237: internal
A238: shock_p200 | B238: AFS: U.S. Treasury notes | C238: asset | D238: 150051.43 | E238: 144407.11 | F238: 1.896 | G238: Securities | H238: 5.697 | I238: internal
A239: shock_p200 | B239: AFS: Agency debentures | C239: asset | D239: 367549.24 | E239: 347655.83 | F239: 2.7487 | G239: Securities | H239: 10.8947 | I239: internal
A240: shock_p200 | B240: AFS: Agency MBS, 2.0% coupon | C240: asset | D240: 548633.75 | E240: 477383.6 | F240: 6.6123 | G240: Securities | H240: 77.0759 | I240: internal
A241: shock_p200 | B241: AFS: Agency MBS, 5.25% coupon | C241: asset | D241: 305274.72 | E241: 266653.38 | F241: 7.2257 | G241: Securities | H241: 15.9621 | I241: internal
A242: shock_p200 | B242: AFS: Agency CMOs | C242: asset | D242: 352414.48 | E242: 320011.43 | F242: 4.664 | G242: Securities | H242: 37.3522 | I242: internal
A243: shock_p200 | B243: AFS: Taxable municipals | C243: asset | D243: 136497.17 | E243: 120239.66 | F243: 6.2711 | G243: Securities | H243: 46.4379 | I243: internal
A244: shock_p200 | B244: AFS: SBA floating pools | C244: asset | D244: 97853.516 | E244: 98092.992 | F244: -0.1338 | G244: Securities | H244: 1.1101 | I244: internal
A245: shock_p200 | B245: HTM: Agency MBS | C245: asset | D245: 700000 | E245: 526458.51 | F245: 5.198 | G245: Securities | H245: 46.113 | I245: internal
A246: shock_p200 | B246: HTM: Agency multifamily CMBS | C246: asset | D246: 300000 | E246: 257031.26 | F246: 3.6572 | G246: Securities | H246: 16.1722 | I246: internal
A247: shock_p200 | B247: HTM: Municipals | C247: asset | D247: 200000 | E247: 147117.34 | F247: 6.8745 | G247: Securities | H247: 56.2914 | I247: internal
A248: shock_p200 | B248: HTM: Agency debentures | C248: asset | D248: 148403.71 | E248: 142177.54 | F248: 2.7209 | G248: Securities | H248: 9.0569 | I248: internal
... A282: shock_p200 | B282: Other liabilities | C282: liability | D282: 124418.2 | E282: 124418.2 | F282: 0 | G282: Other liabilities | H282: 0 | I282: internal
A283: shock_p200 | B283: Fixed-rate loan commitments (pipeline) | C283: off_balance | D283: 0 | E283: -2880 | G283: Off-balance sheet | I283: internal
A284: shock_p300 | B284: Cash and cash equivalents | C284: asset | D284: 695254.49 | E284: 695254.49 | F284: 0 | G284: Cash | H284: 0 | I284: internal
A285: shock_p300 | B285: AFS: U.S. Treasury notes | C285: asset | D285: 150051.43 | E285: 141709.97 | F285: 1.8751 | G285: Securities | H285: 5.589 | I285: internal
A286: shock_p300 | B286: AFS: Agency debentures | C286: asset | D286: 367549.24 | E286: 338286.92 | F286: 2.7155 | G286: Securities | H286: 10.6628 | I286: internal
A287: shock_p300 | B287: AFS: Agency MBS, 2.0% coupon | C287: asset | D287: 548633.75 | E287: 447590.72 | F287: 6.2885 | G287: Securities | H287: 70.8346 | I287: internal
A288: shock_p300 | B288: AFS: Agency MBS, 5.25% coupon | C288: asset | D288: 305274.72 | E288: 249154.03 | F288: 6.1794 | G288: Securities | H288: 70.862 | I288: internal
A289: shock_p300 | B289: AFS: Agency CMOs | C289: asset | D289: 352414.48 | E289: 305668.86 | F289: 4.5109 | G289: Securities | H289: 35.3479 | I289: internal
A290: shock_p300 | B290: AFS: Taxable municipals | C290: asset | D290: 136497.17 | E290: 112972.92 | F290: 6.1999 | G290: Securities | H290: 45.5299 | I290: internal
A291: shock_p300 | B291: AFS: SBA floating pools | C291: asset | D291: 97853.516 | E291: 98229.599 | F291: -0.1442 | G291: Securities | H291: 1.0047 | I291: internal
A292: shock_p300 | B292: HTM: Agency MBS | C292: asset | D292: 700000 | E292: 500273.9 | F292: 5.0108 | G292: Securities | H292: 43.4083 | I292: internal
A293: shock_p300 | B293: HTM: Agency multifamily CMBS | C293: asset | D293: 300000 | E293: 247836.29 | F293: 3.6294 | G293: Securities | H293: 15.9453 | I293: internal
A294: shock_p300 | B294: HTM: Municipals | C294: asset | D294: 200000 | E294: 137408.72 | F294: 6.7838 | G294: Securities | H294: 55.0665 | I294: internal
A295: shock_p300 | B295: HTM: Agency debentures | C295: asset | D295: 148403.71 | E295: 138372.84 | F295: 2.7044 | G295: Securities | H295: 8.9559 | I295: internal
... A329: shock_p300 | B329: Other liabilities | C329: liability | D329: 124418.2 | E329: 124418.2 | F329: 0 | G329: Other liabilities | H329: 0 | I329: internal
A330: shock_p300 | B330: Fixed-rate loan commitments (pipeline) | C330: off_balance | D330: 0 | E330: -4320 | G330: Off-balance sheet | I330: internal
A331: shock_p400 | B331: Cash and cash equivalents | C331: asset | D331: 695254.49 | E331: 695254.49 | F331: 0 | G331: Cash | H331: 0 | I331: internal
...

Sheet nev_test
A1: period | B1: method | C1: base_nev | D1: base_nev_ratio | E1: post_shock_nev | F1: post_shock_nev_ratio | G1: afs_fair_value_model | H1: provenance | I1: source | J1: sensitivity | K1: classification | L1: row_key
A2: 2024-09-30 | B2: internal | C2: 1172337.3 | D2: 0.1381727 | E2: 970524.18 | F2: 0.12441507 | G2: 2145301.5 | H2: modeled | I2: Reconstructed balance sheet (June 2026 mix scaled to period balances, repriced to the period curve); AFS spread interpolated between calibrated dates | J2: =E2/C2-1 -> -0.17214592 | K2: =IF(OR(F2<meta!$B$19,J2<-meta!$B$21),"High",IF(OR(F2<meta!$B$18,J2<-meta!$B$20),"Moderate","Low")) -> Low | L2: =A2&"|"&B2 -> 2024-09-30|internal
A3: 2024-09-30 | B3: ncua_test | C3: 554927.15 | D3: 0.0654042 | E3: 153493.2 | F3: 0.019676859 | G3: 2145301.5 | H3: modeled | I3: Reconstructed balance sheet (June 2026 mix scaled to period balances, repriced to the period curve); AFS spread interpolated between calibrated dates | J3: =E3/C3-1 -> -0.72339937 | K3: =IF(OR(F3<meta!$B$19,J3<-meta!$B$21),"High",IF(OR(F3<meta!$B$18,J3<-meta!$B$20),"Moderate","Low")) -> High | L3: =A3&"|"&B3 -> 2024-09-30|ncua_test
A4: 2024-12-31 | B4: internal | C4: 1175027.5 | D4: 0.13996585 | E4: 985730.14 | F4: 0.12727362 | G4: 2051268.5 | H4: modeled | I4: Reconstructed balance sheet (June 2026 mix scaled to period balances, repriced to the period curve); AFS fair value calibrated to reported value | J4: =E4/C4-1 -> -0.16110036 | K4: =IF(OR(F4<meta!$B$19,J4<-meta!$B$21),"High",IF(OR(F4<meta!$B$18,J4<-meta!$B$20),"Moderate","Low")) -> Low | L4: =A4&"|"&B4 -> 2024-12-31|internal
A5: 2024-12-31 | B5: ncua_test | C5: 385681.65 | D5: 0.045941274 | E5: 23021.467 | F5: 0.0029724418 | G5: 2051268.5 | H5: modeled | I5: Reconstructed balance sheet (June 2026 mix scaled to period balances, repriced to the period curve); AFS fair value calibrated to reported value | J5: =E5/C5-1 -> -0.94030966 | K5: =IF(OR(F5<meta!$B$19,J5<-meta!$B$21),"High",IF(OR(F5<meta!$B$18,J5<-meta!$B$20),"Moderate","Low")) -> High | L5: =A5&"|"&B5 -> 2024-12-31|ncua_test
A6: 2025-03-31 | B6: internal | C6: 1222833.7 | D6: 0.13943707 | E6: 1041212.5 | F6: 0.12858937 | G6: 2073145.3 | H6: modeled | I6: Reconstructed balance sheet (June 2026 mix scaled to period balances, repriced to the period curve); AFS spread interpolated between calibrated dates | J6: =E6/C6-1 -> -0.14852486 | K6: =IF(OR(F6<meta!$B$19,J6<-meta!$B$21),"High",IF(OR(F6<meta!$B$18,J6<-meta!$B$20),"Moderate","Low")) -> Low | L6: =A6&"|"&B6 -> 2025-03-31|internal
A7: 2025-03-31 | B7: ncua_test | C7: 470408.48 | D7: 0.053639655 | E7: 95959.117 | F7: 0.011850917 | G7: 2073145.3 | H7: modeled | I7: Reconstructed balance sheet (June 2026 mix scaled to period balances, repriced to the period curve); AFS spread interpolated between calibrated dates | J7: =E7/C7-1 -> -0.79600895 | K7: =IF(OR(F7<meta!$B$19,J7<-meta!$B$21),"High",IF(OR(F7<meta!$B$18,J7<-meta!$B$20),"Moderate","Low")) -> High | L7: =A7&"|"&B7 -> 2025-03-31|ncua_test
A8: 2025-06-30 | B8: internal | C8: 1243200.1 | D8: 0.14188117 | E8: 1049661.8 | F8: 0.12991133 | G8: 2062597.5 | H8: modeled | I8: Reconstructed balance sheet (June 2026 mix scaled to period balances, repriced to the period curve); AFS spread interpolated between calibrated dates | J8: =E8/C8-1 -> -0.15567752 | K8: =IF(OR(F8<meta!$B$19,J8<-meta!$B$21),"High",IF(OR(F8<meta!$B$18,J8<-meta!$B$20),"Moderate","Low")) -> Low | L8: =A8&"|"&B8 -> 2025-06-30|internal
A9: 2025-06-30 | B9: ncua_test | C9: 502354.14 | D9: 0.057331552 | E9: 116684.95 | F9: 0.014441506 | G9: 2062597.5 | H9: modeled | I9: Reconstructed balance sheet (June 2026 mix scaled to period balances, repriced to the period curve); AFS spread interpolated between calibrated dates | J9: =E9/C9-1 -> -0.76772372 | K9: =IF(OR(F9<meta!$B$19,J9<-meta!$B$21),"High",IF(OR(F9<meta!$B$18,J9<-meta!$B$20),"Moderate","Low")) -> High | L9: =A9&"|"&B9 -> 2025-06-30|ncua_test
A10: 2025-09-30 | B10: internal | C10: 1308763.3 | D10: 0.14618862 | E10: 1112497.7 | F10: 0.13472547 | G10: 2061292 | H10: modeled | I10: Reconstructed balance sheet (June 2026 mix scaled to period balances, repriced to the period curve); AFS spread interpolated between calibrated dates | J10: =E10/C10-1 -> -0.14996266 | K10: =IF(OR(F10<meta!$B$19,J10<-meta!$B$21),"High",IF(OR(F10<meta!$B$18,J10<-meta!$B$20),"Moderate","Low")) -> Low | L10: =A10&"|"&B10 -> 2025-09-30|internal
A11: 2025-09-30 | B11: ncua_test | C11: 568238.04 | D11: 0.063472084 | E11: 174504.56 | F11: 0.021132815 | G11: 2061292 | H11: modeled | I11: Reconstructed balance sheet (June 2026 mix scaled to period balances, repriced to the period curve); AFS spread interpolated between calibrated dates | J11: =E11/C11-1 -> -0.69290237 | K11: =IF(OR(F11<meta!$B$19,J11<-meta!$B$21),"High",IF(OR(F11<meta!$B$18,J11<-meta!$B$20),"Moderate","Low")) -> High | L11: =A11&"|"&B11 -> 2025-09-30|ncua_test
A12: 2025-12-31 | B12: internal | C12: 1516258.8 | D12: 0.16259522 | E12: 1318903.5 | F12: 0.15301318 | G12: 2052971.7 | H12: modeled | I12: Reconstructed balance sheet (June 2026 mix scaled to period balances, repriced to the period curve); AFS fair value calibrated to reported value | J12: =E12/C12-1 -> -0.13015935 | K12: =IF(OR(F12<meta!$B$19,J12<-meta!$B$21),"High",IF(OR(F12<meta!$B$18,J12<-meta!$B$20),"Moderate","Low")) -> Low | L12: =A12&"|"&B12 -> 2025-12-31|internal
A13: 2025-12-31 | B13: ncua_test | C13: 729889.16 | D13: 0.07826928 | E13: 333068.15 | F13: 0.03864105 | G13: 2052971.7 | H13: modeled | I13: Reconstructed balance sheet (June 2026 mix scaled to period balances, repriced to the period curve); AFS fair value calibrated to reported value | J13: =E13/C13-1 -> -0.54367298 | K13: =IF(OR(F13<meta!$B$19,J13<-meta!$B$21),"High",IF(OR(F13<meta!$B$18,J13<-meta!$B$20),"Moderate","Low")) -> High | L13: =A13&"|"&B13 -> 2025-12-31|ncua_test
... A15: 2026-03-31 | B15: ncua_test | C15: 709872.64 | D15: 0.074206829 | E15: 329467.47 | F15: 0.037155481 | G15: 2007273.4 | H15: modeled | I15: Reconstructed balance sheet (June 2026 mix scaled to period balances, repriced to the period curve); AFS spread interpolated between calibrated dates | J15: =E15/C15-1 -> -0.53587806 | K15: =IF(OR(F15<meta!$B$19,J15<-meta!$B$21),"High",IF(OR(F15<meta!$B$18,J15<-meta!$B$20),"Moderate","Low")) -> High | L15: =A15&"|"&B15 -> 2026-03-31|ncua_test
A16: 2026-06-30 | B16: internal | C16: 1655155.3 | D16: 0.1717611 | E16: 1478380.2 | F16: 0.16520553 | H16: modeled | I16: DFCU ALM model v1.0 (hypothetical; model/run_model.py) | J16: =E16/C16-1 -> -0.10680273 | K16: =IF(OR(F16<meta!$B$19,J16<-meta!$B$21),"High",IF(OR(F16<meta!$B$18,J16<-meta!$B$20),"Moderate","Low")) -> Low | L16: =A16&"|"&B16 -> 2026-06-30|internal
A17: 2026-06-30 | B17: ncua_test | C17: 730000.63 | D17: 0.075754651 | E17: 362536.77 | F17: 0.040512636 | H17: modeled | I17: DFCU ALM model v1.0 (hypothetical; model/run_model.py); standardized non-maturity share values (approximation) | J17: =E17/C17-1 -> -0.50337472 | K17: =IF(OR(F17<meta!$B$19,J17<-meta!$B$21),"High",IF(OR(F17<meta!$B$18,J17<-meta!$B$20),"Moderate","Low")) -> Moderate | L17: =A17&"|"&B17 -> 2026-06-30|ncua_test

Sheet assumptions
A1: category | B1: assumption_key | C1: label | D1: value | E1: unit | F1: basis | G1: last_reviewed | H1: owner | I1: bias_up | J1: bias_down | K1: low | L1: high | M1: provenance
A2: deposits | B2: mm_beta_up | C2: Money market beta, rising rates (balance-weighted across 4 tiers) | D2: 0.4272 | E2: beta | F2: Tiered: 0.15 / 0.40 / 0.55 / 0.70. All-shares realized up-cycle beta 2022-2024 was ~0.30 (derived from audited dividend expense); money market assumed above the all-shares figure | G2: 2026-07-21 | H2: Chief Deposit Officer | I2: penalizes | J2: neutral | K2: 0.3204 | L2: 0.534 | M2: modeled
A3: deposits | B3: mm_beta_down | C3: Money market beta, falling rates (balance-weighted) | D3: 0.3408 | E3: beta | F3: Down-cycle 2024 to H1 2026 all-shares realized beta ~0.18 (derived); money market tiers cut faster | G3: 2026-07-21 | H3: Chief Deposit Officer | I3: neutral | J3: flatters | K3: 0.2556 | L3: 0.426 | M3: modeled
A4: deposits | B4: mm_lag_months | C4: Money market repricing lag (balance-weighted) | D4: 1.85 | E4: months | F4: Tier 1 three months; tier 2 two months; tiers 3 and 4 one month | G4: 2026-07-21 | H4: Chief Deposit Officer | I4: flatters | J4: penalizes | K4: 0 | L4: 4 | M4: modeled
A5: deposits | B5: checking_beta | C5: Share draft beta | D5: 0.02 | E5: beta | F5: Consumer checking largely non-interest bearing | G5: 2026-07-21 | H5: Chief Deposit Officer | I5: flatters | J5: neutral | K5: 0 | L5: 0.1 | M5: modeled
A6: deposits | B6: savings_beta | C6: Regular share beta | D6: 0.05 | E6: beta | F6: Administered savings rate near the floor | G6: 2026-07-21 | H6: Chief Deposit Officer | I6: flatters | J6: neutral | K6: 0 | L6: 0.15 | M6: modeled
A7: deposits | B7: nmd_decay_weighted | C7: Non-maturity share decay (balance-weighted annual runoff) | D7: 0.2141 | E7: fraction per year | F7: Checking and savings 14%; money market 20% to 40% by tier; IRA savings 10% | G7: 2026-07-21 | H7: Treasurer / ALM Manager | I7: flatters | J7: penalizes | M7: modeled
A8: deposits | B8: nmd_migration_per_100bp | C8: Money market and savings migration to certificates per +100bp | D8: 0.0248 | E8: fraction of balance by month 12 | F8: Tier-specific 1% to 5% per +100bp; migrated balances earn the 12-month certificate rate | G8: 2026-07-21 | H8: Chief Deposit Officer | I8: penalizes | J8: neutral | K8: 0 | M8: modeled
A9: deposits | B9: cert_offer_spread_12m | C9: 12-month certificate offering rate vs. 1-year CMT | D9: -0.0005 | E9: rate spread | F9: Specials priced near the 1-year Treasury (3.93% at June 30, 2026) | G9: 2026-07-21 | H9: Chief Deposit Officer | I9: neutral | J9: neutral | K9: -0.003 | L9: 0.002 | M9: modeled
A10: deposits | B10: cert_rollover_base | C10: Certificate retention at maturity (base) | D10: 0.85 | E10: fraction | F10: Constant balance sheet assumes full retention in NII; 85% is the liquidity-planning retention | G10: 2026-07-21 | H10: Chief Deposit Officer | I10: neutral | J10: neutral | K10: 0.65 | L10: 0.95 | M10: modeled
A11: deposits | B11: share_cost_runrate | C11: Cost of shares, June 2026 run rate | D11: 0.01477 | E11: rate | F11: Calibrated to H1 2026 dividends ex-giveback / average shares (1.51%) | G11: 2026-07-21 | H11: Chief Financial Officer | I11: neutral | J11: neutral | M11: modeled
A12: valuation | B12: nmd_discount_spread | C12: NMD discount spread over Treasury (alternative funding curve) | D12: 0.0035 | E12: rate spread | F12: FHLB-like marginal funding; drives deposit franchise value in internal NEV | G12: 2026-07-21 | H12: Treasurer / ALM Manager | I12: flatters | J12: penalizes | K12: 0.0015 | L12: 0.0075 | M12: modeled
A13: valuation | B13: cert_discount_spread | C13: Certificate discount spread over Treasury | D13: -0.001 | E13: rate spread | F13: Discount near the certificate offering curve | G13: 2026-07-21 | H13: Treasurer / ALM Manager | I13: neutral | J13: neutral | K13: -0.003 | L13: 0.001 | M13: modeled
A14: valuation | B14: loan_discount_method | C14: Loan discount spreads | E14: method | F14: Spreads solved so a new loan at today's offering rate is worth par; held constant in shocks | G14: 2026-07-21 | H14: Treasurer / ALM Manager | I14: neutral | J14: neutral | M14: modeled
A15: valuation | B15: afs_spread_addon | C15: AFS spread add-on solved to reported fair value | D15: -0.000889 | E15: rate spread | F15: Group spreads (UST 0, agency 15bp, MBS 55bp, CMO 65bp, muni 70bp, SBA 60bp) plus this add-on reproduce the reported AFS fair value | G15: 2026-07-21 | H15: Treasurer / ALM Manager | I15: neutral | J15: neutral | M15: modeled
A16: supervisory | B16: ncua_std_nms_base | C16: NCUA NEV Test: standardized NMS premium at base | D16: 0.01 | E16: fraction of balance | F16: Approximation of NCUA standardized NMS values; confirm against the current NEV Supervisory Test documentation | G16: 2026-07-21 | H16: Treasurer / ALM Manager | I16: penalizes | J16: neutral | M16: modeled
A17: supervisory | B17: ncua_std_nms_shock | C17: NCUA NEV Test: standardized NMS premium after +300bp | D17: 0.05 | E17: fraction of balance | F17: Approximation (see above) | G17: 2026-07-21 | H17: Treasurer / ALM Manager | I17: penalizes | J17: neutral | K17: 0.03 | L17: 0.07 | M17: modeled
A18: loans | B18: heloc_margin | C18: HELOC margin to prime (portfolio average) | D18: -0.0004 | E18: rate spread | F18: Prime 6.75% at June 30, 2026; intro rates amortize into yield (0.26% yield adjustment) | G18: 2026-07-21 | H18: Chief Lending Officer | I18: neutral | J18: neutral | M18: modeled
A19: loans | B19: heloc_floor | C19: HELOC average floor rate | D19: 0.0375 | E19: rate | F19: Floors protect the -300bp scenario | G19: 2026-07-21 | H19: Chief Lending Officer | I19: neutral | J19: flatters | K19: 0.0325 | L19: 0.045 | M19: modeled
A20: loans | B20: heloc_paydown_cpr | C20: HELOC paydown / payoff rate | D20: 0.2 | E20: CPR | F20: Draw-period payments and payoffs | G20: 2026-07-21 | H20: Chief Lending Officer | I20: neutral | J20: neutral | K20: 0.15 | L20: 0.25 | M20: modeled
A21: loans | B21: heloc_utilization | C21: HELOC line utilization | D21: 0.55 | E21: fraction | F21: Unfunded lines ~$1.24B | G21: 2026-07-21 | H21: Chief Lending Officer | I21: neutral | J21: neutral | K21: 0.45 | L21: 0.65 | M21: modeled
A22: loans | B22: auto_cpr | C22: Vehicle loan prepayment (base) | D22: 0.2 | E22: CPR | F22: Roughly 1.5% ABS; 3% CPR per 1% of out-of-market incentive | G22: 2026-07-21 | H22: Chief Lending Officer | I22: neutral | J22: neutral | K22: 0.15 | L22: 0.25 | M22: modeled
A23: loans | B23: mortgage_cpr_base | C23: Portfolio fixed mortgage prepayment (base, out of the money) | D23: 0.05 | E23: CPR | F23: Rate lock-in: 4.30% book vs. 6.49% market; 3.5% turnover floor | G23: 2026-07-21 | H23: Chief Lending Officer | I23: flatters | J23: penalizes | K23: 0.035 | L23: 0.08 | M23: modeled
A24: loans | B24: mortgage_refi_sensitivity | C24: Mortgage refinancing response | D24: 0.12 | E24: CPR per 1% incentive above 0.5% | F24: Standard S-curve approximation | G24: 2026-07-21 | H24: Chief Lending Officer | I24: neutral | J24: penalizes | K24: 0.06 | L24: 0.18 | M24: modeled
A25: loans | B25: cre_cpr | C25: CRE prepayment (base) | D25: 0.07 | E25: CPR | F25: Prepayment penalties limit refinancing | G25: 2026-07-21 | H25: Chief Lending Officer | I25: neutral | J25: neutral | K25: 0.035 | L25: 0.105 | M25: modeled
A26: loans | B26: cre_reset_margin | C26: CRE reset margin over 5-year CMT | D26: 0.0225 | E26: rate spread | F26: Resets spread evenly over the next 60 months | G26: 2026-07-21 | H26: Chief Lending Officer | I26: neutral | J26: neutral | K26: 0.02 | L26: 0.0275 | M26: modeled
